Workbook
Name avc_indicator: SRP!$C$3
Name Commission_Uplift_Factor: [1]SRP!$D$65
Name Commission_Uplift_Factor: SRP!$D$65
Name Contributions_per_year: [1]SRP!$G$61
Name Contributions_per_year: SRP!$G$61
Name DIY_Chrge_Table: 'Investment Strategy Funds'!$T$4:$W$17
Name DIY_ExtManChrge_CurrentFunds: [1]SRP!$Q$6
Name DIY_ExtManChrge_CurrentFunds: SRP!$T$6
Name DIY_ExtManChrge_FuturePremiums: [1]SRP!$Q$15
Name DIY_ExtManChrge_FuturePremiums: SRP!$T$15
Name DIY_ExtManChrge_SP: [1]SRP!$Q$11
Name DIY_ExtManChrge_SP: SRP!$T$11
Name DIY_GteeChrge_CurrentFunds: [1]SRP!$Q$8
Name DIY_GteeChrge_CurrentFunds: SRP!$T$8
Name DIY_GteeChrge_FuturePremiums: [1]SRP!$Q$16
Name DIY_GteeChrge_FuturePremiums: SRP!$T$16
Name DIY_GteeChrge_SP: [1]SRP!$Q$12
Name DIY_GteeChrge_SP: SRP!$T$12
Name DIY_RateOfReturn_CurrentFunds: [1]SRP!$Q$5
Name DIY_RateOfReturn_CurrentFunds: SRP!$T$5
Name DIY_RateOfReturn_FuturePremiums: [1]SRP!$Q$14
Name DIY_RateOfReturn_FuturePremiums: SRP!$T$14
Name DIY_RateofReturn_SP: [1]SRP!$Q$10
Name DIY_RateofReturn_SP: SRP!$T$10
Name External_Man_Chrge: [1]Parameters!$C$38:$I$48
Name External_Man_Chrge: Parameters!$C$47:$I$60
Name Gtee_Chrge: [1]Parameters!$C$31:$D$34
Name Gtee_Chrge: Parameters!$C$40:$D$43
Name Investment_Strategy: [1]SRP!$C$6
Name Investment_Strategy: SRP!$C$6
Name Investment_Strategy_Sub1: [1]SRP!$C$7
Name Investment_Strategy_Sub1: SRP!$C$7
Name Investment_Strategy_Sub2: [1]SRP!$C$8
Name Investment_Strategy_Sub2: SRP!$C$8
Name Max_Contrib_Escalation: [1]SRP!$G$62
Name Max_Contrib_Escalation: SRP!$G$62
Name Max_InvReturn: [1]SRP!$D$78
Name Max_InvReturn: SRP!$D$78
Name NS_AP_Bal: 'Investment Strategy Funds'!$D$21:$G$24
Name NS_AP_Dyn: 'Investment Strategy Funds'!$D$26:$G$28
Name NS_AP_Opp: 'Investment Strategy Funds'!$D$30:$G$32
Name NS_DIS: 'Investment Strategy Funds'!$D$34:$G$40
Name NS_LC_Bal: 'Investment Strategy Funds'!$D$4:$G$7
Name NS_LC_Dyn: 'Investment Strategy Funds'!$D$9:$G$13
Name NS_LC_Opp: 'Investment Strategy Funds'!$D$15:$G$19
Name Opening_Fund_Value: [1]SRP!$D$58
Name Opening_Fund_Value: SRP!$D$58
Name Premium_Month1_Flag: [1]SRP!$I$60
Name Premium_Month1_Flag: SRP!$I$60
Name Product_Type: [1]SRP!$C$5
Name Product_Type: SRP!$C$5
Name Product_Version: [1]SRP!$C$4
Name Product_Version: SRP!$C$4
Name Rates_of_Return: [1]Parameters!$K$38:$L$48
Name Rates_of_Return: Parameters!$K$47:$L$60
Name S_DIS: 'Investment Strategy Funds'!$L$21:$O$23
Name S_LC_Bal: 'Investment Strategy Funds'!$L$4:$O$7
Name S_LC_Dyn: 'Investment Strategy Funds'!$L$9:$O$11
Name S_LC_Opp: 'Investment Strategy Funds'!$L$15:$O$17
Name Single_Equivalence_Charge: [1]SRP!$BE$86

Sheet Version Control
C3: Date | D3: Version | E3: Change | F3: By | G3: Reviewed By
C4: 45806 | D4: V1.0 | E4: Fund Charges Update | F4: Gearóid Hughes | G4: Hugh Gannon
C5: 45814 | D5: V1.1 | E5: Back to old fund charges | F5: Hugh Gannon
C6: 45819 | D6: V2.0 | E6: Fund Charges Update | F6: Gearóid Hughes | G6: Hugh Gannon
C7: 46000 | D7: V3.0 | E7: AVC PRSA Update | F7: Gearóid Hughes | G7: Hugh Gannon
C8: 46080 | D8: V3.1 | E8: Updated to add the new HSBC funds, detailed change notes in email | F8: Gearóid Hughes
C9: 46080 | D9: V3.2 | E9: Updated parameters for AMC and Contribution charge | F9: Gearóid Hughes
C10: 46080 | D10: V3.3 | E10: Updated the Commission Structure | F10: Gearóid Hughes
C11: 46080 | D11: V4 | E11: Sign-off on V3 Changes | F11: Gearóid Hughes | G11: Hugh Gannon
C12: 46141 | D12: V5 | E12: Updated prescribed assumptions | F12: Gearóid Hughes

Sheet Overview
A1: Overview
A3: Cell Color Key | B3: Cell Color Key | C3: Description
C4: Product and Fund Parameters
C5: Customer specific inputs
C6: Formulas
C7: A flag used where a change in formula occurs during the projection
C8: Regulatory/ ASP inputs
C9: Other hardcoded Numbers
C10: Summary tables
A14: User Guide | B14: Step | C14: Description
B15: 1 | C15: Update Customer specific inputs on SRP tab
A18: Sheet Description | B18: Sheet Name | C18: Description | D18: HyperLink
B19: Overview | C19: In this tab: (1.) The key information about the EUC is documented. (2.) The user instructions for updating this model is documented. (3.) The purpose of each sheet is also documented. | D19: =B19 -> Overview
B20: Parameters | C20: This tab contains: - Product specific parameters - Fund specific parameters - Regulatory specific inputs. This tab should only be updated if there are changes to any of the above. | D20: =B20 -> Parameters
B21: Mortality Table | C21: This tab contains the mortality tables that are used to determine the qx used in calculating the annuity rates | D21: =B21 -> Mortality Table
B22: Irish Life Quote | C22: This tab provides the annuity rate to use if term to maturity is less than 5 years | D22: =B22 -> Irish Life Quote
B23: Investment Strategies | C23: This tab contains: - The Fund Glidepaths - Rate of Return -Charges for all defined investment stategies | D23: =B23 -> Investment Strategies
B24: SRP | C24: This tab projection the PRSA over the lifetime of the policy. - Customer specifc inputs should be updated here | D24: =B24 -> SRP
B25: Investment Strategy Funds | C25: This tab contains fund based and guarantee charges for all funds within each investment strategy | D25: =B25 -> Investment Strategy Funds
B26: Fund Based Charges Text | C26: This tab contains the prescribed text to use for each investment strategy which is subsequently used in the 2 following tabs | D26: =B26 -> Fund Based Charges Text
B27: Initial SRP doc Inputs | C27: This tab contains the inputs for the initial SRP document | D27: =B27 -> Initial SRP doc Inputs
B28: InForce SRP doc Inputs | C28: This tab contains the inputs for the existing SRP document | D28: =B28 -> InForce SRP doc Inputs

Sheet Parameters
F5: Commission
C6: Product Version | D6: Type | F6: SP Upfront | G6: RP Upfront | H6: Ongoing | I6: Admin Charge | J6: Total AMC
C7: A | D7: 1. Non-Standard | E7: =C7&"_"&D7 -> A_1. Non-Standard | F7: 0 | G7: N/A | H7: 0.0075 | I7: 0.0115 | J7: 1.30% - 2.25%
C8: A | D8: 2. Non-Standard | E8: =C8&"_"&D8 -> A_2. Non-Standard | F8: 0.01 | G8: 0.4% * Term, max 5% | H8: 0.006 | I8: 0.0115 | J8: 1.30% - 2.25%
C9: A | D9: 3. Non-Standard | E9: =C9&"_"&D9 -> A_3. Non-Standard | F9: 0.02 | G9: 0.8% * Term, max 10% | H9: 0.005 | I9: 0.0115 | J9: 1.30% - 2.25%
C10: A | D10: 4. Non-Standard | E10: =C10&"_"&D10 -> A_4. Non-Standard | F10: 0.03 | G10: 1% * Term, max 15% | H10: 0.0035 | I10: 0.0115 | J10: 1.30% - 2.25%
C11: A | D11: 5. Non-Standard | E11: =C11&"_"&D11 -> A_5. Non-Standard | F11: 0.04 | G11: 1.3% * Term, max 20% | H11: 0.0025 | I11: 0.0115 | J11: 1.30% - 2.25%
C12: B | D12: 1. Non-Standard | E12: =C12&"_"&D12 -> B_1. Non-Standard | F12: 0 | G12: 0 | H12: 0.005 | I12: 0.009 | J12: 1.05% - 2.00%
C13: B | D13: 2. Non-Standard | E13: =C13&"_"&D13 -> B_2. Non-Standard | F13: 0.01 | G13: 0.4% * Term, max 5% | H13: 0.0035 | I13: 0.009 | J13: 1.05% - 2.00%
C14: B | D14: 3. Non-Standard | E14: =C14&"_"&D14 -> B_3. Non-Standard | F14: 0.035 | G14: 0.8% * Term, max 10% | H14: 0.0025 | I14: 0.009 | J14: 1.05% - 2.00%
C15: B | D15: 4. Non-Standard | E15: =C15&"_"&D15 -> B_4. Non-Standard | F15: 0.03 | G15: 1% * Term, max 15% | H15: 0.001 | I15: 0.009 | J15: 1.30% - 2.25%
C16: B | D16: 5. Non-Standard | E16: =C16&"_"&D16 -> B_5. Non-Standard | F16: 0.04 | G16: 1.3% * Term, max 20% | H16: 0 | I16: 0.009 | J16: 1.30% - 2.25%
C17: C | D17: 1. Non-Standard | E17: =C17&"_"&D17 -> C_1. Non-Standard | F17: 0 | G17: 0 | H17: 0.0025 | I17: 0.0065 | J17: 0.85% - 1.80%
C18: C | D18: 2. Non-Standard | E18: =C18&"_"&D18 -> C_2. Non-Standard | F18: 0.01 | G18: 0.4% * Term, max 5% | H18: 0.0012 | I18: 0.0065 | J18: 0.85% - 1.80%
C19: C | D19: 3. Non-Standard | E19: =C19&"_"&D19 -> C_3. Non-Standard | F19: 0.02 | G19: 0.8% * Term, max 10% | H19: 0 | I19: 0.0065 | J19: 0.85% - 1.80%
C20: D | D20: 1. Non-Standard | E20: =C20&"_"&D20 -> D_1. Non-Standard | F20: 0 | G20: 0 | H20: 0 | I20: 0.004 | J20: 0.55% - 1.50%
C21: E | D21: 1. Standard | E21: =C21&"_"&D21 -> E_1. Standard | F21: 0 | G21: 0 | H21: 0.0025 | I21: 0.007
C22: E | D22: 2. Standard | E22: =C22&"_"&D22 -> E_2. Standard | F22: 0.01 | G22: 0.4% * Term, max 5% | H22: 0.0012 | I22: 0.007
C23: E | D23: 3. Standard | E23: =C23&"_"&D23 -> E_3. Standard | F23: 0.02 | G23: 0.8% * Term, max 10% | H23: 0 | I23: 0.007
C24: F | D24: 1. Non-Standard | E24: =C24&"_"&D24 -> F_1. Non-Standard | F24: 0 | G24: N/A | H24: 0.01 | I24: 0.014
C25: F | D25: 2. Non-Standard | E25: =C25&"_"&D25 -> F_2. Non-Standard | F25: 0.01 | G25: 0.4% * Term, max 5% | H25: 0.0085 | I25: 0.014
C26: F | D26: 3. Non-Standard | E26: =C26&"_"&D26 -> F_3. Non-Standard | F26: 0.02 | G26: 0.8% * Term, max 10% | H26: 0.0075 | I26: 0.014
C27: F | D27: 4. Non-Standard | E27: =C27&"_"&D27 -> F_4. Non-Standard | F27: 0.03 | G27: 1% * Term, max 15% | H27: 0.006 | I27: 0.014
C28: F | D28: 5. Non-Standard | E28: =C28&"_"&D28 -> F_5. Non-Standard | F28: 0.04 | G28: 1.3% * Term, max 20% | H28: 0.005 | I28: 0.014
C31: Single Premium Size | D31: Allocation Charge | G31: Regular Premium Size | H31: Allocation Charge
C32: Up €10,000 | D32: 0.02 | G32: Up to €100 per month | H32: 0.02
C33: €10,000 and over | D33: 0 | G33: €100 and over p.m. | H33: 0
C39: Guarnatee Charge
C40: Chosen Fund(s) | D40: GMAB Charge p.a. | G40: Assumed Rates of Return
C41: Allianz Strategy Select 30 | D41: 0.0065 | G41: Equities | H41: 0.072 | I41: =H41*0.75+H42*0.25 -> 0.064625 | J41: 2025 Growth Rates from:
C42: Allianz Strategy Select 50 | D42: 0.0075 | G42: Fixed Income | H42: 0.0425 | J42: ASP PRSA-2 V1.14 final.pdf
C43: Allianz Strategy Select 75 | D43: 0.0085 | G43: Cash | H43: 0.032
E45: Fund Charge Values from:
C46: External Fund Charge | E46: AGL historic TERs and Calc or TER Ranges.xlsx | K46: Rates of Return
C47: Fund Name | D47: ISIN | E47: Fund Manager Charge | F47: Bounded Charge | G47: Lower Bound | H47: Upper Bound | I47: Charge Value 2025 | K47: Fund Name | L47: Rate of return
C48: Allianz Strategy Select 30 | D48: LU1901058732 | E48: 0.0025 | F48: No | G48: N/A | H48: N/A | I48: 0.0025 | K48: Allianz Strategy Select 30 | L48: =0.3*H41+0.7*H42 -> 0.05135
C49: Allianz Strategy Select 50 | D49: LU1462180164 | E49: 0.0025 | F49: No | G49: N/A | H49: N/A | I49: 0.0025 | K49: Allianz Strategy Select 50 | L49: =0.5*H41+0.5*H42 -> 0.05725
C50: Allianz Strategy Select 75 | D50: LU1462191526 | E50: 0.0025 | F50: No | G50: N/A | H50: N/A | I50: 0.0025 | K50: Allianz Strategy Select 75 | L50: =0.75*H41+0.25*H42 -> 0.064625
C51: Allianz Best Styles Global Equity SRI | D51: LU2437558831 | E51: =H51 -> 0.005 | F51: Yes | G51: 0.0043 | H51: 0.005 | I51: 0.0045 | K51: Allianz Best Styles Global Equity SRI | L51: =H41 -> 0.072
C52: Allianz Advanced Fixed Income Short Duration | D52: LU1328247389 | E52: =H52 -> 0.0024 | F52: Yes | G52: 0.0022 | H52: 0.0024 | I52: 0.0022 | K52: Allianz Advanced Fixed Income Short Duration | L52: =$H$42 -> 0.0425
C53: Allianz Advanced Fixed Income Euro | D53: LU2190101332 | E53: =H53 -> 0.0028 | F53: Yes | G53: 0.0026 | H53: 0.0028 | I53: 0.0027 | K53: Allianz Advanced Fixed Income Euro | L53: =$H$42 -> 0.0425
C54: Allianz Dynamic Multi Asset Strategy SRI 75 | D54: LU3068734824 | E54: =H54 -> 0.0072 | F54: Yes | G54: 0.0058 | H54: 0.0072 | I54: 0.0065 | K54: Allianz Dynamic Multi Asset Strategy SRI 75 | L54: =0.75*H41+0.25*H42 -> 0.064625
C55: Allianz Dynamic Multi Asset Strategy SRI 50 | D55: LU3068734667 | E55: =H55 -> 0.0067 | F55: Yes | G55: 0.0053 | H55: 0.0067 | I55: 0.0059 | K55: Allianz Dynamic Multi Asset Strategy SRI 50 | L55: =0.5*H41+0.5*H42 -> 0.05725
C56: Allianz Dynamic Multi Asset Strategy SRI 15 | D56: LU3068734238 | E56: =H56 -> 0.0059 | F56: Yes | G56: 0.0045 | H56: 0.0059 | I56: 0.0049 | K56: Allianz Dynamic Multi Asset Strategy SRI 15 | L56: =0.15*H41+0.85*H42 -> 0.046925
C57: HSBC EURO STOXX 50 UCITS ETF | D57: IE000MWUQBJ0 | E57: 0.0005 | F57: No | G57: N/A | H57: N/A | I57: 0.0005 | K57: HSBC EURO STOXX 50 UCITS ETF | L57: =H41*1+H42*0+H43*0 -> 0.072
C58: HSBC MSCI World UCITS ETF | D58: IE000UQND7H4 | E58: 0.0015 | F58: No | G58: N/A | H58: N/A | I58: 0.0015 | K58: HSBC MSCI World UCITS ETF | L58: =H41*1+H42*0+H43*0 -> 0.072
C59: HSBC S&P 500 UCITS ETF | D59: IE000JZ473P7 | E59: 0.0009 | F59: No | G59: N/A | H59: N/A | I59: 0.0009 | K59: HSBC S&P 500 UCITS ETF | L59: =H41*1+H42*0+H43*0 -> 0.072
C60: Allianz Euro Cash | D60: LU2575878199 | E60: 0.0018 | F60: Yes | G60: 0.0016 | H60: 0.0018 | I60: 0.0016 | K60: Allianz Euro Cash | L60: =$H$43 -> 0.032
E61: For use in Projection Calculations | G61: For use in dynamic paragraph in SRP Charges section | I61: For use in SRP table
E62: Project at max

Sheet Mortality Table
D2: =SRP_Male_qx_adj -> 0.42 | E2: =SRP_Female_qx_adj -> 0.5
A4: AgeExact | B4: ILT15 (Males)_base | C4: ILT15 (Females)_base | D4: ILT15 (Males)_adjusted | E4: ILT15 (Females)_adjusted
A5: 0 | B5: 0 | C5: 0 | D5: =B5*D$2 -> 0 | E5: =C5*E$2 -> 0
A6: 16 | B6: 0 | C6: 0 | D6: =B6*D$2 -> 0 | E6: =C6*E$2 -> 0
A7: 17 | B7: 0 | C7: 0 | D7: =B7*D$2 -> 0 | E7: =C7*E$2 -> 0
A8: 18 | B8: 0 | C8: 0 | D8: =B8*D$2 -> 0 | E8: =C8*E$2 -> 0
A9: 19 | B9: 0 | C9: 0 | D9: =B9*D$2 -> 0 | E9: =C9*E$2 -> 0
A10: 20 | B10: 0.00103 | C10: 0.00033 | D10: =B10*D$2 -> 0.0004326 | E10: =C10*E$2 -> 0.000165
A11: 21 | B11: 0.00109 | C11: 0.00031 | D11: =B11*D$2 -> 0.0004578 | E11: =C11*E$2 -> 0.000155
A12: 22 | B12: 0.00113 | C12: 0.0003 | D12: =B12*D$2 -> 0.0004746 | E12: =C12*E$2 -> 0.00015
A13: 23 | B13: 0.00112 | C13: 0.0003 | D13: =B13*D$2 -> 0.0004704 | E13: =C13*E$2 -> 0.00015
A14: 24 | B14: 0.00107 | C14: 0.00031 | D14: =B14*D$2 -> 0.0004494 | E14: =C14*E$2 -> 0.000155
A15: 25 | B15: 0.00101 | C15: 0.00031 | D15: =B15*D$2 -> 0.0004242 | E15: =C15*E$2 -> 0.000155
A16: 26 | B16: 0.00095 | C16: 0.00032 | D16: =B16*D$2 -> 0.000399 | E16: =C16*E$2 -> 0.00016
... A109: 119 | B109: 0.51026 | C109: 0.45654 | D109: =B109*D$2 -> 0.2143092 | E109: =C109*E$2 -> 0.22827
A110: 120 | B110: 1 | C110: 1 | D110: 1 | E110: 1
A111: =A110+1 -> 121 | B111: 1 | C111: 1 | D111: 1 | E111: 1
A112: =A111+1 -> 122 | B112: 1 | C112: 1 | D112: 1 | E112: 1
A113: =A112+1 -> 123 | B113: 1 | C113: 1 | D113: 1 | E113: 1
A114: =A113+1 -> 124 | B114: 1 | C114: 1 | D114: 1 | E114: 1
A115: =A114+1 -> 125 | B115: 1 | C115: 1 | D115: 1 | E115: 1
A116: =A115+1 -> 126 | B116: 1 | C116: 1 | D116: 1 | E116: 1
A117: =A116+1 -> 127 | B117: 1 | C117: 1 | D117: 1 | E117: 1
A118: =A117+1 -> 128 | B118: 1 | C118: 1 | D118: 1 | E118: 1
A119: =A118+1 -> 129 | B119: 1 | C119: 1 | D119: 1 | E119: 1
A120: =A119+1 -> 130 | B120: 1 | C120: 1 | D120: 1 | E120: 1
A121: =A120+1 -> 131 | B121: 1 | C121: 1 | D121: 1 | E121: 1
A122: =A121+1 -> 132 | B122: 1 | C122: 1 | D122: 1 | E122: 1
... A153: =A152+1 -> 163 | B153: 1 | C153: 1 | D153: 1 | E153: 1

Sheet Irish Life Quote
B1: https://www.pensionplanetinteractive.ie/ppi/public/pensionChoicePersonalDetails.action
S8: Rate | T8: 0.05129
S9: Factor per month | T9: =12/T8 -> 233.96374

Sheet Investment Strategies
D1: Rate of Return | E1: =VLOOKUP(E$4,Rates_of_Return,2,FALSE) -> 0.0425 | F1: =VLOOKUP(F$4,Rates_of_Return,2,FALSE) -> 0.046925 | G1: =VLOOKUP(G$4,Rates_of_Return,2,FALSE) -> 0.064625 | H1: =VLOOKUP(H$4,Rates_of_Return,2,FALSE) -> 0.072 | U1: Rate of Return | V1: =VLOOKUP(V$4,Rates_of_Return,2,FALSE) -> 0.064625 | W1: =VLOOKUP(W$4,Rates_of_Return,2,FALSE) -> 0.05135 | X1: =VLOOKUP(X$4,Rates_of_Return,2,FALSE) -> 0.0425 | AK1: Rate of Return | AL1: =VLOOKUP(AL$4,Rates_of_Return,2,FALSE) -> 0.064625 | AM1: =VLOOKUP(AM$4,Rates_of_Return,2,FALSE) -> 0.05135 | AN1: =VLOOKUP(AN$4,Rates_of_Return,2,FALSE) -> 0.0425 | BA1: Rate of Return | BB1: =VLOOKUP(BB$4,Rates_of_Return,2,FALSE) -> 0.0425 | BC1: =VLOOKUP(BC$4,Rates_of_Return,2,FALSE) -> 0.046925 | BD1: =VLOOKUP(BD$4,Rates_of_Return,2,FALSE) -> 0.064625 | BE1: =VLOOKUP(BE$4,Rates_of_Return,2,FALSE) -> 0.072 | BF1: =VLOOKUP(BF$4,Rates_of_Return,2,FALSE) -> 0.064625 | BG1: =VLOOKUP(BG$4,Rates_of_Return,2,FALSE) -> 0.05725 | BH1: =VLOOKUP(BH$4,Rates_of_Return,2,FALSE) -> 0.05135
D2: External Management Charge | E2: =VLOOKUP(E$4,External_Man_Chrge,3,FALSE) -> 0.0024 | F2: =VLOOKUP(F$4,External_Man_Chrge,3,FALSE) -> 0.0059 | G2: =VLOOKUP(G$4,External_Man_Chrge,3,FALSE) -> 0.0072 | H2: =VLOOKUP(H$4,External_Man_Chrge,3,FALSE) -> 0.005 | U2: External Management Charge | V2: =VLOOKUP(V$4,External_Man_Chrge,3,FALSE) -> 0.0025 | W2: =VLOOKUP(W$4,External_Man_Chrge,3,FALSE) -> 0.0025 | X2: =VLOOKUP(X$4,External_Man_Chrge,3,FALSE) -> 0.0024 | AK2: External Management Charge | AL2: =VLOOKUP(AL$4,External_Man_Chrge,3,FALSE) -> 0.0025 | AM2: =VLOOKUP(AM$4,External_Man_Chrge,3,FALSE) -> 0.0025 | AN2: =VLOOKUP(AN$4,External_Man_Chrge,3,FALSE) -> 0.0024 | BA2: External Management Charge | BB2: =VLOOKUP(BB$4,External_Man_Chrge,3,FALSE) -> 0.0024 | BC2: =VLOOKUP(BC$4,External_Man_Chrge,3,FALSE) -> 0.0059 | BD2: =VLOOKUP(BD$4,External_Man_Chrge,3,FALSE) -> 0.0072 | BE2: =VLOOKUP(BE$4,External_Man_Chrge,3,FALSE) -> 0.005 | BF2: =VLOOKUP(BF$4,External_Man_Chrge,3,FALSE) -> 0.0025 | BG2: =VLOOKUP(BG$4,External_Man_Chrge,3,FALSE) -> 0.0025 | BH2: =VLOOKUP(BH$4,External_Man_Chrge,3,FALSE) -> 0.0025
A3: Non-Standard | D3: Guarantee Charge | E3: =IFERROR(VLOOKUP(E$4,Gtee_Chrge,2,FALSE),) -> 0 | F3: =IFERROR(VLOOKUP(F$4,Gtee_Chrge,2,FALSE),) -> 0 | G3: =IFERROR(VLOOKUP(G$4,Gtee_Chrge,2,FALSE),) -> 0 | H3: =IFERROR(VLOOKUP(H$4,Gtee_Chrge,2,FALSE),) -> 0 | U3: Guarantee Charge | V3: =IFERROR(VLOOKUP(V$4,Gtee_Chrge,2,FALSE),) -> 0.0085 | W3: =IFERROR(VLOOKUP(W$4,Gtee_Chrge,2,FALSE),) -> 0.0065 | X3: =IFERROR(VLOOKUP(X$4,Gtee_Chrge,2,FALSE),) -> 0 | AH3: Standard | AK3: Guarantee Charge | AL3: =IFERROR(VLOOKUP(AL$4,Gtee_Chrge,2,FALSE),) -> 0.0085 | AM3: =IFERROR(VLOOKUP(AM$4,Gtee_Chrge,2,FALSE),) -> 0.0065 | AN3: =IFERROR(VLOOKUP(AN$4,Gtee_Chrge,2,FALSE),) -> 0 | BA3: Guarantee Charge | BB3: =IFERROR(VLOOKUP(BB$4,Gtee_Chrge,2,FALSE),) -> 0 | BC3: =IFERROR(VLOOKUP(BC$4,Gtee_Chrge,2,FALSE),) -> 0 | BD3: =IFERROR(VLOOKUP(BD$4,Gtee_Chrge,2,FALSE),) -> 0 | BE3: =IFERROR(VLOOKUP(BE$4,Gtee_Chrge,2,FALSE),) -> 0 | BF3: =IFERROR(VLOOKUP(BF$4,Gtee_Chrge,2,FALSE),) -> 0.0085 | BG3: =IFERROR(VLOOKUP(BG$4,Gtee_Chrge,2,FALSE),) -> 0.0075 | BH3: =IFERROR(VLOOKUP(BH$4,Gtee_Chrge,2,FALSE),) -> 0.0065
A4: Strategy | B4: Sub Category | D4: Months to retirement | E4: Allianz Advanced Fixed Income Short Duration | F4: Allianz Dynamic Multi Asset Strategy SRI 15 | G4: Allianz Dynamic Multi Asset Strategy SRI 75 | H4: Allianz Best Styles Global Equity SRI | J4: Average Rate of Return | K4: Monthly rate of Return | L4: Guarantee Status | M4: Average Guarantee Charge | N4: Monthly Guarantee charge | O4: Average External AMC | P4: Monthly External AMC | R4: Stragegy | S4: Sub Category | U4: Months to retirement | V4: ='[2]AP Balanced'!R$1 -> Allianz Strategy Select 75 | W4: ='[2]AP Balanced'!S$1 -> Allianz Strategy Select 30 | X4: ='[2]AP Balanced'!T$1 -> Allianz Advanced Fixed Income Short Duration | Z4: Average Rate of Return | AA4: Monthly rate of Return | AB4: Guarantee Status | AC4: Average Guarantee Charge | AD4: Monthly Guarantee charge | AE4: Average External AMC | AF4: Monthly External AMC | AH4: Stragegy | AI4: Sub Category | AK4: Months to retirement | AL4: =[2]Standard_Balanced!R$1 -> Allianz Strategy Select 75 | AM4: =[2]Standard_Balanced!S$1 -> Allianz Strategy Select 30 | AN4: =[2]Standard_Balanced!T$1 -> Allianz Advanced Fixed Income Short Duration | AP4: Average Rate of Return | AQ4: Monthly rate of Return | AR4: Guarantee Status | AS4: Average Guarantee Charge | AT4: Monthly Guarantee charge | AU4: Average External AMC | AV4: Monthly External AMC | AX4: Stragegy | AY4: Sub Category | BA4: Month | BB4: ='[2]NonStandard DIS'!R$1 -> Allianz Advanced Fixed Income Short Duration | BC4: ='[2]NonStandard DIS'!S$1 -> Allianz Dynamic Multi Asset Strategy SRI 15 | BD4: ='[2]NonStandard DIS'!T$1 -> Allianz Dynamic Multi Asset Strategy SRI 75 | BE4: ='[2]NonStandard DIS'!U$1 -> Allianz Best Styles Global Equity SRI | BF4: ='[2]NonStandard DIS'!V$1 -> Allianz Strategy Select 75 | BG4: ='[2]NonStandard DIS'!W$1 -> Allianz Strategy Select 50 | BH4: ='[2]NonStandard DIS'!X$1 -> Allianz Strategy Select 30 | BJ4: Average Rate of Return | BK4: Monthly rate of Return | BL4: Guarantee Status | BM4: Average Guarantee Charge | BN4: Monthly Guarantee charge | BO4: Average External AMC | BP4: Monthly External AMC
A5: Lifecycle | B5: Balanced | C5: =A5&"_"&B5&"_"&D5 -> Lifecycle_Balanced_540 | D5: 540 | E5: =VLOOKUP($D5,'[2]LC Balanced'!$Q$2:$U$542,2,FALSE) -> 0 | F5: =VLOOKUP($D5,'[2]LC Balanced'!$Q$2:$U$542,3,FALSE) -> 0.149 | G5: =VLOOKUP($D5,'[2]LC Balanced'!$Q$2:$U$542,4,FALSE) -> 0.851 | H5: =VLOOKUP($D5,'[2]LC Balanced'!$Q$2:$U$542,5,FALSE) -> 0 | I5: =SUM(E5:H5) -> 1 | J5: =SUMPRODUCT($E$1:$H$1,E5:H5) -> 0.0619877 | K5: =(1+J5)^(1/12)-1 -> 0.0050244421 | L5: 0 | M5: =IF($L5=0,0,SUMPRODUCT($E$3:$H$3,E5:H5)) -> 0 | N5: =1-(1-M5)^(1/12) -> 0 | O5: =SUMPRODUCT($E$2:$H$2,E5:H5) -> 0.0070063 | P5: =1-(1-O5)^(1/12) -> 0.00058574167 | R5: Autopilot | S5: Balanced | T5: =R5&"_"&S5&"_"&U5 -> Autopilot_Balanced_540 | U5: 540 | V5: =VLOOKUP($U5,'[2]AP Balanced'!$Q$1:$T$542,2,FALSE) -> 0.77777778 | W5: =VLOOKUP($U5,'[2]AP Balanced'!$Q$1:$T$542,3,FALSE) -> 0.22222222 | X5: =VLOOKUP($U5,'[2]AP Balanced'!$Q$1:$T$542,4,FALSE) -> 0 | Y5: =SUM(V5:X5) -> 1 | Z5: =SUMPRODUCT($V$1:$X$1,V5:X5) -> 0.061675 | AA5: =(1+Z5)^(1/12)-1 -> 0.0049997782 | AB5: 1 | AC5: =IF($AB5=0,0,SUMPRODUCT($V$3:$X$3,V5:X5)) -> 0.0080555556 | AD5: =1-(1-AC5)^(1/12) -> 0.00067378764 | AE5: =SUMPRODUCT($V$2:$X$2,V5:X5) -> 0.0025 | AF5: =1-(1-AE5)^(1/12) -> 0.00020857243 | AH5: Lifecycle | AI5: Balanced | AJ5: =AH5&"_"&AI5&"_"&AK5 -> Lifecycle_Balanced_540 | AK5: 540 | AL5: =VLOOKUP($U5,[2]Standard_Balanced!$Q$1:$T$542,2,FALSE) -> 0.77777778 | AM5: =VLOOKUP($U5,[2]Standard_Balanced!$Q$1:$T$542,3,FALSE) -> 0.22222222 | AN5: =VLOOKUP($U5,[2]Standard_Balanced!$Q$1:$T$542,4,FALSE) -> 0 | AO5: =SUM(AL5:AN5) -> 1 | AP5: =SUMPRODUCT($AL$1:$AN$1,AL5:AN5) -> 0.061675 | AQ5: =(1+AP5)^(1/12)-1 -> 0.0049997782 | AR5: 0 | AS5: =IF(AR5=0,0,SUMPRODUCT($AL$3:$AN$3,AL5:AN5)) -> 0 | AT5: =1-(1-AS5)^(1/12) -> 0 | AU5: =SUMPRODUCT($AL$2:$AN$2,AL5:AN5) -> 0.0025 | AV5: =1-(1-AU5)^(1/12) -> 0.00020857243 | AX5: DIS | AY5: Non-Standard | AZ5: =AX5&"_"&AY5&"_"&BA5 -> DIS_Non-Standard_540 | BA5: 540 | BB5: =VLOOKUP($BA5,'[2]NonStandard DIS'!$Q$1:$X$542,2,FALSE) -> 0 | BC5: =VLOOKUP($BA5,'[2]NonStandard DIS'!$Q$1:$X$542,3,FALSE) -> 0 | BD5: =VLOOKUP($BA5,'[2]NonStandard DIS'!$Q$1:$X$542,4,FALSE) -> 0.308 | BE5: =VLOOKUP($BA5,'[2]NonStandard DIS'!$Q$1:$X$542,5,FALSE) -> 0.692 | BF5: =VLOOKUP($BA5,'[2]NonStandard DIS'!$Q$1:$X$542,6,FALSE) -> 0 | BG5: =VLOOKUP($BA5,'[2]NonStandard DIS'!$Q$1:$X$542,7,FALSE) -> 0 | BH5: =VLOOKUP($BA5,'[2]NonStandard DIS'!$Q$1:$X$542,8,FALSE) -> 0 | BI5: =SUM(BB5:BH5) -> 1 | BJ5: =SUMPRODUCT($BB$1:$BH$1,BB5:BH5) -> 0.0697285 | BK5: =(1+BJ5)^(1/12)-1 -> 0.0056328785 | BL5: 0 | BM5: =IF(BL5=0,0,SUMPRODUCT($BB$3:$BH$3,BB5:BH5)) -> 0 | BN5: =(1+BM5)^(1/12)-1 -> 0 | BO5: =SUMPRODUCT($BB$2:$BH$2,BB5:BH5) -> 0.0056776 | BP5: =(1+BO5)^(1/12)-1 -> 0.00047190658
A6: Lifecycle | B6: Balanced | C6: =A6&"_"&B6&"_"&D6 -> Lifecycle_Balanced_539 | D6: 539 | E6: =VLOOKUP($D6,'[2]LC Balanced'!$Q$2:$U$542,2,FALSE) -> 0 | F6: =VLOOKUP($D6,'[2]LC Balanced'!$Q$2:$U$542,3,FALSE) -> 0.149 | G6: =VLOOKUP($D6,'[2]LC Balanced'!$Q$2:$U$542,4,FALSE) -> 0.851 | H6: =VLOOKUP($D6,'[2]LC Balanced'!$Q$2:$U$542,5,FALSE) -> 0 | I6: =SUM(E6:H6) -> 1 | J6: =SUMPRODUCT($E$1:$H$1,E6:H6) -> 0.0619877 | K6: =(1+J6)^(1/12)-1 -> 0.0050244421 | L6: 0 | M6: =IF($L6=0,0,SUMPRODUCT($E$3:$H$3,E6:H6)) -> 0 | N6: =1-(1-M6)^(1/12) -> 0 | O6: =SUMPRODUCT($E$2:$H$2,E6:H6) -> 0.0070063 | P6: =1-(1-O6)^(1/12) -> 0.00058574167 | R6: Autopilot | S6: Balanced | T6: =R6&"_"&S6&"_"&U6 -> Autopilot_Balanced_539 | U6: 539 | V6: =VLOOKUP($U6,'[2]AP Balanced'!$Q$1:$T$542,2,FALSE) -> 0.77777778 | W6: =VLOOKUP($U6,'[2]AP Balanced'!$Q$1:$T$542,3,FALSE) -> 0.22222222 | X6: =VLOOKUP($U6,'[2]AP Balanced'!$Q$1:$T$542,4,FALSE) -> 0 | Y6: =SUM(V6:X6) -> 1 | Z6: =SUMPRODUCT($V$1:$X$1,V6:X6) -> 0.061675 | AA6: =(1+Z6)^(1/12)-1 -> 0.0049997782 | AB6: 1 | AC6: =IF($AB6=0,0,SUMPRODUCT($V$3:$X$3,V6:X6)) -> 0.0080555556 | AD6: =1-(1-AC6)^(1/12) -> 0.00067378764 | AE6: =SUMPRODUCT($V$2:$X$2,V6:X6) -> 0.0025 | AF6: =1-(1-AE6)^(1/12) -> 0.00020857243 | AH6: Lifecycle | AI6: Balanced | AJ6: =AH6&"_"&AI6&"_"&AK6 -> Lifecycle_Balanced_539 | AK6: 539 | AL6: =VLOOKUP($U6,[2]Standard_Balanced!$Q$1:$T$542,2,FALSE) -> 0.77777778 | AM6: =VLOOKUP($U6,[2]Standard_Balanced!$Q$1:$T$542,3,FALSE) -> 0.22222222 | AN6: =VLOOKUP($U6,[2]Standard_Balanced!$Q$1:$T$542,4,FALSE) -> 0 | AO6: =SUM(AL6:AN6) -> 1 | AP6: =SUMPRODUCT($AL$1:$AN$1,AL6:AN6) -> 0.061675 | AQ6: =(1+AP6)^(1/12)-1 -> 0.0049997782 | AR6: 0 | AS6: =IF(AR6=0,0,SUMPRODUCT($AL$3:$AN$3,AL6:AN6)) -> 0 | AT6: =1-(1-AS6)^(1/12) -> 0 | AU6: =SUMPRODUCT($AL$2:$AN$2,AL6:AN6) -> 0.0025 | AV6: =1-(1-AU6)^(1/12) -> 0.00020857243 | AX6: DIS | AY6: Non-Standard | AZ6: =AX6&"_"&AY6&"_"&BA6 -> DIS_Non-Standard_539 | BA6: 539 | BB6: =VLOOKUP($BA6,'[2]NonStandard DIS'!$Q$1:$X$542,2,FALSE) -> 0 | BC6: =VLOOKUP($BA6,'[2]NonStandard DIS'!$Q$1:$X$542,3,FALSE) -> 0 | BD6: =VLOOKUP($BA6,'[2]NonStandard DIS'!$Q$1:$X$542,4,FALSE) -> 0.308 | BE6: =VLOOKUP($BA6,'[2]NonStandard DIS'!$Q$1:$X$542,5,FALSE) -> 0.692 | BF6: =VLOOKUP($BA6,'[2]NonStandard DIS'!$Q$1:$X$542,6,FALSE) -> 0 | BG6: =VLOOKUP($BA6,'[2]NonStandard DIS'!$Q$1:$X$542,7,FALSE) -> 0 | BH6: =VLOOKUP($BA6,'[2]NonStandard DIS'!$Q$1:$X$542,8,FALSE) -> 0 | BI6: =SUM(BB6:BH6) -> 1 | BJ6: =SUMPRODUCT($BB$1:$BH$1,BB6:BH6) -> 0.0697285 | BK6: =(1+BJ6)^(1/12)-1 -> 0.0056328785 | BL6: 0 | BM6: =IF(BL6=0,0,SUMPRODUCT($BB$3:$BH$3,BB6:BH6)) -> 0 | BN6: =(1+BM6)^(1/12)-1 -> 0 | BO6: =SUMPRODUCT($BB$2:$BH$2,BB6:BH6) -> 0.0056776 | BP6: =(1+BO6)^(1/12)-1 -> 0.00047190658
A7: Lifecycle | B7: Balanced | C7: =A7&"_"&B7&"_"&D7 -> Lifecycle_Balanced_538 | D7: 538 | E7: =VLOOKUP($D7,'[2]LC Balanced'!$Q$2:$U$542,2,FALSE) -> 0 | F7: =VLOOKUP($D7,'[2]LC Balanced'!$Q$2:$U$542,3,FALSE) -> 0.149 | G7: =VLOOKUP($D7,'[2]LC Balanced'!$Q$2:$U$542,4,FALSE) -> 0.851 | H7: =VLOOKUP($D7,'[2]LC Balanced'!$Q$2:$U$542,5,FALSE) -> 0 | I7: =SUM(E7:H7) -> 1 | J7: =SUMPRODUCT($E$1:$H$1,E7:H7) -> 0.0619877 | K7: =(1+J7)^(1/12)-1 -> 0.0050244421 | L7: 0 | M7: =IF($L7=0,0,SUMPRODUCT($E$3:$H$3,E7:H7)) -> 0 | N7: =1-(1-M7)^(1/12) -> 0 | O7: =SUMPRODUCT($E$2:$H$2,E7:H7) -> 0.0070063 | P7: =1-(1-O7)^(1/12) -> 0.00058574167 | R7: Autopilot | S7: Balanced | T7: =R7&"_"&S7&"_"&U7 -> Autopilot_Balanced_538 | U7: 538 | V7: =VLOOKUP($U7,'[2]AP Balanced'!$Q$1:$T$542,2,FALSE) -> 0.77777778 | W7: =VLOOKUP($U7,'[2]AP Balanced'!$Q$1:$T$542,3,FALSE) -> 0.22222222 | X7: =VLOOKUP($U7,'[2]AP Balanced'!$Q$1:$T$542,4,FALSE) -> 0 | Y7: =SUM(V7:X7) -> 1 | Z7: =SUMPRODUCT($V$1:$X$1,V7:X7) -> 0.061675 | AA7: =(1+Z7)^(1/12)-1 -> 0.0049997782 | AB7: 1 | AC7: =IF($AB7=0,0,SUMPRODUCT($V$3:$X$3,V7:X7)) -> 0.0080555556 | AD7: =1-(1-AC7)^(1/12) -> 0.00067378764 | AE7: =SUMPRODUCT($V$2:$X$2,V7:X7) -> 0.0025 | AF7: =1-(1-AE7)^(1/12) -> 0.00020857243 | AH7: Lifecycle | AI7: Balanced | AJ7: =AH7&"_"&AI7&"_"&AK7 -> Lifecycle_Balanced_538 | AK7: 538 | AL7: =VLOOKUP($U7,[2]Standard_Balanced!$Q$1:$T$542,2,FALSE) -> 0.77777778 | AM7: =VLOOKUP($U7,[2]Standard_Balanced!$Q$1:$T$542,3,FALSE) -> 0.22222222 | AN7: =VLOOKUP($U7,[2]Standard_Balanced!$Q$1:$T$542,4,FALSE) -> 0 | AO7: =SUM(AL7:AN7) -> 1 | AP7: =SUMPRODUCT($AL$1:$AN$1,AL7:AN7) -> 0.061675 | AQ7: =(1+AP7)^(1/12)-1 -> 0.0049997782 | AR7: 0 | AS7: =IF(AR7=0,0,SUMPRODUCT($AL$3:$AN$3,AL7:AN7)) -> 0 | AT7: =1-(1-AS7)^(1/12) -> 0 | AU7: =SUMPRODUCT($AL$2:$AN$2,AL7:AN7) -> 0.0025 | AV7: =1-(1-AU7)^(1/12) -> 0.00020857243 | AX7: DIS | AY7: Non-Standard | AZ7: =AX7&"_"&AY7&"_"&BA7 -> DIS_Non-Standard_538 | BA7: 538 | BB7: =VLOOKUP($BA7,'[2]NonStandard DIS'!$Q$1:$X$542,2,FALSE) -> 0 | BC7: =VLOOKUP($BA7,'[2]NonStandard DIS'!$Q$1:$X$542,3,FALSE) -> 0 | BD7: =VLOOKUP($BA7,'[2]NonStandard DIS'!$Q$1:$X$542,4,FALSE) -> 0.308 | BE7: =VLOOKUP($BA7,'[2]NonStandard DIS'!$Q$1:$X$542,5,FALSE) -> 0.692 | BF7: =VLOOKUP($BA7,'[2]NonStandard DIS'!$Q$1:$X$542,6,FALSE) -> 0 | BG7: =VLOOKUP($BA7,'[2]NonStandard DIS'!$Q$1:$X$542,7,FALSE) -> 0 | BH7: =VLOOKUP($BA7,'[2]NonStandard DIS'!$Q$1:$X$542,8,FALSE) -> 0 | BI7: =SUM(BB7:BH7) -> 1 | BJ7: =SUMPRODUCT($BB$1:$BH$1,BB7:BH7) -> 0.0697285 | BK7: =(1+BJ7)^(1/12)-1 -> 0.0056328785 | BL7: 0 | BM7: =IF(BL7=0,0,SUMPRODUCT($BB$3:$BH$3,BB7:BH7)) -> 0 | BN7: =(1+BM7)^(1/12)-1 -> 0 | BO7: =SUMPRODUCT($BB$2:$BH$2,BB7:BH7) -> 0.0056776 | BP7: =(1+BO7)^(1/12)-1 -> 0.00047190658
A8: Lifecycle | B8: Balanced | C8: =A8&"_"&B8&"_"&D8 -> Lifecycle_Balanced_537 | D8: 537 | E8: =VLOOKUP($D8,'[2]LC Balanced'!$Q$2:$U$542,2,FALSE) -> 0 | F8: =VLOOKUP($D8,'[2]LC Balanced'!$Q$2:$U$542,3,FALSE) -> 0.149 | G8: =VLOOKUP($D8,'[2]LC Balanced'!$Q$2:$U$542,4,FALSE) -> 0.851 | H8: =VLOOKUP($D8,'[2]LC Balanced'!$Q$2:$U$542,5,FALSE) -> 0 | I8: =SUM(E8:H8) -> 1 | J8: =SUMPRODUCT($E$1:$H$1,E8:H8) -> 0.0619877 | K8: =(1+J8)^(1/12)-1 -> 0.0050244421 | L8: 0 | M8: =IF($L8=0,0,SUMPRODUCT($E$3:$H$3,E8:H8)) -> 0 | N8: =1-(1-M8)^(1/12) -> 0 | O8: =SUMPRODUCT($E$2:$H$2,E8:H8) -> 0.0070063 | P8: =1-(1-O8)^(1/12) -> 0.00058574167 | R8: Autopilot | S8: Balanced | T8: =R8&"_"&S8&"_"&U8 -> Autopilot_Balanced_537 | U8: 537 | V8: =VLOOKUP($U8,'[2]AP Balanced'!$Q$1:$T$542,2,FALSE) -> 0.77777778 | W8: =VLOOKUP($U8,'[2]AP Balanced'!$Q$1:$T$542,3,FALSE) -> 0.22222222 | X8: =VLOOKUP($U8,'[2]AP Balanced'!$Q$1:$T$542,4,FALSE) -> 0 | Y8: =SUM(V8:X8) -> 1 | Z8: =SUMPRODUCT($V$1:$X$1,V8:X8) -> 0.061675 | AA8: =(1+Z8)^(1/12)-1 -> 0.0049997782 | AB8: 1 | AC8: =IF($AB8=0,0,SUMPRODUCT($V$3:$X$3,V8:X8)) -> 0.0080555556 | AD8: =1-(1-AC8)^(1/12) -> 0.00067378764 | AE8: =SUMPRODUCT($V$2:$X$2,V8:X8) -> 0.0025 | AF8: =1-(1-AE8)^(1/12) -> 0.00020857243 | AH8: Lifecycle | AI8: Balanced | AJ8: =AH8&"_"&AI8&"_"&AK8 -> Lifecycle_Balanced_537 | AK8: 537 | AL8: =VLOOKUP($U8,[2]Standard_Balanced!$Q$1:$T$542,2,FALSE) -> 0.77777778 | AM8: =VLOOKUP($U8,[2]Standard_Balanced!$Q$1:$T$542,3,FALSE) -> 0.22222222 | AN8: =VLOOKUP($U8,[2]Standard_Balanced!$Q$1:$T$542,4,FALSE) -> 0 | AO8: =SUM(AL8:AN8) -> 1 | AP8: =SUMPRODUCT($AL$1:$AN$1,AL8:AN8) -> 0.061675 | AQ8: =(1+AP8)^(1/12)-1 -> 0.0049997782 | AR8: 0 | AS8: =IF(AR8=0,0,SUMPRODUCT($AL$3:$AN$3,AL8:AN8)) -> 0 | AT8: =1-(1-AS8)^(1/12) -> 0 | AU8: =SUMPRODUCT($AL$2:$AN$2,AL8:AN8) -> 0.0025 | AV8: =1-(1-AU8)^(1/12) -> 0.00020857243 | AX8: DIS | AY8: Non-Standard | AZ8: =AX8&"_"&AY8&"_"&BA8 -> DIS_Non-Standard_537 | BA8: 537 | BB8: =VLOOKUP($BA8,'[2]NonStandard DIS'!$Q$1:$X$542,2,FALSE) -> 0 | BC8: =VLOOKUP($BA8,'[2]NonStandard DIS'!$Q$1:$X$542,3,FALSE) -> 0 | BD8: =VLOOKUP($BA8,'[2]NonStandard DIS'!$Q$1:$X$542,4,FALSE) -> 0.308 | BE8: =VLOOKUP($BA8,'[2]NonStandard DIS'!$Q$1:$X$542,5,FALSE) -> 0.692 | BF8: =VLOOKUP($BA8,'[2]NonStandard DIS'!$Q$1:$X$542,6,FALSE) -> 0 | BG8: =VLOOKUP($BA8,'[2]NonStandard DIS'!$Q$1:$X$542,7,FALSE) -> 0 | BH8: =VLOOKUP($BA8,'[2]NonStandard DIS'!$Q$1:$X$542,8,FALSE) -> 0 | BI8: =SUM(BB8:BH8) -> 1 | BJ8: =SUMPRODUCT($BB$1:$BH$1,BB8:BH8) -> 0.0697285 | BK8: =(1+BJ8)^(1/12)-1 -> 0.0056328785 | BL8: 0 | BM8: =IF(BL8=0,0,SUMPRODUCT($BB$3:$BH$3,BB8:BH8)) -> 0 | BN8: =(1+BM8)^(1/12)-1 -> 0 | BO8: =SUMPRODUCT($BB$2:$BH$2,BB8:BH8) -> 0.0056776 | BP8: =(1+BO8)^(1/12)-1 -> 0.00047190658
A9: Lifecycle | B9: Balanced | C9: =A9&"_"&B9&"_"&D9 -> Lifecycle_Balanced_536 | D9: 536 | E9: =VLOOKUP($D9,'[2]LC Balanced'!$Q$2:$U$542,2,FALSE) -> 0 | F9: =VLOOKUP($D9,'[2]LC Balanced'!$Q$2:$U$542,3,FALSE) -> 0.149 | G9: =VLOOKUP($D9,'[2]LC Balanced'!$Q$2:$U$542,4,FALSE) -> 0.851 | H9: =VLOOKUP($D9,'[2]LC Balanced'!$Q$2:$U$542,5,FALSE) -> 0 | I9: =SUM(E9:H9) -> 1 | J9: =SUMPRODUCT($E$1:$H$1,E9:H9) -> 0.0619877 | K9: =(1+J9)^(1/12)-1 -> 0.0050244421 | L9: 0 | M9: =IF($L9=0,0,SUMPRODUCT($E$3:$H$3,E9:H9)) -> 0 | N9: =1-(1-M9)^(1/12) -> 0 | O9: =SUMPRODUCT($E$2:$H$2,E9:H9) -> 0.0070063 | P9: =1-(1-O9)^(1/12) -> 0.00058574167 | R9: Autopilot | S9: Balanced | T9: =R9&"_"&S9&"_"&U9 -> Autopilot_Balanced_536 | U9: 536 | V9: =VLOOKUP($U9,'[2]AP Balanced'!$Q$1:$T$542,2,FALSE) -> 0.77777778 | W9: =VLOOKUP($U9,'[2]AP Balanced'!$Q$1:$T$542,3,FALSE) -> 0.22222222 | X9: =VLOOKUP($U9,'[2]AP Balanced'!$Q$1:$T$542,4,FALSE) -> 0 | Y9: =SUM(V9:X9) -> 1 | Z9: =SUMPRODUCT($V$1:$X$1,V9:X9) -> 0.061675 | AA9: =(1+Z9)^(1/12)-1 -> 0.0049997782 | AB9: 1 | AC9: =IF($AB9=0,0,SUMPRODUCT($V$3:$X$3,V9:X9)) -> 0.0080555556 | AD9: =1-(1-AC9)^(1/12) -> 0.00067378764 | AE9: =SUMPRODUCT($V$2:$X$2,V9:X9) -> 0.0025 | AF9: =1-(1-AE9)^(1/12) -> 0.00020857243 | AH9: Lifecycle | AI9: Balanced | AJ9: =AH9&"_"&AI9&"_"&AK9 -> Lifecycle_Balanced_536 | AK9: 536 | AL9: =VLOOKUP($U9,[2]Standard_Balanced!$Q$1:$T$542,2,FALSE) -> 0.77777778 | AM9: =VLOOKUP($U9,[2]Standard_Balanced!$Q$1:$T$542,3,FALSE) -> 0.22222222 | AN9: =VLOOKUP($U9,[2]Standard_Balanced!$Q$1:$T$542,4,FALSE) -> 0 | AO9: =SUM(AL9:AN9) -> 1 | AP9: =SUMPRODUCT($AL$1:$AN$1,AL9:AN9) -> 0.061675 | AQ9: =(1+AP9)^(1/12)-1 -> 0.0049997782 | AR9: 0 | AS9: =IF(AR9=0,0,SUMPRODUCT($AL$3:$AN$3,AL9:AN9)) -> 0 | AT9: =1-(1-AS9)^(1/12) -> 0 | AU9: =SUMPRODUCT($AL$2:$AN$2,AL9:AN9) -> 0.0025 | AV9: =1-(1-AU9)^(1/12) -> 0.00020857243 | AX9: DIS | AY9: Non-Standard | AZ9: =AX9&"_"&AY9&"_"&BA9 -> DIS_Non-Standard_536 | BA9: 536 | BB9: =VLOOKUP($BA9,'[2]NonStandard DIS'!$Q$1:$X$542,2,FALSE) -> 0 | BC9: =VLOOKUP($BA9,'[2]NonStandard DIS'!$Q$1:$X$542,3,FALSE) -> 0 | BD9: =VLOOKUP($BA9,'[2]NonStandard DIS'!$Q$1:$X$542,4,FALSE) -> 0.308 | BE9: =VLOOKUP($BA9,'[2]NonStandard DIS'!$Q$1:$X$542,5,FALSE) -> 0.692 | BF9: =VLOOKUP($BA9,'[2]NonStandard DIS'!$Q$1:$X$542,6,FALSE) -> 0 | BG9: =VLOOKUP($BA9,'[2]NonStandard DIS'!$Q$1:$X$542,7,FALSE) -> 0 | BH9: =VLOOKUP($BA9,'[2]NonStandard DIS'!$Q$1:$X$542,8,FALSE) -> 0 | BI9: =SUM(BB9:BH9) -> 1 | BJ9: =SUMPRODUCT($BB$1:$BH$1,BB9:BH9) -> 0.0697285 | BK9: =(1+BJ9)^(1/12)-1 -> 0.0056328785 | BL9: 0 | BM9: =IF(BL9=0,0,SUMPRODUCT($BB$3:$BH$3,BB9:BH9)) -> 0 | BN9: =(1+BM9)^(1/12)-1 -> 0 | BO9: =SUMPRODUCT($BB$2:$BH$2,BB9:BH9) -> 0.0056776 | BP9: =(1+BO9)^(1/12)-1 -> 0.00047190658
A10: Lifecycle | B10: Balanced | C10: =A10&"_"&B10&"_"&D10 -> Lifecycle_Balanced_535 | D10: 535 | E10: =VLOOKUP($D10,'[2]LC Balanced'!$Q$2:$U$542,2,FALSE) -> 0 | F10: =VLOOKUP($D10,'[2]LC Balanced'!$Q$2:$U$542,3,FALSE) -> 0.149 | G10: =VLOOKUP($D10,'[2]LC Balanced'!$Q$2:$U$542,4,FALSE) -> 0.851 | H10: =VLOOKUP($D10,'[2]LC Balanced'!$Q$2:$U$542,5,FALSE) -> 0 | I10: =SUM(E10:H10) -> 1 | J10: =SUMPRODUCT($E$1:$H$1,E10:H10) -> 0.0619877 | K10: =(1+J10)^(1/12)-1 -> 0.0050244421 | L10: 0 | M10: =IF($L10=0,0,SUMPRODUCT($E$3:$H$3,E10:H10)) -> 0 | N10: =1-(1-M10)^(1/12) -> 0 | O10: =SUMPRODUCT($E$2:$H$2,E10:H10) -> 0.0070063 | P10: =1-(1-O10)^(1/12) -> 0.00058574167 | R10: Autopilot | S10: Balanced | T10: =R10&"_"&S10&"_"&U10 -> Autopilot_Balanced_535 | U10: 535 | V10: =VLOOKUP($U10,'[2]AP Balanced'!$Q$1:$T$542,2,FALSE) -> 0.77777778 | W10: =VLOOKUP($U10,'[2]AP Balanced'!$Q$1:$T$542,3,FALSE) -> 0.22222222 | X10: =VLOOKUP($U10,'[2]AP Balanced'!$Q$1:$T$542,4,FALSE) -> 0 | Y10: =SUM(V10:X10) -> 1 | Z10: =SUMPRODUCT($V$1:$X$1,V10:X10) -> 0.061675 | AA10: =(1+Z10)^(1/12)-1 -> 0.0049997782 | AB10: 1 | AC10: =IF($AB10=0,0,SUMPRODUCT($V$3:$X$3,V10:X10)) -> 0.0080555556 | AD10: =1-(1-AC10)^(1/12) -> 0.00067378764 | AE10: =SUMPRODUCT($V$2:$X$2,V10:X10) -> 0.0025 | AF10: =1-(1-AE10)^(1/12) -> 0.00020857243 | AH10: Lifecycle | AI10: Balanced | AJ10: =AH10&"_"&AI10&"_"&AK10 -> Lifecycle_Balanced_535 | AK10: 535 | AL10: =VLOOKUP($U10,[2]Standard_Balanced!$Q$1:$T$542,2,FALSE) -> 0.77777778 | AM10: =VLOOKUP($U10,[2]Standard_Balanced!$Q$1:$T$542,3,FALSE) -> 0.22222222 | AN10: =VLOOKUP($U10,[2]Standard_Balanced!$Q$1:$T$542,4,FALSE) -> 0 | AO10: =SUM(AL10:AN10) -> 1 | AP10: =SUMPRODUCT($AL$1:$AN$1,AL10:AN10) -> 0.061675 | AQ10: =(1+AP10)^(1/12)-1 -> 0.0049997782 | AR10: 0 | AS10: =IF(AR10=0,0,SUMPRODUCT($AL$3:$AN$3,AL10:AN10)) -> 0 | AT10: =1-(1-AS10)^(1/12) -> 0 | AU10: =SUMPRODUCT($AL$2:$AN$2,AL10:AN10) -> 0.0025 | AV10: =1-(1-AU10)^(1/12) -> 0.00020857243 | AX10: DIS | AY10: Non-Standard | AZ10: =AX10&"_"&AY10&"_"&BA10 -> DIS_Non-Standard_535 | BA10: 535 | BB10: =VLOOKUP($BA10,'[2]NonStandard DIS'!$Q$1:$X$542,2,FALSE) -> 0 | BC10: =VLOOKUP($BA10,'[2]NonStandard DIS'!$Q$1:$X$542,3,FALSE) -> 0 | BD10: =VLOOKUP($BA10,'[2]NonStandard DIS'!$Q$1:$X$542,4,FALSE) -> 0.308 | BE10: =VLOOKUP($BA10,'[2]NonStandard DIS'!$Q$1:$X$542,5,FALSE) -> 0.692 | BF10: =VLOOKUP($BA10,'[2]NonStandard DIS'!$Q$1:$X$542,6,FALSE) -> 0 | BG10: =VLOOKUP($BA10,'[2]NonStandard DIS'!$Q$1:$X$542,7,FALSE) -> 0 | BH10: =VLOOKUP($BA10,'[2]NonStandard DIS'!$Q$1:$X$542,8,FALSE) -> 0 | BI10: =SUM(BB10:BH10) -> 1 | BJ10: =SUMPRODUCT($BB$1:$BH$1,BB10:BH10) -> 0.0697285 | BK10: =(1+BJ10)^(1/12)-1 -> 0.0056328785 | BL10: 0 | BM10: =IF(BL10=0,0,SUMPRODUCT($BB$3:$BH$3,BB10:BH10)) -> 0 | BN10: =(1+BM10)^(1/12)-1 -> 0 | BO10: =SUMPRODUCT($BB$2:$BH$2,BB10:BH10) -> 0.0056776 | BP10: =(1+BO10)^(1/12)-1 -> 0.00047190658
A11: Lifecycle | B11: Balanced | C11: =A11&"_"&B11&"_"&D11 -> Lifecycle_Balanced_534 | D11: 534 | E11: =VLOOKUP($D11,'[2]LC Balanced'!$Q$2:$U$542,2,FALSE) -> 0 | F11: =VLOOKUP($D11,'[2]LC Balanced'!$Q$2:$U$542,3,FALSE) -> 0.149 | G11: =VLOOKUP($D11,'[2]LC Balanced'!$Q$2:$U$542,4,FALSE) -> 0.851 | H11: =VLOOKUP($D11,'[2]LC Balanced'!$Q$2:$U$542,5,FALSE) -> 0 | I11: =SUM(E11:H11) -> 1 | J11: =SUMPRODUCT($E$1:$H$1,E11:H11) -> 0.0619877 | K11: =(1+J11)^(1/12)-1 -> 0.0050244421 | L11: 0 | M11: =IF($L11=0,0,SUMPRODUCT($E$3:$H$3,E11:H11)) -> 0 | N11: =1-(1-M11)^(1/12) -> 0 | O11: =SUMPRODUCT($E$2:$H$2,E11:H11) -> 0.0070063 | P11: =1-(1-O11)^(1/12) -> 0.00058574167 | R11: Autopilot | S11: Balanced | T11: =R11&"_"&S11&"_"&U11 -> Autopilot_Balanced_534 | U11: 534 | V11: =VLOOKUP($U11,'[2]AP Balanced'!$Q$1:$T$542,2,FALSE) -> 0.77777778 | W11: =VLOOKUP($U11,'[2]AP Balanced'!$Q$1:$T$542,3,FALSE) -> 0.22222222 | X11: =VLOOKUP($U11,'[2]AP Balanced'!$Q$1:$T$542,4,FALSE) -> 0 | Y11: =SUM(V11:X11) -> 1 | Z11: =SUMPRODUCT($V$1:$X$1,V11:X11) -> 0.061675 | AA11: =(1+Z11)^(1/12)-1 -> 0.0049997782 | AB11: 1 | AC11: =IF($AB11=0,0,SUMPRODUCT($V$3:$X$3,V11:X11)) -> 0.0080555556 | AD11: =1-(1-AC11)^(1/12) -> 0.00067378764 | AE11: =SUMPRODUCT($V$2:$X$2,V11:X11) -> 0.0025 | AF11: =1-(1-AE11)^(1/12) -> 0.00020857243 | AH11: Lifecycle | AI11: Balanced | AJ11: =AH11&"_"&AI11&"_"&AK11 -> Lifecycle_Balanced_534 | AK11: 534 | AL11: =VLOOKUP($U11,[2]Standard_Balanced!$Q$1:$T$542,2,FALSE) -> 0.77777778 | AM11: =VLOOKUP($U11,[2]Standard_Balanced!$Q$1:$T$542,3,FALSE) -> 0.22222222 | AN11: =VLOOKUP($U11,[2]Standard_Balanced!$Q$1:$T$542,4,FALSE) -> 0 | AO11: =SUM(AL11:AN11) -> 1 | AP11: =SUMPRODUCT($AL$1:$AN$1,AL11:AN11) -> 0.061675 | AQ11: =(1+AP11)^(1/12)-1 -> 0.0049997782 | AR11: 0 | AS11: =IF(AR11=0,0,SUMPRODUCT($AL$3:$AN$3,AL11:AN11)) -> 0 | AT11: =1-(1-AS11)^(1/12) -> 0 | AU11: =SUMPRODUCT($AL$2:$AN$2,AL11:AN11) -> 0.0025 | AV11: =1-(1-AU11)^(1/12) -> 0.00020857243 | AX11: DIS | AY11: Non-Standard | AZ11: =AX11&"_"&AY11&"_"&BA11 -> DIS_Non-Standard_534 | BA11: 534 | BB11: =VLOOKUP($BA11,'[2]NonStandard DIS'!$Q$1:$X$542,2,FALSE) -> 0 | BC11: =VLOOKUP($BA11,'[2]NonStandard DIS'!$Q$1:$X$542,3,FALSE) -> 0 | BD11: =VLOOKUP($BA11,'[2]NonStandard DIS'!$Q$1:$X$542,4,FALSE) -> 0.308 | BE11: =VLOOKUP($BA11,'[2]NonStandard DIS'!$Q$1:$X$542,5,FALSE) -> 0.692 | BF11: =VLOOKUP($BA11,'[2]NonStandard DIS'!$Q$1:$X$542,6,FALSE) -> 0 | BG11: =VLOOKUP($BA11,'[2]NonStandard DIS'!$Q$1:$X$542,7,FALSE) -> 0 | BH11: =VLOOKUP($BA11,'[2]NonStandard DIS'!$Q$1:$X$542,8,FALSE) -> 0 | BI11: =SUM(BB11:BH11) -> 1 | BJ11: =SUMPRODUCT($BB$1:$BH$1,BB11:BH11) -> 0.0697285 | BK11: =(1+BJ11)^(1/12)-1 -> 0.0056328785 | BL11: 0 | BM11: =IF(BL11=0,0,SUMPRODUCT($BB$3:$BH$3,BB11:BH11)) -> 0 | BN11: =(1+BM11)^(1/12)-1 -> 0 | BO11: =SUMPRODUCT($BB$2:$BH$2,BB11:BH11) -> 0.0056776 | BP11: =(1+BO11)^(1/12)-1 -> 0.00047190658
A12: Lifecycle | B12: Balanced | C12: =A12&"_"&B12&"_"&D12 -> Lifecycle_Balanced_533 | D12: 533 | E12: =VLOOKUP($D12,'[2]LC Balanced'!$Q$2:$U$542,2,FALSE) -> 0 | F12: =VLOOKUP($D12,'[2]LC Balanced'!$Q$2:$U$542,3,FALSE) -> 0.149 | G12: =VLOOKUP($D12,'[2]LC Balanced'!$Q$2:$U$542,4,FALSE) -> 0.851 | H12: =VLOOKUP($D12,'[2]LC Balanced'!$Q$2:$U$542,5,FALSE) -> 0 | I12: =SUM(E12:H12) -> 1 | J12: =SUMPRODUCT($E$1:$H$1,E12:H12) -> 0.0619877 | K12: =(1+J12)^(1/12)-1 -> 0.0050244421 | L12: 0 | M12: =IF($L12=0,0,SUMPRODUCT($E$3:$H$3,E12:H12)) -> 0 | N12: =1-(1-M12)^(1/12) -> 0 | O12: =SUMPRODUCT($E$2:$H$2,E12:H12) -> 0.0070063 | P12: =1-(1-O12)^(1/12) -> 0.00058574167 | R12: Autopilot | S12: Balanced | T12: =R12&"_"&S12&"_"&U12 -> Autopilot_Balanced_533 | U12: 533 | V12: =VLOOKUP($U12,'[2]AP Balanced'!$Q$1:$T$542,2,FALSE) -> 0.77777778 | W12: =VLOOKUP($U12,'[2]AP Balanced'!$Q$1:$T$542,3,FALSE) -> 0.22222222 | X12: =VLOOKUP($U12,'[2]AP Balanced'!$Q$1:$T$542,4,FALSE) -> 0 | Y12: =SUM(V12:X12) -> 1 | Z12: =SUMPRODUCT($V$1:$X$1,V12:X12) -> 0.061675 | AA12: =(1+Z12)^(1/12)-1 -> 0.0049997782 | AB12: 1 | AC12: =IF($AB12=0,0,SUMPRODUCT($V$3:$X$3,V12:X12)) -> 0.0080555556 | AD12: =1-(1-AC12)^(1/12) -> 0.00067378764 | AE12: =SUMPRODUCT($V$2:$X$2,V12:X12) -> 0.0025 | AF12: =1-(1-AE12)^(1/12) -> 0.00020857243 | AH12: Lifecycle | AI12: Balanced | AJ12: =AH12&"_"&AI12&"_"&AK12 -> Lifecycle_Balanced_533 | AK12: 533 | AL12: =VLOOKUP($U12,[2]Standard_Balanced!$Q$1:$T$542,2,FALSE) -> 0.77777778 | AM12: =VLOOKUP($U12,[2]Standard_Balanced!$Q$1:$T$542,3,FALSE) -> 0.22222222 | AN12: =VLOOKUP($U12,[2]Standard_Balanced!$Q$1:$T$542,4,FALSE) -> 0 | AO12: =SUM(AL12:AN12) -> 1 | AP12: =SUMPRODUCT($AL$1:$AN$1,AL12:AN12) -> 0.061675 | AQ12: =(1+AP12)^(1/12)-1 -> 0.0049997782 | AR12: 0 | AS12: =IF(AR12=0,0,SUMPRODUCT($AL$3:$AN$3,AL12:AN12)) -> 0 | AT12: =1-(1-AS12)^(1/12) -> 0 | AU12: =SUMPRODUCT($AL$2:$AN$2,AL12:AN12) -> 0.0025 | AV12: =1-(1-AU12)^(1/12) -> 0.00020857243 | AX12: DIS | AY12: Non-Standard | AZ12: =AX12&"_"&AY12&"_"&BA12 -> DIS_Non-Standard_533 | BA12: 533 | BB12: =VLOOKUP($BA12,'[2]NonStandard DIS'!$Q$1:$X$542,2,FALSE) -> 0 | BC12: =VLOOKUP($BA12,'[2]NonStandard DIS'!$Q$1:$X$542,3,FALSE) -> 0 | BD12: =VLOOKUP($BA12,'[2]NonStandard DIS'!$Q$1:$X$542,4,FALSE) -> 0.308 | BE12: =VLOOKUP($BA12,'[2]NonStandard DIS'!$Q$1:$X$542,5,FALSE) -> 0.692 | BF12: =VLOOKUP($BA12,'[2]NonStandard DIS'!$Q$1:$X$542,6,FALSE) -> 0 | BG12: =VLOOKUP($BA12,'[2]NonStandard DIS'!$Q$1:$X$542,7,FALSE) -> 0 | BH12: =VLOOKUP($BA12,'[2]NonStandard DIS'!$Q$1:$X$542,8,FALSE) -> 0 | BI12: =SUM(BB12:BH12) -> 1 | BJ12: =SUMPRODUCT($BB$1:$BH$1,BB12:BH12) -> 0.0697285 | BK12: =(1+BJ12)^(1/12)-1 -> 0.0056328785 | BL12: 0 | BM12: =IF(BL12=0,0,SUMPRODUCT($BB$3:$BH$3,BB12:BH12)) -> 0 | BN12: =(1+BM12)^(1/12)-1 -> 0 | BO12: =SUMPRODUCT($BB$2:$BH$2,BB12:BH12) -> 0.0056776 | BP12: =(1+BO12)^(1/12)-1 -> 0.00047190658
A13: Lifecycle | B13: Balanced | C13: =A13&"_"&B13&"_"&D13 -> Lifecycle_Balanced_532 | D13: 532 | E13: =VLOOKUP($D13,'[2]LC Balanced'!$Q$2:$U$542,2,FALSE) -> 0 | F13: =VLOOKUP($D13,'[2]LC Balanced'!$Q$2:$U$542,3,FALSE) -> 0.149 | G13: =VLOOKUP($D13,'[2]LC Balanced'!$Q$2:$U$542,4,FALSE) -> 0.851 | H13: =VLOOKUP($D13,'[2]LC Balanced'!$Q$2:$U$542,5,FALSE) -> 0 | I13: =SUM(E13:H13) -> 1 | J13: =SUMPRODUCT($E$1:$H$1,E13:H13) -> 0.0619877 | K13: =(1+J13)^(1/12)-1 -> 0.0050244421 | L13: 0 | M13: =IF($L13=0,0,SUMPRODUCT($E$3:$H$3,E13:H13)) -> 0 | N13: =1-(1-M13)^(1/12) -> 0 | O13: =SUMPRODUCT($E$2:$H$2,E13:H13) -> 0.0070063 | P13: =1-(1-O13)^(1/12) -> 0.00058574167 | R13: Autopilot | S13: Balanced | T13: =R13&"_"&S13&"_"&U13 -> Autopilot_Balanced_532 | U13: 532 | V13: =VLOOKUP($U13,'[2]AP Balanced'!$Q$1:$T$542,2,FALSE) -> 0.77777778 | W13: =VLOOKUP($U13,'[2]AP Balanced'!$Q$1:$T$542,3,FALSE) -> 0.22222222 | X13: =VLOOKUP($U13,'[2]AP Balanced'!$Q$1:$T$542,4,FALSE) -> 0 | Y13: =SUM(V13:X13) -> 1 | Z13: =SUMPRODUCT($V$1:$X$1,V13:X13) -> 0.061675 | AA13: =(1+Z13)^(1/12)-1 -> 0.0049997782 | AB13: 1 | AC13: =IF($AB13=0,0,SUMPRODUCT($V$3:$X$3,V13:X13)) -> 0.0080555556 | AD13: =1-(1-AC13)^(1/12) -> 0.00067378764 | AE13: =SUMPRODUCT($V$2:$X$2,V13:X13) -> 0.0025 | AF13: =1-(1-AE13)^(1/12) -> 0.00020857243 | AH13: Lifecycle | AI13: Balanced | AJ13: =AH13&"_"&AI13&"_"&AK13 -> Lifecycle_Balanced_532 | AK13: 532 | AL13: =VLOOKUP($U13,[2]Standard_Balanced!$Q$1:$T$542,2,FALSE) -> 0.77777778 | AM13: =VLOOKUP($U13,[2]Standard_Balanced!$Q$1:$T$542,3,FALSE) -> 0.22222222 | AN13: =VLOOKUP($U13,[2]Standard_Balanced!$Q$1:$T$542,4,FALSE) -> 0 | AO13: =SUM(AL13:AN13) -> 1 | AP13: =SUMPRODUCT($AL$1:$AN$1,AL13:AN13) -> 0.061675 | AQ13: =(1+AP13)^(1/12)-1 -> 0.0049997782 | AR13: 0 | AS13: =IF(AR13=0,0,SUMPRODUCT($AL$3:$AN$3,AL13:AN13)) -> 0 | AT13: =1-(1-AS13)^(1/12) -> 0 | AU13: =SUMPRODUCT($AL$2:$AN$2,AL13:AN13) -> 0.0025 | AV13: =1-(1-AU13)^(1/12) -> 0.00020857243 | AX13: DIS | AY13: Non-Standard | AZ13: =AX13&"_"&AY13&"_"&BA13 -> DIS_Non-Standard_532 | BA13: 532 | BB13: =VLOOKUP($BA13,'[2]NonStandard DIS'!$Q$1:$X$542,2,FALSE) -> 0 | BC13: =VLOOKUP($BA13,'[2]NonStandard DIS'!$Q$1:$X$542,3,FALSE) -> 0 | BD13: =VLOOKUP($BA13,'[2]NonStandard DIS'!$Q$1:$X$542,4,FALSE) -> 0.308 | BE13: =VLOOKUP($BA13,'[2]NonStandard DIS'!$Q$1:$X$542,5,FALSE) -> 0.692 | BF13: =VLOOKUP($BA13,'[2]NonStandard DIS'!$Q$1:$X$542,6,FALSE) -> 0 | BG13: =VLOOKUP($BA13,'[2]NonStandard DIS'!$Q$1:$X$542,7,FALSE) -> 0 | BH13: =VLOOKUP($BA13,'[2]NonStandard DIS'!$Q$1:$X$542,8,FALSE) -> 0 | BI13: =SUM(BB13:BH13) -> 1 | BJ13: =SUMPRODUCT($BB$1:$BH$1,BB13:BH13) -> 0.0697285 | BK13: =(1+BJ13)^(1/12)-1 -> 0.0056328785 | BL13: 0 | BM13: =IF(BL13=0,0,SUMPRODUCT($BB$3:$BH$3,BB13:BH13)) -> 0 | BN13: =(1+BM13)^(1/12)-1 -> 0 | BO13: =SUMPRODUCT($BB$2:$BH$2,BB13:BH13) -> 0.0056776 | BP13: =(1+BO13)^(1/12)-1 -> 0.00047190658
A14: Lifecycle | B14: Balanced | C14: =A14&"_"&B14&"_"&D14 -> Lifecycle_Balanced_531 | D14: 531 | E14: =VLOOKUP($D14,'[2]LC Balanced'!$Q$2:$U$542,2,FALSE) -> 0 | F14: =VLOOKUP($D14,'[2]LC Balanced'!$Q$2:$U$542,3,FALSE) -> 0.149 | G14: =VLOOKUP($D14,'[2]LC Balanced'!$Q$2:$U$542,4,FALSE) -> 0.851 | H14: =VLOOKUP($D14,'[2]LC Balanced'!$Q$2:$U$542,5,FALSE) -> 0 | I14: =SUM(E14:H14) -> 1 | J14: =SUMPRODUCT($E$1:$H$1,E14:H14) -> 0.0619877 | K14: =(1+J14)^(1/12)-1 -> 0.0050244421 | L14: 0 | M14: =IF($L14=0,0,SUMPRODUCT($E$3:$H$3,E14:H14)) -> 0 | N14: =1-(1-M14)^(1/12) -> 0 | O14: =SUMPRODUCT($E$2:$H$2,E14:H14) -> 0.0070063 | P14: =1-(1-O14)^(1/12) -> 0.00058574167 | R14: Autopilot | S14: Balanced | T14: =R14&"_"&S14&"_"&U14 -> Autopilot_Balanced_531 | U14: 531 | V14: =VLOOKUP($U14,'[2]AP Balanced'!$Q$1:$T$542,2,FALSE) -> 0.77777778 | W14: =VLOOKUP($U14,'[2]AP Balanced'!$Q$1:$T$542,3,FALSE) -> 0.22222222 | X14: =VLOOKUP($U14,'[2]AP Balanced'!$Q$1:$T$542,4,FALSE) -> 0 | Y14: =SUM(V14:X14) -> 1 | Z14: =SUMPRODUCT($V$1:$X$1,V14:X14) -> 0.061675 | AA14: =(1+Z14)^(1/12)-1 -> 0.0049997782 | AB14: 1 | AC14: =IF($AB14=0,0,SUMPRODUCT($V$3:$X$3,V14:X14)) -> 0.0080555556 | AD14: =1-(1-AC14)^(1/12) -> 0.00067378764 | AE14: =SUMPRODUCT($V$2:$X$2,V14:X14) -> 0.0025 | AF14: =1-(1-AE14)^(1/12) -> 0.00020857243 | AH14: Lifecycle | AI14: Balanced | AJ14: =AH14&"_"&AI14&"_"&AK14 -> Lifecycle_Balanced_531 | AK14: 531 | AL14: =VLOOKUP($U14,[2]Standard_Balanced!$Q$1:$T$542,2,FALSE) -> 0.77777778 | AM14: =VLOOKUP($U14,[2]Standard_Balanced!$Q$1:$T$542,3,FALSE) -> 0.22222222 | AN14: =VLOOKUP($U14,[2]Standard_Balanced!$Q$1:$T$542,4,FALSE) -> 0 | AO14: =SUM(AL14:AN14) -> 1 | AP14: =SUMPRODUCT($AL$1:$AN$1,AL14:AN14) -> 0.061675 | AQ14: =(1+AP14)^(1/12)-1 -> 0.0049997782 | AR14: 0 | AS14: =IF(AR14=0,0,SUMPRODUCT($AL$3:$AN$3,AL14:AN14)) -> 0 | AT14: =1-(1-AS14)^(1/12) -> 0 | AU14: =SUMPRODUCT($AL$2:$AN$2,AL14:AN14) -> 0.0025 | AV14: =1-(1-AU14)^(1/12) -> 0.00020857243 | AX14: DIS | AY14: Non-Standard | AZ14: =AX14&"_"&AY14&"_"&BA14 -> DIS_Non-Standard_531 | BA14: 531 | BB14: =VLOOKUP($BA14,'[2]NonStandard DIS'!$Q$1:$X$542,2,FALSE) -> 0 | BC14: =VLOOKUP($BA14,'[2]NonStandard DIS'!$Q$1:$X$542,3,FALSE) -> 0 | BD14: =VLOOKUP($BA14,'[2]NonStandard DIS'!$Q$1:$X$542,4,FALSE) -> 0.308 | BE14: =VLOOKUP($BA14,'[2]NonStandard DIS'!$Q$1:$X$542,5,FALSE) -> 0.692 | BF14: =VLOOKUP($BA14,'[2]NonStandard DIS'!$Q$1:$X$542,6,FALSE) -> 0 | BG14: =VLOOKUP($BA14,'[2]NonStandard DIS'!$Q$1:$X$542,7,FALSE) -> 0 | BH14: =VLOOKUP($BA14,'[2]NonStandard DIS'!$Q$1:$X$542,8,FALSE) -> 0 | BI14: =SUM(BB14:BH14) -> 1 | BJ14: =SUMPRODUCT($BB$1:$BH$1,BB14:BH14) -> 0.0697285 | BK14: =(1+BJ14)^(1/12)-1 -> 0.0056328785 | BL14: 0 | BM14: =IF(BL14=0,0,SUMPRODUCT($BB$3:$BH$3,BB14:BH14)) -> 0 | BN14: =(1+BM14)^(1/12)-1 -> 0 | BO14: =SUMPRODUCT($BB$2:$BH$2,BB14:BH14) -> 0.0056776 | BP14: =(1+BO14)^(1/12)-1 -> 0.00047190658
A15: Lifecycle | B15: Balanced | C15: =A15&"_"&B15&"_"&D15 -> Lifecycle_Balanced_530 | D15: 530 | E15: =VLOOKUP($D15,'[2]LC Balanced'!$Q$2:$U$542,2,FALSE) -> 0 | F15: =VLOOKUP($D15,'[2]LC Balanced'!$Q$2:$U$542,3,FALSE) -> 0.149 | G15: =VLOOKUP($D15,'[2]LC Balanced'!$Q$2:$U$542,4,FALSE) -> 0.851 | H15: =VLOOKUP($D15,'[2]LC Balanced'!$Q$2:$U$542,5,FALSE) -> 0 | I15: =SUM(E15:H15) -> 1 | J15: =SUMPRODUCT($E$1:$H$1,E15:H15) -> 0.0619877 | K15: =(1+J15)^(1/12)-1 -> 0.0050244421 | L15: 0 | M15: =IF($L15=0,0,SUMPRODUCT($E$3:$H$3,E15:H15)) -> 0 | N15: =1-(1-M15)^(1/12) -> 0 | O15: =SUMPRODUCT($E$2:$H$2,E15:H15) -> 0.0070063 | P15: =1-(1-O15)^(1/12) -> 0.00058574167 | R15: Autopilot | S15: Balanced | T15: =R15&"_"&S15&"_"&U15 -> Autopilot_Balanced_530 | U15: 530 | V15: =VLOOKUP($U15,'[2]AP Balanced'!$Q$1:$T$542,2,FALSE) -> 0.77777778 | W15: =VLOOKUP($U15,'[2]AP Balanced'!$Q$1:$T$542,3,FALSE) -> 0.22222222 | X15: =VLOOKUP($U15,'[2]AP Balanced'!$Q$1:$T$542,4,FALSE) -> 0 | Y15: =SUM(V15:X15) -> 1 | Z15: =SUMPRODUCT($V$1:$X$1,V15:X15) -> 0.061675 | AA15: =(1+Z15)^(1/12)-1 -> 0.0049997782 | AB15: 1 | AC15: =IF($AB15=0,0,SUMPRODUCT($V$3:$X$3,V15:X15)) -> 0.0080555556 | AD15: =1-(1-AC15)^(1/12) -> 0.00067378764 | AE15: =SUMPRODUCT($V$2:$X$2,V15:X15) -> 0.0025 | AF15: =1-(1-AE15)^(1/12) -> 0.00020857243 | AH15: Lifecycle | AI15: Balanced | AJ15: =AH15&"_"&AI15&"_"&AK15 -> Lifecycle_Balanced_530 | AK15: 530 | AL15: =VLOOKUP($U15,[2]Standard_Balanced!$Q$1:$T$542,2,FALSE) -> 0.77777778 | AM15: =VLOOKUP($U15,[2]Standard_Balanced!$Q$1:$T$542,3,FALSE) -> 0.22222222 | AN15: =VLOOKUP($U15,[2]Standard_Balanced!$Q$1:$T$542,4,FALSE) -> 0 | AO15: =SUM(AL15:AN15) -> 1 | AP15: =SUMPRODUCT($AL$1:$AN$1,AL15:AN15) -> 0.061675 | AQ15: =(1+AP15)^(1/12)-1 -> 0.0049997782 | AR15: 0 | AS15: =IF(AR15=0,0,SUMPRODUCT($AL$3:$AN$3,AL15:AN15)) -> 0 | AT15: =1-(1-AS15)^(1/12) -> 0 | AU15: =SUMPRODUCT($AL$2:$AN$2,AL15:AN15) -> 0.0025 | AV15: =1-(1-AU15)^(1/12) -> 0.00020857243 | AX15: DIS | AY15: Non-Standard | AZ15: =AX15&"_"&AY15&"_"&BA15 -> DIS_Non-Standard_530 | BA15: 530 | BB15: =VLOOKUP($BA15,'[2]NonStandard DIS'!$Q$1:$X$542,2,FALSE) -> 0 | BC15: =VLOOKUP($BA15,'[2]NonStandard DIS'!$Q$1:$X$542,3,FALSE) -> 0 | BD15: =VLOOKUP($BA15,'[2]NonStandard DIS'!$Q$1:$X$542,4,FALSE) -> 0.308 | BE15: =VLOOKUP($BA15,'[2]NonStandard DIS'!$Q$1:$X$542,5,FALSE) -> 0.692 | BF15: =VLOOKUP($BA15,'[2]NonStandard DIS'!$Q$1:$X$542,6,FALSE) -> 0 | BG15: =VLOOKUP($BA15,'[2]NonStandard DIS'!$Q$1:$X$542,7,FALSE) -> 0 | BH15: =VLOOKUP($BA15,'[2]NonStandard DIS'!$Q$1:$X$542,8,FALSE) -> 0 | BI15: =SUM(BB15:BH15) -> 1 | BJ15: =SUMPRODUCT($BB$1:$BH$1,BB15:BH15) -> 0.0697285 | BK15: =(1+BJ15)^(1/12)-1 -> 0.0056328785 | BL15: 0 | BM15: =IF(BL15=0,0,SUMPRODUCT($BB$3:$BH$3,BB15:BH15)) -> 0 | BN15: =(1+BM15)^(1/12)-1 -> 0 | BO15: =SUMPRODUCT($BB$2:$BH$2,BB15:BH15) -> 0.0056776 | BP15: =(1+BO15)^(1/12)-1 -> 0.00047190658
A16: Lifecycle | B16: Balanced | C16: =A16&"_"&B16&"_"&D16 -> Lifecycle_Balanced_529 | D16: 529 | E16: =VLOOKUP($D16,'[2]LC Balanced'!$Q$2:$U$542,2,FALSE) -> 0 | F16: =VLOOKUP($D16,'[2]LC Balanced'!$Q$2:$U$542,3,FALSE) -> 0.149 | G16: =VLOOKUP($D16,'[2]LC Balanced'!$Q$2:$U$542,4,FALSE) -> 0.851 | H16: =VLOOKUP($D16,'[2]LC Balanced'!$Q$2:$U$542,5,FALSE) -> 0 | I16: =SUM(E16:H16) -> 1 | J16: =SUMPRODUCT($E$1:$H$1,E16:H16) -> 0.0619877 | K16: =(1+J16)^(1/12)-1 -> 0.0050244421 | L16: 0 | M16: =IF($L16=0,0,SUMPRODUCT($E$3:$H$3,E16:H16)) -> 0 | N16: =1-(1-M16)^(1/12) -> 0 | O16: =SUMPRODUCT($E$2:$H$2,E16:H16) -> 0.0070063 | P16: =1-(1-O16)^(1/12) -> 0.00058574167 | R16: Autopilot | S16: Balanced | T16: =R16&"_"&S16&"_"&U16 -> Autopilot_Balanced_529 | U16: 529 | V16: =VLOOKUP($U16,'[2]AP Balanced'!$Q$1:$T$542,2,FALSE) -> 0.77777778 | W16: =VLOOKUP($U16,'[2]AP Balanced'!$Q$1:$T$542,3,FALSE) -> 0.22222222 | X16: =VLOOKUP($U16,'[2]AP Balanced'!$Q$1:$T$542,4,FALSE) -> 0 | Y16: =SUM(V16:X16) -> 1 | Z16: =SUMPRODUCT($V$1:$X$1,V16:X16) -> 0.061675 | AA16: =(1+Z16)^(1/12)-1 -> 0.0049997782 | AB16: 1 | AC16: =IF($AB16=0,0,SUMPRODUCT($V$3:$X$3,V16:X16)) -> 0.0080555556 | AD16: =1-(1-AC16)^(1/12) -> 0.00067378764 | AE16: =SUMPRODUCT($V$2:$X$2,V16:X16) -> 0.0025 | AF16: =1-(1-AE16)^(1/12) -> 0.00020857243 | AH16: Lifecycle | AI16: Balanced | AJ16: =AH16&"_"&AI16&"_"&AK16 -> Lifecycle_Balanced_529 | AK16: 529 | AL16: =VLOOKUP($U16,[2]Standard_Balanced!$Q$1:$T$542,2,FALSE) -> 0.77777778 | AM16: =VLOOKUP($U16,[2]Standard_Balanced!$Q$1:$T$542,3,FALSE) -> 0.22222222 | AN16: =VLOOKUP($U16,[2]Standard_Balanced!$Q$1:$T$542,4,FALSE) -> 0 | AO16: =SUM(AL16:AN16) -> 1 | AP16: =SUMPRODUCT($AL$1:$AN$1,AL16:AN16) -> 0.061675 | AQ16: =(1+AP16)^(1/12)-1 -> 0.0049997782 | AR16: 0 | AS16: =IF(AR16=0,0,SUMPRODUCT($AL$3:$AN$3,AL16:AN16)) -> 0 | AT16: =1-(1-AS16)^(1/12) -> 0 | AU16: =SUMPRODUCT($AL$2:$AN$2,AL16:AN16) -> 0.0025 | AV16: =1-(1-AU16)^(1/12) -> 0.00020857243 | AX16: DIS | AY16: Non-Standard | AZ16: =AX16&"_"&AY16&"_"&BA16 -> DIS_Non-Standard_529 | BA16: 529 | BB16: =VLOOKUP($BA16,'[2]NonStandard DIS'!$Q$1:$X$542,2,FALSE) -> 0 | BC16: =VLOOKUP($BA16,'[2]NonStandard DIS'!$Q$1:$X$542,3,FALSE) -> 0 | BD16: =VLOOKUP($BA16,'[2]NonStandard DIS'!$Q$1:$X$542,4,FALSE) -> 0.308 | BE16: =VLOOKUP($BA16,'[2]NonStandard DIS'!$Q$1:$X$542,5,FALSE) -> 0.692 | BF16: =VLOOKUP($BA16,'[2]NonStandard DIS'!$Q$1:$X$542,6,FALSE) -> 0 | BG16: =VLOOKUP($BA16,'[2]NonStandard DIS'!$Q$1:$X$542,7,FALSE) -> 0 | BH16: =VLOOKUP($BA16,'[2]NonStandard DIS'!$Q$1:$X$542,8,FALSE) -> 0 | BI16: =SUM(BB16:BH16) -> 1 | BJ16: =SUMPRODUCT($BB$1:$BH$1,BB16:BH16) -> 0.0697285 | BK16: =(1+BJ16)^(1/12)-1 -> 0.0056328785 | BL16: 0 | BM16: =IF(BL16=0,0,SUMPRODUCT($BB$3:$BH$3,BB16:BH16)) -> 0 | BN16: =(1+BM16)^(1/12)-1 -> 0 | BO16: =SUMPRODUCT($BB$2:$BH$2,BB16:BH16) -> 0.0056776 | BP16: =(1+BO16)^(1/12)-1 -> 0.00047190658
... A436: Lifecycle | B436: Balanced | C436: =A436&"_"&B436&"_"&D436 -> Lifecycle_Balanced_109 | D436: 109 | E436: =VLOOKUP($D436,'[2]LC Balanced'!$Q$2:$U$542,2,FALSE) -> 0.37316667 | F436: =VLOOKUP($D436,'[2]LC Balanced'!$Q$2:$U$542,3,FALSE) -> 0.249 | G436: =VLOOKUP($D436,'[2]LC Balanced'!$Q$2:$U$542,4,FALSE) -> 0.37783333 | H436: =VLOOKUP($D436,'[2]LC Balanced'!$Q$2:$U$542,5,FALSE) -> 0 | I436: =SUM(E436:H436) -> 1 | J436: =SUMPRODUCT($E$1:$H$1,E436:H436) -> 0.051961387 | K436: =(1+J436)^(1/12)-1 -> 0.00423029 | L436: 0 | M436: =IF($L436=0,0,SUMPRODUCT($E$3:$H$3,E436:H436)) -> 0 | N436: =1-(1-M436)^(1/12) -> 0 | O436: =SUMPRODUCT($E$2:$H$2,E436:H436) -> 0.0050851 | P436: =1-(1-O436)^(1/12) -> 0.0004247492 | R436: Autopilot | S436: Balanced | T436: =R436&"_"&S436&"_"&U436 -> Autopilot_Balanced_109 | U436: 109 | V436: =VLOOKUP($U436,'[2]AP Balanced'!$Q$1:$T$542,2,FALSE) -> 0.125437 | W436: =VLOOKUP($U436,'[2]AP Balanced'!$Q$1:$T$542,3,FALSE) -> 0.874563 | X436: =VLOOKUP($U436,'[2]AP Balanced'!$Q$1:$T$542,4,FALSE) -> 0 | Y436: =SUM(V436:X436) -> 1 | Z436: =SUMPRODUCT($V$1:$X$1,V436:X436) -> 0.053015176 | AA436: =(1+Z436)^(1/12)-1 -> 0.0043140828 | AB436: 1 | AC436: =IF($AB436=0,0,SUMPRODUCT($V$3:$X$3,V436:X436)) -> 0.006750874 | AD436: =1-(1-AC436)^(1/12) -> 0.00056432106 | AE436: =SUMPRODUCT($V$2:$X$2,V436:X436) -> 0.0025 | AF436: =1-(1-AE436)^(1/12) -> 0.00020857243 | AH436: Lifecycle | AI436: Balanced | AJ436: =AH436&"_"&AI436&"_"&AK436 -> Lifecycle_Balanced_109 | AK436: 109 | AL436: =VLOOKUP($U436,[2]Standard_Balanced!$Q$1:$T$542,2,FALSE) -> 0.083509247 | AM436: =VLOOKUP($U436,[2]Standard_Balanced!$Q$1:$T$542,3,FALSE) -> 0.91649075 | AN436: =VLOOKUP($U436,[2]Standard_Balanced!$Q$1:$T$542,4,FALSE) -> 0 | AO436: =SUM(AL436:AN436) -> 1 | AP436: =SUMPRODUCT($AL$1:$AN$1,AL436:AN436) -> 0.052458585 | AQ436: =(1+AP436)^(1/12)-1 -> 0.0042698346 | AR436: 0 | AS436: =IF(AR436=0,0,SUMPRODUCT($AL$3:$AN$3,AL436:AN436)) -> 0 | AT436: =1-(1-AS436)^(1/12) -> 0 | AU436: =SUMPRODUCT($AL$2:$AN$2,AL436:AN436) -> 0.0025 | AV436: =1-(1-AU436)^(1/12) -> 0.00020857243 | AX436: DIS | AY436: Non-Standard | AZ436: =AX436&"_"&AY436&"_"&BA436 -> DIS_Non-Standard_109 | BA436: 109 | BB436: =VLOOKUP($BA436,'[2]NonStandard DIS'!$Q$1:$X$542,2,FALSE) -> 0.026916667 | BC436: =VLOOKUP($BA436,'[2]NonStandard DIS'!$Q$1:$X$542,3,FALSE) -> 0.31825 | BD436: =VLOOKUP($BA436,'[2]NonStandard DIS'!$Q$1:$X$542,4,FALSE) -> 0.65483333 | BE436: =VLOOKUP($BA436,'[2]NonStandard DIS'!$Q$1:$X$542,5,FALSE) -> 0 | BF436: =VLOOKUP($BA436,'[2]NonStandard DIS'!$Q$1:$X$542,6,FALSE) -> 0 | BG436: =VLOOKUP($BA436,'[2]NonStandard DIS'!$Q$1:$X$542,7,FALSE) -> 0 | BH436: =VLOOKUP($BA436,'[2]NonStandard DIS'!$Q$1:$X$542,8,FALSE) -> 0 | BI436: =SUM(BB436:BH436) -> 1 | BJ436: =SUMPRODUCT($BB$1:$BH$1,BB436:BH436) -> 0.058396444 | BK436: =(1+BJ436)^(1/12)-1 -> 0.0047407833 | BL436: 0 | BM436: =IF(BL436=0,0,SUMPRODUCT($BB$3:$BH$3,BB436:BH436)) -> 0 | BN436: =(1+BM436)^(1/12)-1 -> 0 | BO436: =SUMPRODUCT($BB$2:$BH$2,BB436:BH436) -> 0.006657075 | BP436: =(1+BO436)^(1/12)-1 -> 0.00055307076
A437: Lifecycle | B437: Balanced | C437: =A437&"_"&B437&"_"&D437 -> Lifecycle_Balanced_108 | D437: 108 | E437: =VLOOKUP($D437,'[2]LC Balanced'!$Q$2:$U$542,2,FALSE) -> 0.377 | F437: =VLOOKUP($D437,'[2]LC Balanced'!$Q$2:$U$542,3,FALSE) -> 0.247 | G437: =VLOOKUP($D437,'[2]LC Balanced'!$Q$2:$U$542,4,FALSE) -> 0.376 | H437: =VLOOKUP($D437,'[2]LC Balanced'!$Q$2:$U$542,5,FALSE) -> 0 | I437: =SUM(E437:H437) -> 1 | J437: =SUMPRODUCT($E$1:$H$1,E437:H437) -> 0.051911975 | K437: =(1+J437)^(1/12)-1 -> 0.004226359 | L437: 0 | M437: =IF($L437=0,0,SUMPRODUCT($E$3:$H$3,E437:H437)) -> 0 | N437: =1-(1-M437)^(1/12) -> 0 | O437: =SUMPRODUCT($E$2:$H$2,E437:H437) -> 0.0050693 | P437: =1-(1-O437)^(1/12) -> 0.00042342637 | R437: Autopilot | S437: Balanced | T437: =R437&"_"&S437&"_"&U437 -> Autopilot_Balanced_108 | U437: 108 | V437: =VLOOKUP($U437,'[2]AP Balanced'!$Q$1:$T$542,2,FALSE) -> 0.079697633 | W437: =VLOOKUP($U437,'[2]AP Balanced'!$Q$1:$T$542,3,FALSE) -> 0.92030237 | X437: =VLOOKUP($U437,'[2]AP Balanced'!$Q$1:$T$542,4,FALSE) -> 0 | Y437: =SUM(V437:X437) -> 1 | Z437: =SUMPRODUCT($V$1:$X$1,V437:X437) -> 0.052407986 | AA437: =(1+Z437)^(1/12)-1 -> 0.004265811 | AB437: 1 | AC437: =IF($AB437=0,0,SUMPRODUCT($V$3:$X$3,V437:X437)) -> 0.0066593953 | AD437: =1-(1-AC437)^(1/12) -> 0.00055665068 | AE437: =SUMPRODUCT($V$2:$X$2,V437:X437) -> 0.0025 | AF437: =1-(1-AE437)^(1/12) -> 0.00020857243 | AH437: Lifecycle | AI437: Balanced | AJ437: =AH437&"_"&AI437&"_"&AK437 -> Lifecycle_Balanced_108 | AK437: 108 | AL437: =VLOOKUP($U437,[2]Standard_Balanced!$Q$1:$T$542,2,FALSE) -> 0.079697633 | AM437: =VLOOKUP($U437,[2]Standard_Balanced!$Q$1:$T$542,3,FALSE) -> 0.92030237 | AN437: =VLOOKUP($U437,[2]Standard_Balanced!$Q$1:$T$542,4,FALSE) -> 0 | AO437: =SUM(AL437:AN437) -> 1 | AP437: =SUMPRODUCT($AL$1:$AN$1,AL437:AN437) -> 0.052407986 | AQ437: =(1+AP437)^(1/12)-1 -> 0.004265811 | AR437: 0 | AS437: =IF(AR437=0,0,SUMPRODUCT($AL$3:$AN$3,AL437:AN437)) -> 0 | AT437: =1-(1-AS437)^(1/12) -> 0 | AU437: =SUMPRODUCT($AL$2:$AN$2,AL437:AN437) -> 0.0025 | AV437: =1-(1-AU437)^(1/12) -> 0.00020857243 | AX437: DIS | AY437: Non-Standard | AZ437: =AX437&"_"&AY437&"_"&BA437 -> DIS_Non-Standard_108 | BA437: 108 | BB437: 0.028 | BC437: 0.323 | BD437: 0.649 | BE437: =VLOOKUP($BA437,'[2]NonStandard DIS'!$Q$1:$X$542,5,FALSE) -> 0 | BF437: =VLOOKUP($BA437,'[2]NonStandard DIS'!$Q$1:$X$542,6,FALSE) -> 0 | BG437: 0 | BH437: =VLOOKUP($BA437,'[2]NonStandard DIS'!$Q$1:$X$542,8,FALSE) -> 0 | BI437: =SUM(BB437:BH437) -> 1 | BJ437: =SUMPRODUCT($BB$1:$BH$1,BB437:BH437) -> 0.0582884 | BK437: =(1+BJ437)^(1/12)-1 -> 0.0047322357 | BL437: 0 | BM437: =IF(BL437=0,0,SUMPRODUCT($BB$3:$BH$3,BB437:BH437)) -> 0 | BN437: =(1+BM437)^(1/12)-1 -> 0 | BO437: =SUMPRODUCT($BB$2:$BH$2,BB437:BH437) -> 0.0066457 | BP437: =(1+BO437)^(1/12)-1 -> 0.00055212859
A438: Lifecycle | B438: Balanced | C438: =A438&"_"&B438&"_"&D438 -> Lifecycle_Balanced_107 | D438: 107 | E438: =VLOOKUP($D438,'[2]LC Balanced'!$Q$2:$U$542,2,FALSE) -> 0.38033333 | F438: =VLOOKUP($D438,'[2]LC Balanced'!$Q$2:$U$542,3,FALSE) -> 0.24533333 | G438: =VLOOKUP($D438,'[2]LC Balanced'!$Q$2:$U$542,4,FALSE) -> 0.37433333 | H438: =VLOOKUP($D438,'[2]LC Balanced'!$Q$2:$U$542,5,FALSE) -> 0 | I438: =SUM(E438:H438) -> 1 | J438: =SUMPRODUCT($E$1:$H$1,E438:H438) -> 0.051867725 | K438: =(1+J438)^(1/12)-1 -> 0.0042228386 | L438: 0 | M438: =IF($L438=0,0,SUMPRODUCT($E$3:$H$3,E438:H438)) -> 0 | N438: =1-(1-M438)^(1/12) -> 0 | O438: =SUMPRODUCT($E$2:$H$2,E438:H438) -> 0.0050554667 | P438: =1-(1-O438)^(1/12) -> 0.00042226822 | R438: Autopilot | S438: Balanced | T438: =R438&"_"&S438&"_"&U438 -> Autopilot_Balanced_107 | U438: 107 | V438: =VLOOKUP($U438,'[2]AP Balanced'!$Q$1:$T$542,2,FALSE) -> 0.079697633 | W438: =VLOOKUP($U438,'[2]AP Balanced'!$Q$1:$T$542,3,FALSE) -> 0.92030237 | X438: =VLOOKUP($U438,'[2]AP Balanced'!$Q$1:$T$542,4,FALSE) -> 0 | Y438: =SUM(V438:X438) -> 1 | Z438: =SUMPRODUCT($V$1:$X$1,V438:X438) -> 0.052407986 | AA438: =(1+Z438)^(1/12)-1 -> 0.004265811 | AB438: 1 | AC438: =IF($AB438=0,0,SUMPRODUCT($V$3:$X$3,V438:X438)) -> 0.0066593953 | AD438: =1-(1-AC438)^(1/12) -> 0.00055665068 | AE438: =SUMPRODUCT($V$2:$X$2,V438:X438) -> 0.0025 | AF438: =1-(1-AE438)^(1/12) -> 0.00020857243 | AH438: Lifecycle | AI438: Balanced | AJ438: =AH438&"_"&AI438&"_"&AK438 -> Lifecycle_Balanced_107 | AK438: 107 | AL438: =VLOOKUP($U438,[2]Standard_Balanced!$Q$1:$T$542,2,FALSE) -> 0.076283408 | AM438: =VLOOKUP($U438,[2]Standard_Balanced!$Q$1:$T$542,3,FALSE) -> 0.92371659 | AN438: =VLOOKUP($U438,[2]Standard_Balanced!$Q$1:$T$542,4,FALSE) -> 0 | AO438: =SUM(AL438:AN438) -> 1 | AP438: =SUMPRODUCT($AL$1:$AN$1,AL438:AN438) -> 0.052362662 | AQ438: =(1+AP438)^(1/12)-1 -> 0.0042622067 | AR438: 0 | AS438: =IF(AR438=0,0,SUMPRODUCT($AL$3:$AN$3,AL438:AN438)) -> 0 | AT438: =1-(1-AS438)^(1/12) -> 0 | AU438: =SUMPRODUCT($AL$2:$AN$2,AL438:AN438) -> 0.0025 | AV438: =1-(1-AU438)^(1/12) -> 0.00020857243 | AX438: DIS | AY438: Non-Standard | AZ438: =AX438&"_"&AY438&"_"&BA438 -> DIS_Non-Standard_107 | BA438: 107 | BB438: 0.025666667 | BC438: 0.29608333 | BD438: 0.59491667 | BE438: =VLOOKUP($BA438,'[2]NonStandard DIS'!$Q$1:$X$542,5,FALSE) -> 0 | BF438: =VLOOKUP($BA438,'[2]NonStandard DIS'!$Q$1:$X$542,6,FALSE) -> 0 | BG438: 0.083333333 | BH438: =VLOOKUP($BA438,'[2]NonStandard DIS'!$Q$1:$X$542,8,FALSE) -> 0 | BI438: =SUM(BB438:BH438) -> 1 | BJ438: =SUMPRODUCT($BB$1:$BH$1,BB438:BH438) -> 0.058201867 | BK438: =(1+BJ438)^(1/12)-1 -> 0.0047253892 | BL438: 0 | BM438: =IF(BL438=0,0,SUMPRODUCT($BB$3:$BH$3,BB438:BH438)) -> 0 | BN438: =(1+BM438)^(1/12)-1 -> 0 | BO438: =SUMPRODUCT($BB$2:$BH$2,BB438:BH438) -> 0.006300225 | BP438: =(1+BO438)^(1/12)-1 -> 0.00052350878
A439: Lifecycle | B439: Balanced | C439: =A439&"_"&B439&"_"&D439 -> Lifecycle_Balanced_106 | D439: 106 | E439: =VLOOKUP($D439,'[2]LC Balanced'!$Q$2:$U$542,2,FALSE) -> 0.38366667 | F439: =VLOOKUP($D439,'[2]LC Balanced'!$Q$2:$U$542,3,FALSE) -> 0.24366667 | G439: =VLOOKUP($D439,'[2]LC Balanced'!$Q$2:$U$542,4,FALSE) -> 0.37266667 | H439: =VLOOKUP($D439,'[2]LC Balanced'!$Q$2:$U$542,5,FALSE) -> 0 | I439: =SUM(E439:H439) -> 1 | J439: =SUMPRODUCT($E$1:$H$1,E439:H439) -> 0.051823475 | K439: =(1+J439)^(1/12)-1 -> 0.0042193181 | L439: 0 | M439: =IF($L439=0,0,SUMPRODUCT($E$3:$H$3,E439:H439)) -> 0 | N439: =1-(1-M439)^(1/12) -> 0 | O439: =SUMPRODUCT($E$2:$H$2,E439:H439) -> 0.0050416333 | P439: =1-(1-O439)^(1/12) -> 0.00042111008 | R439: Autopilot | S439: Balanced | T439: =R439&"_"&S439&"_"&U439 -> Autopilot_Balanced_106 | U439: 106 | V439: =VLOOKUP($U439,'[2]AP Balanced'!$Q$1:$T$542,2,FALSE) -> 0.079697633 | W439: =VLOOKUP($U439,'[2]AP Balanced'!$Q$1:$T$542,3,FALSE) -> 0.92030237 | X439: =VLOOKUP($U439,'[2]AP Balanced'!$Q$1:$T$542,4,FALSE) -> 0 | Y439: =SUM(V439:X439) -> 1 | Z439: =SUMPRODUCT($V$1:$X$1,V439:X439) -> 0.052407986 | AA439: =(1+Z439)^(1/12)-1 -> 0.004265811 | AB439: 1 | AC439: =IF($AB439=0,0,SUMPRODUCT($V$3:$X$3,V439:X439)) -> 0.0066593953 | AD439: =1-(1-AC439)^(1/12) -> 0.00055665068 | AE439: =SUMPRODUCT($V$2:$X$2,V439:X439) -> 0.0025 | AF439: =1-(1-AE439)^(1/12) -> 0.00020857243 | AH439: Lifecycle | AI439: Balanced | AJ439: =AH439&"_"&AI439&"_"&AK439 -> Lifecycle_Balanced_106 | AK439: 106 | AL439: =VLOOKUP($U439,[2]Standard_Balanced!$Q$1:$T$542,2,FALSE) -> 0.072869183 | AM439: =VLOOKUP($U439,[2]Standard_Balanced!$Q$1:$T$542,3,FALSE) -> 0.92713082 | AN439: =VLOOKUP($U439,[2]Standard_Balanced!$Q$1:$T$542,4,FALSE) -> 0 | AO439: =SUM(AL439:AN439) -> 1 | AP439: =SUMPRODUCT($AL$1:$AN$1,AL439:AN439) -> 0.052317338 | AQ439: =(1+AP439)^(1/12)-1 -> 0.0042586023 | AR439: 0 | AS439: =IF(AR439=0,0,SUMPRODUCT($AL$3:$AN$3,AL439:AN439)) -> 0 | AT439: =1-(1-AS439)^(1/12) -> 0 | AU439: =SUMPRODUCT($AL$2:$AN$2,AL439:AN439) -> 0.0025 | AV439: =1-(1-AU439)^(1/12) -> 0.00020857243 | AX439: DIS | AY439: Non-Standard | AZ439: =AX439&"_"&AY439&"_"&BA439 -> DIS_Non-Standard_106 | BA439: 106 | BB439: 0.023333333 | BC439: 0.26916667 | BD439: 0.54083333 | BE439: =VLOOKUP($BA439,'[2]NonStandard DIS'!$Q$1:$X$542,5,FALSE) -> 0 | BF439: =VLOOKUP($BA439,'[2]NonStandard DIS'!$Q$1:$X$542,6,FALSE) -> 0 | BG439: 0.16666667 | BH439: =VLOOKUP($BA439,'[2]NonStandard DIS'!$Q$1:$X$542,8,FALSE) -> 0 | BI439: =SUM(BB439:BH439) -> 1 | BJ439: =SUMPRODUCT($BB$1:$BH$1,BB439:BH439) -> 0.058115333 | BK439: =(1+BJ439)^(1/12)-1 -> 0.0047185423 | BL439: 0 | BM439: =IF(BL439=0,0,SUMPRODUCT($BB$3:$BH$3,BB439:BH439)) -> 0 | BN439: =(1+BM439)^(1/12)-1 -> 0 | BO439: =SUMPRODUCT($BB$2:$BH$2,BB439:BH439) -> 0.00595475 | BP439: =(1+BO439)^(1/12)-1 -> 0.00049487996
A440: Lifecycle | B440: Balanced | C440: =A440&"_"&B440&"_"&D440 -> Lifecycle_Balanced_105 | D440: 105 | E440: =VLOOKUP($D440,'[2]LC Balanced'!$Q$2:$U$542,2,FALSE) -> 0.387 | F440: =VLOOKUP($D440,'[2]LC Balanced'!$Q$2:$U$542,3,FALSE) -> 0.242 | G440: =VLOOKUP($D440,'[2]LC Balanced'!$Q$2:$U$542,4,FALSE) -> 0.371 | H440: =VLOOKUP($D440,'[2]LC Balanced'!$Q$2:$U$542,5,FALSE) -> 0 | I440: =SUM(E440:H440) -> 1 | J440: =SUMPRODUCT($E$1:$H$1,E440:H440) -> 0.051779225 | K440: =(1+J440)^(1/12)-1 -> 0.0042157974 | L440: 0 | M440: =IF($L440=0,0,SUMPRODUCT($E$3:$H$3,E440:H440)) -> 0 | N440: =1-(1-M440)^(1/12) -> 0 | O440: =SUMPRODUCT($E$2:$H$2,E440:H440) -> 0.0050278 | P440: =1-(1-O440)^(1/12) -> 0.00041995195 | R440: Autopilot | S440: Balanced | T440: =R440&"_"&S440&"_"&U440 -> Autopilot_Balanced_105 | U440: 105 | V440: =VLOOKUP($U440,'[2]AP Balanced'!$Q$1:$T$542,2,FALSE) -> 0.079697633 | W440: =VLOOKUP($U440,'[2]AP Balanced'!$Q$1:$T$542,3,FALSE) -> 0.92030237 | X440: =VLOOKUP($U440,'[2]AP Balanced'!$Q$1:$T$542,4,FALSE) -> 0 | Y440: =SUM(V440:X440) -> 1 | Z440: =SUMPRODUCT($V$1:$X$1,V440:X440) -> 0.052407986 | AA440: =(1+Z440)^(1/12)-1 -> 0.004265811 | AB440: 1 | AC440: =IF($AB440=0,0,SUMPRODUCT($V$3:$X$3,V440:X440)) -> 0.0066593953 | AD440: =1-(1-AC440)^(1/12) -> 0.00055665068 | AE440: =SUMPRODUCT($V$2:$X$2,V440:X440) -> 0.0025 | AF440: =1-(1-AE440)^(1/12) -> 0.00020857243 | AH440: Lifecycle | AI440: Balanced | AJ440: =AH440&"_"&AI440&"_"&AK440 -> Lifecycle_Balanced_105 | AK440: 105 | AL440: =VLOOKUP($U440,[2]Standard_Balanced!$Q$1:$T$542,2,FALSE) -> 0.069454958 | AM440: =VLOOKUP($U440,[2]Standard_Balanced!$Q$1:$T$542,3,FALSE) -> 0.93054504 | AN440: =VLOOKUP($U440,[2]Standard_Balanced!$Q$1:$T$542,4,FALSE) -> 0 | AO440: =SUM(AL440:AN440) -> 1 | AP440: =SUMPRODUCT($AL$1:$AN$1,AL440:AN440) -> 0.052272015 | AQ440: =(1+AP440)^(1/12)-1 -> 0.0042549977 | AR440: 0 | AS440: =IF(AR440=0,0,SUMPRODUCT($AL$3:$AN$3,AL440:AN440)) -> 0 | AT440: =1-(1-AS440)^(1/12) -> 0 | AU440: =SUMPRODUCT($AL$2:$AN$2,AL440:AN440) -> 0.0025 | AV440: =1-(1-AU440)^(1/12) -> 0.00020857243 | AX440: DIS | AY440: Non-Standard | AZ440: =AX440&"_"&AY440&"_"&BA440 -> DIS_Non-Standard_105 | BA440: 105 | BB440: 0.021 | BC440: 0.24225 | BD440: 0.48675 | BE440: =VLOOKUP($BA440,'[2]NonStandard DIS'!$Q$1:$X$542,5,FALSE) -> 0 | BF440: =VLOOKUP($BA440,'[2]NonStandard DIS'!$Q$1:$X$542,6,FALSE) -> 0 | BG440: 0.25 | BH440: =VLOOKUP($BA440,'[2]NonStandard DIS'!$Q$1:$X$542,8,FALSE) -> 0 | BI440: =SUM(BB440:BH440) -> 1 | BJ440: =SUMPRODUCT($BB$1:$BH$1,BB440:BH440) -> 0.0580288 | BK440: =(1+BJ440)^(1/12)-1 -> 0.0047116948 | BL440: 0 | BM440: =IF(BL440=0,0,SUMPRODUCT($BB$3:$BH$3,BB440:BH440)) -> 0 | BN440: =(1+BM440)^(1/12)-1 -> 0 | BO440: =SUMPRODUCT($BB$2:$BH$2,BB440:BH440) -> 0.005609275 | BP440: =(1+BO440)^(1/12)-1 -> 0.00046624212
A441: Lifecycle | B441: Balanced | C441: =A441&"_"&B441&"_"&D441 -> Lifecycle_Balanced_104 | D441: 104 | E441: =VLOOKUP($D441,'[2]LC Balanced'!$Q$2:$U$542,2,FALSE) -> 0.39033333 | F441: =VLOOKUP($D441,'[2]LC Balanced'!$Q$2:$U$542,3,FALSE) -> 0.24033333 | G441: =VLOOKUP($D441,'[2]LC Balanced'!$Q$2:$U$542,4,FALSE) -> 0.36933333 | H441: =VLOOKUP($D441,'[2]LC Balanced'!$Q$2:$U$542,5,FALSE) -> 0 | I441: =SUM(E441:H441) -> 1 | J441: =SUMPRODUCT($E$1:$H$1,E441:H441) -> 0.051734975 | K441: =(1+J441)^(1/12)-1 -> 0.0042122766 | L441: 0 | M441: =IF($L441=0,0,SUMPRODUCT($E$3:$H$3,E441:H441)) -> 0 | N441: =1-(1-M441)^(1/12) -> 0 | O441: =SUMPRODUCT($E$2:$H$2,E441:H441) -> 0.0050139667 | P441: =1-(1-O441)^(1/12) -> 0.00041879385 | R441: Autopilot | S441: Balanced | T441: =R441&"_"&S441&"_"&U441 -> Autopilot_Balanced_104 | U441: 104 | V441: =VLOOKUP($U441,'[2]AP Balanced'!$Q$1:$T$542,2,FALSE) -> 0.079697633 | W441: =VLOOKUP($U441,'[2]AP Balanced'!$Q$1:$T$542,3,FALSE) -> 0.92030237 | X441: =VLOOKUP($U441,'[2]AP Balanced'!$Q$1:$T$542,4,FALSE) -> 0 | Y441: =SUM(V441:X441) -> 1 | Z441: =SUMPRODUCT($V$1:$X$1,V441:X441) -> 0.052407986 | AA441: =(1+Z441)^(1/12)-1 -> 0.004265811 | AB441: 1 | AC441: =IF($AB441=0,0,SUMPRODUCT($V$3:$X$3,V441:X441)) -> 0.0066593953 | AD441: =1-(1-AC441)^(1/12) -> 0.00055665068 | AE441: =SUMPRODUCT($V$2:$X$2,V441:X441) -> 0.0025 | AF441: =1-(1-AE441)^(1/12) -> 0.00020857243 | AH441: Lifecycle | AI441: Balanced | AJ441: =AH441&"_"&AI441&"_"&AK441 -> Lifecycle_Balanced_104 | AK441: 104 | AL441: =VLOOKUP($U441,[2]Standard_Balanced!$Q$1:$T$542,2,FALSE) -> 0.066040733 | AM441: =VLOOKUP($U441,[2]Standard_Balanced!$Q$1:$T$542,3,FALSE) -> 0.93395927 | AN441: =VLOOKUP($U441,[2]Standard_Balanced!$Q$1:$T$542,4,FALSE) -> 0 | AO441: =SUM(AL441:AN441) -> 1 | AP441: =SUMPRODUCT($AL$1:$AN$1,AL441:AN441) -> 0.052226691 | AQ441: =(1+AP441)^(1/12)-1 -> 0.004251393 | AR441: 0 | AS441: =IF(AR441=0,0,SUMPRODUCT($AL$3:$AN$3,AL441:AN441)) -> 0 | AT441: =1-(1-AS441)^(1/12) -> 0 | AU441: =SUMPRODUCT($AL$2:$AN$2,AL441:AN441) -> 0.0025 | AV441: =1-(1-AU441)^(1/12) -> 0.00020857243 | AX441: DIS | AY441: Non-Standard | AZ441: =AX441&"_"&AY441&"_"&BA441 -> DIS_Non-Standard_104 | BA441: 104 | BB441: 0.018666667 | BC441: 0.21533333 | BD441: 0.43266667 | BE441: =VLOOKUP($BA441,'[2]NonStandard DIS'!$Q$1:$X$542,5,FALSE) -> 0 | BF441: =VLOOKUP($BA441,'[2]NonStandard DIS'!$Q$1:$X$542,6,FALSE) -> 0 | BG441: 0.33333333 | BH441: =VLOOKUP($BA441,'[2]NonStandard DIS'!$Q$1:$X$542,8,FALSE) -> 0 | BI441: =SUM(BB441:BH441) -> 1 | BJ441: =SUMPRODUCT($BB$1:$BH$1,BB441:BH441) -> 0.057942267 | BK441: =(1+BJ441)^(1/12)-1 -> 0.0047048468 | BL441: 0 | BM441: =IF(BL441=0,0,SUMPRODUCT($BB$3:$BH$3,BB441:BH441)) -> 0 | BN441: =(1+BM441)^(1/12)-1 -> 0 | BO441: =SUMPRODUCT($BB$2:$BH$2,BB441:BH441) -> 0.0052638 | BP441: =(1+BO441)^(1/12)-1 -> 0.00043759527
A442: Lifecycle | B442: Balanced | C442: =A442&"_"&B442&"_"&D442 -> Lifecycle_Balanced_103 | D442: 103 | E442: =VLOOKUP($D442,'[2]LC Balanced'!$Q$2:$U$542,2,FALSE) -> 0.39366667 | F442: =VLOOKUP($D442,'[2]LC Balanced'!$Q$2:$U$542,3,FALSE) -> 0.23866667 | G442: =VLOOKUP($D442,'[2]LC Balanced'!$Q$2:$U$542,4,FALSE) -> 0.36766667 | H442: =VLOOKUP($D442,'[2]LC Balanced'!$Q$2:$U$542,5,FALSE) -> 0 | I442: =SUM(E442:H442) -> 1 | J442: =SUMPRODUCT($E$1:$H$1,E442:H442) -> 0.051690725 | K442: =(1+J442)^(1/12)-1 -> 0.0042087557 | L442: 0 | M442: =IF($L442=0,0,SUMPRODUCT($E$3:$H$3,E442:H442)) -> 0 | N442: =1-(1-M442)^(1/12) -> 0 | O442: =SUMPRODUCT($E$2:$H$2,E442:H442) -> 0.0050001333 | P442: =1-(1-O442)^(1/12) -> 0.00041763575 | R442: Autopilot | S442: Balanced | T442: =R442&"_"&S442&"_"&U442 -> Autopilot_Balanced_103 | U442: 103 | V442: =VLOOKUP($U442,'[2]AP Balanced'!$Q$1:$T$542,2,FALSE) -> 0.079697633 | W442: =VLOOKUP($U442,'[2]AP Balanced'!$Q$1:$T$542,3,FALSE) -> 0.92030237 | X442: =VLOOKUP($U442,'[2]AP Balanced'!$Q$1:$T$542,4,FALSE) -> 0 | Y442: =SUM(V442:X442) -> 1 | Z442: =SUMPRODUCT($V$1:$X$1,V442:X442) -> 0.052407986 | AA442: =(1+Z442)^(1/12)-1 -> 0.004265811 | AB442: 1 | AC442: =IF($AB442=0,0,SUMPRODUCT($V$3:$X$3,V442:X442)) -> 0.0066593953 | AD442: =1-(1-AC442)^(1/12) -> 0.00055665068 | AE442: =SUMPRODUCT($V$2:$X$2,V442:X442) -> 0.0025 | AF442: =1-(1-AE442)^(1/12) -> 0.00020857243 | AH442: Lifecycle | AI442: Balanced | AJ442: =AH442&"_"&AI442&"_"&AK442 -> Lifecycle_Balanced_103 | AK442: 103 | AL442: =VLOOKUP($U442,[2]Standard_Balanced!$Q$1:$T$542,2,FALSE) -> 0.062626508 | AM442: =VLOOKUP($U442,[2]Standard_Balanced!$Q$1:$T$542,3,FALSE) -> 0.93737349 | AN442: =VLOOKUP($U442,[2]Standard_Balanced!$Q$1:$T$542,4,FALSE) -> 0 | AO442: =SUM(AL442:AN442) -> 1 | AP442: =SUMPRODUCT($AL$1:$AN$1,AL442:AN442) -> 0.052181367 | AQ442: =(1+AP442)^(1/12)-1 -> 0.0042477882 | AR442: 0 | AS442: =IF(AR442=0,0,SUMPRODUCT($AL$3:$AN$3,AL442:AN442)) -> 0 | AT442: =1-(1-AS442)^(1/12) -> 0 | AU442: =SUMPRODUCT($AL$2:$AN$2,AL442:AN442) -> 0.0025 | AV442: =1-(1-AU442)^(1/12) -> 0.00020857243 | AX442: DIS | AY442: Non-Standard | AZ442: =AX442&"_"&AY442&"_"&BA442 -> DIS_Non-Standard_103 | BA442: 103 | BB442: 0.016333333 | BC442: 0.18841667 | BD442: 0.37858333 | BE442: =VLOOKUP($BA442,'[2]NonStandard DIS'!$Q$1:$X$542,5,FALSE) -> 0 | BF442: =VLOOKUP($BA442,'[2]NonStandard DIS'!$Q$1:$X$542,6,FALSE) -> 0 | BG442: 0.41666667 | BH442: =VLOOKUP($BA442,'[2]NonStandard DIS'!$Q$1:$X$542,8,FALSE) -> 0 | BI442: =SUM(BB442:BH442) -> 1 | BJ442: =SUMPRODUCT($BB$1:$BH$1,BB442:BH442) -> 0.057855733 | BK442: =(1+BJ442)^(1/12)-1 -> 0.0046979983 | BL442: 0 | BM442: =IF(BL442=0,0,SUMPRODUCT($BB$3:$BH$3,BB442:BH442)) -> 0 | BN442: =(1+BM442)^(1/12)-1 -> 0 | BO442: =SUMPRODUCT($BB$2:$BH$2,BB442:BH442) -> 0.004918325 | BP442: =(1+BO442)^(1/12)-1 -> 0.00040893939
A443: Lifecycle | B443: Balanced | C443: =A443&"_"&B443&"_"&D443 -> Lifecycle_Balanced_102 | D443: 102 | E443: =VLOOKUP($D443,'[2]LC Balanced'!$Q$2:$U$542,2,FALSE) -> 0.397 | F443: =VLOOKUP($D443,'[2]LC Balanced'!$Q$2:$U$542,3,FALSE) -> 0.237 | G443: =VLOOKUP($D443,'[2]LC Balanced'!$Q$2:$U$542,4,FALSE) -> 0.366 | H443: =VLOOKUP($D443,'[2]LC Balanced'!$Q$2:$U$542,5,FALSE) -> 0 | I443: =SUM(E443:H443) -> 1 | J443: =SUMPRODUCT($E$1:$H$1,E443:H443) -> 0.051646475 | K443: =(1+J443)^(1/12)-1 -> 0.0042052346 | L443: 0 | M443: =IF($L443=0,0,SUMPRODUCT($E$3:$H$3,E443:H443)) -> 0 | N443: =1-(1-M443)^(1/12) -> 0 | O443: =SUMPRODUCT($E$2:$H$2,E443:H443) -> 0.0049863 | P443: =1-(1-O443)^(1/12) -> 0.00041647767 | R443: Autopilot | S443: Balanced | T443: =R443&"_"&S443&"_"&U443 -> Autopilot_Balanced_102 | U443: 102 | V443: =VLOOKUP($U443,'[2]AP Balanced'!$Q$1:$T$542,2,FALSE) -> 0.079697633 | W443: =VLOOKUP($U443,'[2]AP Balanced'!$Q$1:$T$542,3,FALSE) -> 0.92030237 | X443: =VLOOKUP($U443,'[2]AP Balanced'!$Q$1:$T$542,4,FALSE) -> 0 | Y443: =SUM(V443:X443) -> 1 | Z443: =SUMPRODUCT($V$1:$X$1,V443:X443) -> 0.052407986 | AA443: =(1+Z443)^(1/12)-1 -> 0.004265811 | AB443: 1 | AC443: =IF($AB443=0,0,SUMPRODUCT($V$3:$X$3,V443:X443)) -> 0.0066593953 | AD443: =1-(1-AC443)^(1/12) -> 0.00055665068 | AE443: =SUMPRODUCT($V$2:$X$2,V443:X443) -> 0.0025 | AF443: =1-(1-AE443)^(1/12) -> 0.00020857243 | AH443: Lifecycle | AI443: Balanced | AJ443: =AH443&"_"&AI443&"_"&AK443 -> Lifecycle_Balanced_102 | AK443: 102 | AL443: =VLOOKUP($U443,[2]Standard_Balanced!$Q$1:$T$542,2,FALSE) -> 0.059212283 | AM443: =VLOOKUP($U443,[2]Standard_Balanced!$Q$1:$T$542,3,FALSE) -> 0.94078772 | AN443: =VLOOKUP($U443,[2]Standard_Balanced!$Q$1:$T$542,4,FALSE) -> 0 | AO443: =SUM(AL443:AN443) -> 1 | AP443: =SUMPRODUCT($AL$1:$AN$1,AL443:AN443) -> 0.052136043 | AQ443: =(1+AP443)^(1/12)-1 -> 0.0042441832 | AR443: 0 | AS443: =IF(AR443=0,0,SUMPRODUCT($AL$3:$AN$3,AL443:AN443)) -> 0 | AT443: =1-(1-AS443)^(1/12) -> 0 | AU443: =SUMPRODUCT($AL$2:$AN$2,AL443:AN443) -> 0.0025 | AV443: =1-(1-AU443)^(1/12) -> 0.00020857243 | AX443: DIS | AY443: Non-Standard | AZ443: =AX443&"_"&AY443&"_"&BA443 -> DIS_Non-Standard_102 | BA443: 102 | BB443: 0.014 | BC443: 0.1615 | BD443: 0.3245 | BE443: =VLOOKUP($BA443,'[2]NonStandard DIS'!$Q$1:$X$542,5,FALSE) -> 0 | BF443: =VLOOKUP($BA443,'[2]NonStandard DIS'!$Q$1:$X$542,6,FALSE) -> 0 | BG443: 0.5 | BH443: =VLOOKUP($BA443,'[2]NonStandard DIS'!$Q$1:$X$542,8,FALSE) -> 0 | BI443: =SUM(BB443:BH443) -> 1 | BJ443: =SUMPRODUCT($BB$1:$BH$1,BB443:BH443) -> 0.0577692 | BK443: =(1+BJ443)^(1/12)-1 -> 0.0046911493 | BL443: 0 | BM443: =IF(BL443=0,0,SUMPRODUCT($BB$3:$BH$3,BB443:BH443)) -> 0 | BN443: =(1+BM443)^(1/12)-1 -> 0 | BO443: =SUMPRODUCT($BB$2:$BH$2,BB443:BH443) -> 0.00457285 | BP443: =(1+BO443)^(1/12)-1 -> 0.00038027448
A444: Lifecycle | B444: Balanced | C444: =A444&"_"&B444&"_"&D444 -> Lifecycle_Balanced_101 | D444: 101 | E444: =VLOOKUP($D444,'[2]LC Balanced'!$Q$2:$U$542,2,FALSE) -> 0.40033333 | F444: =VLOOKUP($D444,'[2]LC Balanced'!$Q$2:$U$542,3,FALSE) -> 0.23533333 | G444: =VLOOKUP($D444,'[2]LC Balanced'!$Q$2:$U$542,4,FALSE) -> 0.36433333 | H444: =VLOOKUP($D444,'[2]LC Balanced'!$Q$2:$U$542,5,FALSE) -> 0 | I444: =SUM(E444:H444) -> 1 | J444: =SUMPRODUCT($E$1:$H$1,E444:H444) -> 0.051602225 | K444: =(1+J444)^(1/12)-1 -> 0.0042017134 | L444: 0 | M444: =IF($L444=0,0,SUMPRODUCT($E$3:$H$3,E444:H444)) -> 0 | N444: =1-(1-M444)^(1/12) -> 0 | O444: =SUMPRODUCT($E$2:$H$2,E444:H444) -> 0.0049724667 | P444: =1-(1-O444)^(1/12) -> 0.00041531961 | R444: Autopilot | S444: Balanced | T444: =R444&"_"&S444&"_"&U444 -> Autopilot_Balanced_101 | U444: 101 | V444: =VLOOKUP($U444,'[2]AP Balanced'!$Q$1:$T$542,2,FALSE) -> 0.079697633 | W444: =VLOOKUP($U444,'[2]AP Balanced'!$Q$1:$T$542,3,FALSE) -> 0.92030237 | X444: =VLOOKUP($U444,'[2]AP Balanced'!$Q$1:$T$542,4,FALSE) -> 0 | Y444: =SUM(V444:X444) -> 1 | Z444: =SUMPRODUCT($V$1:$X$1,V444:X444) -> 0.052407986 | AA444: =(1+Z444)^(1/12)-1 -> 0.004265811 | AB444: 1 | AC444: =IF($AB444=0,0,SUMPRODUCT($V$3:$X$3,V444:X444)) -> 0.0066593953 | AD444: =1-(1-AC444)^(1/12) -> 0.00055665068 | AE444: =SUMPRODUCT($V$2:$X$2,V444:X444) -> 0.0025 | AF444: =1-(1-AE444)^(1/12) -> 0.00020857243 | AH444: Lifecycle | AI444: Balanced | AJ444: =AH444&"_"&AI444&"_"&AK444 -> Lifecycle_Balanced_101 | AK444: 101 | AL444: =VLOOKUP($U444,[2]Standard_Balanced!$Q$1:$T$542,2,FALSE) -> 0.055798058 | AM444: =VLOOKUP($U444,[2]Standard_Balanced!$Q$1:$T$542,3,FALSE) -> 0.94420194 | AN444: =VLOOKUP($U444,[2]Standard_Balanced!$Q$1:$T$542,4,FALSE) -> 0 | AO444: =SUM(AL444:AN444) -> 1 | AP444: =SUMPRODUCT($AL$1:$AN$1,AL444:AN444) -> 0.052090719 | AQ444: =(1+AP444)^(1/12)-1 -> 0.004240578 | AR444: 0 | AS444: =IF(AR444=0,0,SUMPRODUCT($AL$3:$AN$3,AL444:AN444)) -> 0 | AT444: =1-(1-AS444)^(1/12) -> 0 | AU444: =SUMPRODUCT($AL$2:$AN$2,AL444:AN444) -> 0.0025 | AV444: =1-(1-AU444)^(1/12) -> 0.00020857243 | AX444: DIS | AY444: Non-Standard | AZ444: =AX444&"_"&AY444&"_"&BA444 -> DIS_Non-Standard_101 | BA444: 101 | BB444: 0.011666667 | BC444: 0.13458333 | BD444: 0.27041667 | BE444: =VLOOKUP($BA444,'[2]NonStandard DIS'!$Q$1:$X$542,5,FALSE) -> 0 | BF444: =VLOOKUP($BA444,'[2]NonStandard DIS'!$Q$1:$X$542,6,FALSE) -> 0 | BG444: 0.58333333 | BH444: =VLOOKUP($BA444,'[2]NonStandard DIS'!$Q$1:$X$542,8,FALSE) -> 0 | BI444: =SUM(BB444:BH444) -> 1 | BJ444: =SUMPRODUCT($BB$1:$BH$1,BB444:BH444) -> 0.057682667 | BK444: =(1+BJ444)^(1/12)-1 -> 0.0046842998 | BL444: 0 | BM444: =IF(BL444=0,0,SUMPRODUCT($BB$3:$BH$3,BB444:BH444)) -> 0 | BN444: =(1+BM444)^(1/12)-1 -> 0 | BO444: =SUMPRODUCT($BB$2:$BH$2,BB444:BH444) -> 0.004227375 | BP444: =(1+BO444)^(1/12)-1 -> 0.00035160053
A445: Lifecycle | B445: Balanced | C445: =A445&"_"&B445&"_"&D445 -> Lifecycle_Balanced_100 | D445: 100 | E445: =VLOOKUP($D445,'[2]LC Balanced'!$Q$2:$U$542,2,FALSE) -> 0.40366667 | F445: =VLOOKUP($D445,'[2]LC Balanced'!$Q$2:$U$542,3,FALSE) -> 0.23366667 | G445: =VLOOKUP($D445,'[2]LC Balanced'!$Q$2:$U$542,4,FALSE) -> 0.36266667 | H445: =VLOOKUP($D445,'[2]LC Balanced'!$Q$2:$U$542,5,FALSE) -> 0 | I445: =SUM(E445:H445) -> 1 | J445: =SUMPRODUCT($E$1:$H$1,E445:H445) -> 0.051557975 | K445: =(1+J445)^(1/12)-1 -> 0.004198192 | L445: 0 | M445: =IF($L445=0,0,SUMPRODUCT($E$3:$H$3,E445:H445)) -> 0 | N445: =1-(1-M445)^(1/12) -> 0 | O445: =SUMPRODUCT($E$2:$H$2,E445:H445) -> 0.0049586333 | P445: =1-(1-O445)^(1/12) -> 0.00041416156 | R445: Autopilot | S445: Balanced | T445: =R445&"_"&S445&"_"&U445 -> Autopilot_Balanced_100 | U445: 100 | V445: =VLOOKUP($U445,'[2]AP Balanced'!$Q$1:$T$542,2,FALSE) -> 0.079697633 | W445: =VLOOKUP($U445,'[2]AP Balanced'!$Q$1:$T$542,3,FALSE) -> 0.92030237 | X445: =VLOOKUP($U445,'[2]AP Balanced'!$Q$1:$T$542,4,FALSE) -> 0 | Y445: =SUM(V445:X445) -> 1 | Z445: =SUMPRODUCT($V$1:$X$1,V445:X445) -> 0.052407986 | AA445: =(1+Z445)^(1/12)-1 -> 0.004265811 | AB445: 1 | AC445: =IF($AB445=0,0,SUMPRODUCT($V$3:$X$3,V445:X445)) -> 0.0066593953 | AD445: =1-(1-AC445)^(1/12) -> 0.00055665068 | AE445: =SUMPRODUCT($V$2:$X$2,V445:X445) -> 0.0025 | AF445: =1-(1-AE445)^(1/12) -> 0.00020857243 | AH445: Lifecycle | AI445: Balanced | AJ445: =AH445&"_"&AI445&"_"&AK445 -> Lifecycle_Balanced_100 | AK445: 100 | AL445: =VLOOKUP($U445,[2]Standard_Balanced!$Q$1:$T$542,2,FALSE) -> 0.052383833 | AM445: =VLOOKUP($U445,[2]Standard_Balanced!$Q$1:$T$542,3,FALSE) -> 0.94761617 | AN445: =VLOOKUP($U445,[2]Standard_Balanced!$Q$1:$T$542,4,FALSE) -> 0 | AO445: =SUM(AL445:AN445) -> 1 | AP445: =SUMPRODUCT($AL$1:$AN$1,AL445:AN445) -> 0.052045395 | AQ445: =(1+AP445)^(1/12)-1 -> 0.0042369728 | AR445: 0 | AS445: =IF(AR445=0,0,SUMPRODUCT($AL$3:$AN$3,AL445:AN445)) -> 0 | AT445: =1-(1-AS445)^(1/12) -> 0 | AU445: =SUMPRODUCT($AL$2:$AN$2,AL445:AN445) -> 0.0025 | AV445: =1-(1-AU445)^(1/12) -> 0.00020857243 | AX445: DIS | AY445: Non-Standard | AZ445: =AX445&"_"&AY445&"_"&BA445 -> DIS_Non-Standard_100 | BA445: 100 | BB445: 0.0093333333 | BC445: 0.10766667 | BD445: 0.21633333 | BE445: =VLOOKUP($BA445,'[2]NonStandard DIS'!$Q$1:$X$542,5,FALSE) -> 0 | BF445: =VLOOKUP($BA445,'[2]NonStandard DIS'!$Q$1:$X$542,6,FALSE) -> 0 | BG445: 0.66666667 | BH445: =VLOOKUP($BA445,'[2]NonStandard DIS'!$Q$1:$X$542,8,FALSE) -> 0 | BI445: =SUM(BB445:BH445) -> 1 | BJ445: =SUMPRODUCT($BB$1:$BH$1,BB445:BH445) -> 0.057596133 | BK445: =(1+BJ445)^(1/12)-1 -> 0.0046774498 | BL445: 0 | BM445: =IF(BL445=0,0,SUMPRODUCT($BB$3:$BH$3,BB445:BH445)) -> 0 | BN445: =(1+BM445)^(1/12)-1 -> 0 | BO445: =SUMPRODUCT($BB$2:$BH$2,BB445:BH445) -> 0.0038819 | BP445: =(1+BO445)^(1/12)-1 -> 0.00032291753
A446: Lifecycle | B446: Balanced | C446: =A446&"_"&B446&"_"&D446 -> Lifecycle_Balanced_99 | D446: 99 | E446: =VLOOKUP($D446,'[2]LC Balanced'!$Q$2:$U$542,2,FALSE) -> 0.407 | F446: =VLOOKUP($D446,'[2]LC Balanced'!$Q$2:$U$542,3,FALSE) -> 0.232 | G446: =VLOOKUP($D446,'[2]LC Balanced'!$Q$2:$U$542,4,FALSE) -> 0.361 | H446: =VLOOKUP($D446,'[2]LC Balanced'!$Q$2:$U$542,5,FALSE) -> 0 | I446: =SUM(E446:H446) -> 1 | J446: =SUMPRODUCT($E$1:$H$1,E446:H446) -> 0.051513725 | K446: =(1+J446)^(1/12)-1 -> 0.0041946705 | L446: 0 | M446: =IF($L446=0,0,SUMPRODUCT($E$3:$H$3,E446:H446)) -> 0 | N446: =1-(1-M446)^(1/12) -> 0 | O446: =SUMPRODUCT($E$2:$H$2,E446:H446) -> 0.0049448 | P446: =1-(1-O446)^(1/12) -> 0.00041300352 | R446: Autopilot | S446: Balanced | T446: =R446&"_"&S446&"_"&U446 -> Autopilot_Balanced_99 | U446: 99 | V446: =VLOOKUP($U446,'[2]AP Balanced'!$Q$1:$T$542,2,FALSE) -> 0.079697633 | W446: =VLOOKUP($U446,'[2]AP Balanced'!$Q$1:$T$542,3,FALSE) -> 0.92030237 | X446: =VLOOKUP($U446,'[2]AP Balanced'!$Q$1:$T$542,4,FALSE) -> 0 | Y446: =SUM(V446:X446) -> 1 | Z446: =SUMPRODUCT($V$1:$X$1,V446:X446) -> 0.052407986 | AA446: =(1+Z446)^(1/12)-1 -> 0.004265811 | AB446: 1 | AC446: =IF($AB446=0,0,SUMPRODUCT($V$3:$X$3,V446:X446)) -> 0.0066593953 | AD446: =1-(1-AC446)^(1/12) -> 0.00055665068 | AE446: =SUMPRODUCT($V$2:$X$2,V446:X446) -> 0.0025 | AF446: =1-(1-AE446)^(1/12) -> 0.00020857243 | AH446: Lifecycle | AI446: Balanced | AJ446: =AH446&"_"&AI446&"_"&AK446 -> Lifecycle_Balanced_99 | AK446: 99 | AL446: =VLOOKUP($U446,[2]Standard_Balanced!$Q$1:$T$542,2,FALSE) -> 0.048969608 | AM446: =VLOOKUP($U446,[2]Standard_Balanced!$Q$1:$T$542,3,FALSE) -> 0.95103039 | AN446: =VLOOKUP($U446,[2]Standard_Balanced!$Q$1:$T$542,4,FALSE) -> 0 | AO446: =SUM(AL446:AN446) -> 1 | AP446: =SUMPRODUCT($AL$1:$AN$1,AL446:AN446) -> 0.052000072 | AQ446: =(1+AP446)^(1/12)-1 -> 0.0042333674 | AR446: 0 | AS446: =IF(AR446=0,0,SUMPRODUCT($AL$3:$AN$3,AL446:AN446)) -> 0 | AT446: =1-(1-AS446)^(1/12) -> 0 | AU446: =SUMPRODUCT($AL$2:$AN$2,AL446:AN446) -> 0.0025 | AV446: =1-(1-AU446)^(1/12) -> 0.00020857243 | AX446: DIS | AY446: Non-Standard | AZ446: =AX446&"_"&AY446&"_"&BA446 -> DIS_Non-Standard_99 | BA446: 99 | BB446: 0.007 | BC446: 0.08075 | BD446: 0.16225 | BE446: =VLOOKUP($BA446,'[2]NonStandard DIS'!$Q$1:$X$542,5,FALSE) -> 0 | BF446: =VLOOKUP($BA446,'[2]NonStandard DIS'!$Q$1:$X$542,6,FALSE) -> 0 | BG446: 0.75 | BH446: =VLOOKUP($BA446,'[2]NonStandard DIS'!$Q$1:$X$542,8,FALSE) -> 0 | BI446: =SUM(BB446:BH446) -> 1 | BJ446: =SUMPRODUCT($BB$1:$BH$1,BB446:BH446) -> 0.0575096 | BK446: =(1+BJ446)^(1/12)-1 -> 0.0046705992 | BL446: 0 | BM446: =IF(BL446=0,0,SUMPRODUCT($BB$3:$BH$3,BB446:BH446)) -> 0 | BN446: =(1+BM446)^(1/12)-1 -> 0 | BO446: =SUMPRODUCT($BB$2:$BH$2,BB446:BH446) -> 0.003536425 | BP446: =(1+BO446)^(1/12)-1 -> 0.00029422549
A447: Lifecycle | B447: Balanced | C447: =A447&"_"&B447&"_"&D447 -> Lifecycle_Balanced_98 | D447: 98 | E447: =VLOOKUP($D447,'[2]LC Balanced'!$Q$2:$U$542,2,FALSE) -> 0.41033333 | F447: =VLOOKUP($D447,'[2]LC Balanced'!$Q$2:$U$542,3,FALSE) -> 0.23033333 | G447: =VLOOKUP($D447,'[2]LC Balanced'!$Q$2:$U$542,4,FALSE) -> 0.35933333 | H447: =VLOOKUP($D447,'[2]LC Balanced'!$Q$2:$U$542,5,FALSE) -> 0 | I447: =SUM(E447:H447) -> 1 | J447: =SUMPRODUCT($E$1:$H$1,E447:H447) -> 0.051469475 | K447: =(1+J447)^(1/12)-1 -> 0.0041911489 | L447: 0 | M447: =IF($L447=0,0,SUMPRODUCT($E$3:$H$3,E447:H447)) -> 0 | N447: =1-(1-M447)^(1/12) -> 0 | O447: =SUMPRODUCT($E$2:$H$2,E447:H447) -> 0.0049309667 | P447: =1-(1-O447)^(1/12) -> 0.0004118455 | R447: Autopilot | S447: Balanced | T447: =R447&"_"&S447&"_"&U447 -> Autopilot_Balanced_98 | U447: 98 | V447: =VLOOKUP($U447,'[2]AP Balanced'!$Q$1:$T$542,2,FALSE) -> 0.079697633 | W447: =VLOOKUP($U447,'[2]AP Balanced'!$Q$1:$T$542,3,FALSE) -> 0.92030237 | X447: =VLOOKUP($U447,'[2]AP Balanced'!$Q$1:$T$542,4,FALSE) -> 0 | Y447: =SUM(V447:X447) -> 1 | Z447: =SUMPRODUCT($V$1:$X$1,V447:X447) -> 0.052407986 | AA447: =(1+Z447)^(1/12)-1 -> 0.004265811 | AB447: 1 | AC447: =IF($AB447=0,0,SUMPRODUCT($V$3:$X$3,V447:X447)) -> 0.0066593953 | AD447: =1-(1-AC447)^(1/12) -> 0.00055665068 | AE447: =SUMPRODUCT($V$2:$X$2,V447:X447) -> 0.0025 | AF447: =1-(1-AE447)^(1/12) -> 0.00020857243 | AH447: Lifecycle | AI447: Balanced | AJ447: =AH447&"_"&AI447&"_"&AK447 -> Lifecycle_Balanced_98 | AK447: 98 | AL447: =VLOOKUP($U447,[2]Standard_Balanced!$Q$1:$T$542,2,FALSE) -> 0.045555383 | AM447: =VLOOKUP($U447,[2]Standard_Balanced!$Q$1:$T$542,3,FALSE) -> 0.95444462 | AN447: =VLOOKUP($U447,[2]Standard_Balanced!$Q$1:$T$542,4,FALSE) -> 0 | AO447: =SUM(AL447:AN447) -> 1 | AP447: =SUMPRODUCT($AL$1:$AN$1,AL447:AN447) -> 0.051954748 | AQ447: =(1+AP447)^(1/12)-1 -> 0.0042297618 | AR447: 0 | AS447: =IF(AR447=0,0,SUMPRODUCT($AL$3:$AN$3,AL447:AN447)) -> 0 | AT447: =1-(1-AS447)^(1/12) -> 0 | AU447: =SUMPRODUCT($AL$2:$AN$2,AL447:AN447) -> 0.0025 | AV447: =1-(1-AU447)^(1/12) -> 0.00020857243 | AX447: DIS | AY447: Non-Standard | AZ447: =AX447&"_"&AY447&"_"&BA447 -> DIS_Non-Standard_98 | BA447: 98 | BB447: 0.0046666667 | BC447: 0.053833333 | BD447: 0.10816667 | BE447: =VLOOKUP($BA447,'[2]NonStandard DIS'!$Q$1:$X$542,5,FALSE) -> 0 | BF447: =VLOOKUP($BA447,'[2]NonStandard DIS'!$Q$1:$X$542,6,FALSE) -> 0 | BG447: 0.83333333 | BH447: =VLOOKUP($BA447,'[2]NonStandard DIS'!$Q$1:$X$542,8,FALSE) -> 0 | BI447: =SUM(BB447:BH447) -> 1 | BJ447: =SUMPRODUCT($BB$1:$BH$1,BB447:BH447) -> 0.057423067 | BK447: =(1+BJ447)^(1/12)-1 -> 0.0046637482 | BL447: 0 | BM447: =IF(BL447=0,0,SUMPRODUCT($BB$3:$BH$3,BB447:BH447)) -> 0 | BN447: =(1+BM447)^(1/12)-1 -> 0 | BO447: =SUMPRODUCT($BB$2:$BH$2,BB447:BH447) -> 0.00319095 | BP447: =(1+BO447)^(1/12)-1 -> 0.00026552439
A448: Lifecycle | B448: Balanced | C448: =A448&"_"&B448&"_"&D448 -> Lifecycle_Balanced_97 | D448: 97 | E448: =VLOOKUP($D448,'[2]LC Balanced'!$Q$2:$U$542,2,FALSE) -> 0.41366667 | F448: =VLOOKUP($D448,'[2]LC Balanced'!$Q$2:$U$542,3,FALSE) -> 0.22866667 | G448: =VLOOKUP($D448,'[2]LC Balanced'!$Q$2:$U$542,4,FALSE) -> 0.35766667 | H448: =VLOOKUP($D448,'[2]LC Balanced'!$Q$2:$U$542,5,FALSE) -> 0 | I448: =SUM(E448:H448) -> 1 | J448: =SUMPRODUCT($E$1:$H$1,E448:H448) -> 0.051425225 | K448: =(1+J448)^(1/12)-1 -> 0.0041876271 | L448: 0 | M448: =IF($L448=0,0,SUMPRODUCT($E$3:$H$3,E448:H448)) -> 0 | N448: =1-(1-M448)^(1/12) -> 0 | O448: =SUMPRODUCT($E$2:$H$2,E448:H448) -> 0.0049171333 | P448: =1-(1-O448)^(1/12) -> 0.0004106875 | R448: Autopilot | S448: Balanced | T448: =R448&"_"&S448&"_"&U448 -> Autopilot_Balanced_97 | U448: 97 | V448: =VLOOKUP($U448,'[2]AP Balanced'!$Q$1:$T$542,2,FALSE) -> 0.079697633 | W448: =VLOOKUP($U448,'[2]AP Balanced'!$Q$1:$T$542,3,FALSE) -> 0.92030237 | X448: =VLOOKUP($U448,'[2]AP Balanced'!$Q$1:$T$542,4,FALSE) -> 0 | Y448: =SUM(V448:X448) -> 1 | Z448: =SUMPRODUCT($V$1:$X$1,V448:X448) -> 0.052407986 | AA448: =(1+Z448)^(1/12)-1 -> 0.004265811 | AB448: 1 | AC448: =IF($AB448=0,0,SUMPRODUCT($V$3:$X$3,V448:X448)) -> 0.0066593953 | AD448: =1-(1-AC448)^(1/12) -> 0.00055665068 | AE448: =SUMPRODUCT($V$2:$X$2,V448:X448) -> 0.0025 | AF448: =1-(1-AE448)^(1/12) -> 0.00020857243 | AH448: Lifecycle | AI448: Balanced | AJ448: =AH448&"_"&AI448&"_"&AK448 -> Lifecycle_Balanced_97 | AK448: 97 | AL448: =VLOOKUP($U448,[2]Standard_Balanced!$Q$1:$T$542,2,FALSE) -> 0.042141158 | AM448: =VLOOKUP($U448,[2]Standard_Balanced!$Q$1:$T$542,3,FALSE) -> 0.95785884 | AN448: =VLOOKUP($U448,[2]Standard_Balanced!$Q$1:$T$542,4,FALSE) -> 0 | AO448: =SUM(AL448:AN448) -> 1 | AP448: =SUMPRODUCT($AL$1:$AN$1,AL448:AN448) -> 0.051909424 | AQ448: =(1+AP448)^(1/12)-1 -> 0.0042261561 | AR448: 0 | AS448: =IF(AR448=0,0,SUMPRODUCT($AL$3:$AN$3,AL448:AN448)) -> 0 | AT448: =1-(1-AS448)^(1/12) -> 0 | AU448: =SUMPRODUCT($AL$2:$AN$2,AL448:AN448) -> 0.0025 | AV448: =1-(1-AU448)^(1/12) -> 0.00020857243 | AX448: DIS | AY448: Non-Standard | AZ448: =AX448&"_"&AY448&"_"&BA448 -> DIS_Non-Standard_97 | BA448: 97 | BB448: 0.0023333333 | BC448: 0.026916667 | BD448: 0.054083333 | BE448: =VLOOKUP($BA448,'[2]NonStandard DIS'!$Q$1:$X$542,5,FALSE) -> 0 | BF448: =VLOOKUP($BA448,'[2]NonStandard DIS'!$Q$1:$X$542,6,FALSE) -> 0 | BG448: 0.91666667 | BH448: =VLOOKUP($BA448,'[2]NonStandard DIS'!$Q$1:$X$542,8,FALSE) -> 0 | BI448: =SUM(BB448:BH448) -> 1 | BJ448: =SUMPRODUCT($BB$1:$BH$1,BB448:BH448) -> 0.057336533 | BK448: =(1+BJ448)^(1/12)-1 -> 0.0046568966 | BL448: 0 | BM448: =IF(BL448=0,0,SUMPRODUCT($BB$3:$BH$3,BB448:BH448)) -> 0 | BN448: =(1+BM448)^(1/12)-1 -> 0 | BO448: =SUMPRODUCT($BB$2:$BH$2,BB448:BH448) -> 0.002845475 | BP448: =(1+BO448)^(1/12)-1 -> 0.00023681423
A449: Lifecycle | B449: Balanced | C449: =A449&"_"&B449&"_"&D449 -> Lifecycle_Balanced_96 | D449: 96 | E449: =VLOOKUP($D449,'[2]LC Balanced'!$Q$2:$U$542,2,FALSE) -> 0.417 | F449: =VLOOKUP($D449,'[2]LC Balanced'!$Q$2:$U$542,3,FALSE) -> 0.227 | G449: =VLOOKUP($D449,'[2]LC Balanced'!$Q$2:$U$542,4,FALSE) -> 0.356 | H449: =VLOOKUP($D449,'[2]LC Balanced'!$Q$2:$U$542,5,FALSE) -> 0 | I449: =SUM(E449:H449) -> 1 | J449: =SUMPRODUCT($E$1:$H$1,E449:H449) -> 0.051380975 | K449: =(1+J449)^(1/12)-1 -> 0.0041841052 | L449: 0 | M449: =IF($L449=0,0,SUMPRODUCT($E$3:$H$3,E449:H449)) -> 0 | N449: =1-(1-M449)^(1/12) -> 0 | O449: =SUMPRODUCT($E$2:$H$2,E449:H449) -> 0.0049033 | P449: =1-(1-O449)^(1/12) -> 0.0004095295 | R449: Autopilot | S449: Balanced | T449: =R449&"_"&S449&"_"&U449 -> Autopilot_Balanced_96 | U449: 96 | V449: =VLOOKUP($U449,'[2]AP Balanced'!$Q$1:$T$542,2,FALSE) -> 0.038726933 | W449: =VLOOKUP($U449,'[2]AP Balanced'!$Q$1:$T$542,3,FALSE) -> 0.96127307 | X449: =VLOOKUP($U449,'[2]AP Balanced'!$Q$1:$T$542,4,FALSE) -> 0 | Y449: =SUM(V449:X449) -> 1 | Z449: =SUMPRODUCT($V$1:$X$1,V449:X449) -> 0.0518641 | AA449: =(1+Z449)^(1/12)-1 -> 0.0042225502 | AB449: 1 | AC449: =IF($AB449=0,0,SUMPRODUCT($V$3:$X$3,V449:X449)) -> 0.0065774539 | AD449: =1-(1-AC449)^(1/12) -> 0.00054978054 | AE449: =SUMPRODUCT($V$2:$X$2,V449:X449) -> 0.0025 | AF449: =1-(1-AE449)^(1/12) -> 0.00020857243 | AH449: Lifecycle | AI449: Balanced | AJ449: =AH449&"_"&AI449&"_"&AK449 -> Lifecycle_Balanced_96 | AK449: 96 | AL449: =VLOOKUP($U449,[2]Standard_Balanced!$Q$1:$T$542,2,FALSE) -> 0.038726933 | AM449: =VLOOKUP($U449,[2]Standard_Balanced!$Q$1:$T$542,3,FALSE) -> 0.96127307 | AN449: =VLOOKUP($U449,[2]Standard_Balanced!$Q$1:$T$542,4,FALSE) -> 0 | AO449: =SUM(AL449:AN449) -> 1 | AP449: =SUMPRODUCT($AL$1:$AN$1,AL449:AN449) -> 0.0518641 | AQ449: =(1+AP449)^(1/12)-1 -> 0.0042225502 | AR449: 0 | AS449: =IF(AR449=0,0,SUMPRODUCT($AL$3:$AN$3,AL449:AN449)) -> 0 | AT449: =1-(1-AS449)^(1/12) -> 0 | AU449: =SUMPRODUCT($AL$2:$AN$2,AL449:AN449) -> 0.0025 | AV449: =1-(1-AU449)^(1/12) -> 0.00020857243 | AX449: DIS | AY449: Non-Standard | AZ449: =AX449&"_"&AY449&"_"&BA449 -> DIS_Non-Standard_96 | BA449: 96 | BB449: =VLOOKUP($BA449,'[2]NonStandard DIS'!$Q$1:$X$542,2,FALSE) -> 0 | BC449: =VLOOKUP($BA449,'[2]NonStandard DIS'!$Q$1:$X$542,3,FALSE) -> 0 | BD449: =VLOOKUP($BA449,'[2]NonStandard DIS'!$Q$1:$X$542,4,FALSE) -> 0 | BE449: =VLOOKUP($BA449,'[2]NonStandard DIS'!$Q$1:$X$542,5,FALSE) -> 0 | BF449: =VLOOKUP($BA449,'[2]NonStandard DIS'!$Q$1:$X$542,6,FALSE) -> 0 | BG449: =VLOOKUP($BA449,'[2]NonStandard DIS'!$Q$1:$X$542,7,FALSE) -> 1 | BH449: =VLOOKUP($BA449,'[2]NonStandard DIS'!$Q$1:$X$542,8,FALSE) -> 0 | BI449: =SUM(BB449:BH449) -> 1 | BJ449: =SUMPRODUCT($BB$1:$BH$1,BB449:BH449) -> 0.05725 | BK449: =(1+BJ449)^(1/12)-1 -> 0.0046500445 | BL449: 1 | BM449: =IF(BL449=0,0,SUMPRODUCT($BB$3:$BH$3,BB449:BH449)) -> 0.0075 | BN449: =(1+BM449)^(1/12)-1 -> 0.0006228618 | BO449: =SUMPRODUCT($BB$2:$BH$2,BB449:BH449) -> 0.0025 | BP449: =(1+BO449)^(1/12)-1 -> 0.000208095
A450: Lifecycle | B450: Balanced | C450: =A450&"_"&B450&"_"&D450 -> Lifecycle_Balanced_95 | D450: 95 | E450: =VLOOKUP($D450,'[2]LC Balanced'!$Q$2:$U$542,2,FALSE) -> 0.41991667 | F450: =VLOOKUP($D450,'[2]LC Balanced'!$Q$2:$U$542,3,FALSE) -> 0.22541667 | G450: =VLOOKUP($D450,'[2]LC Balanced'!$Q$2:$U$542,4,FALSE) -> 0.35466667 | H450: =VLOOKUP($D450,'[2]LC Balanced'!$Q$2:$U$542,5,FALSE) -> 0 | I450: =SUM(E450:H450) -> 1 | J450: =SUMPRODUCT($E$1:$H$1,E450:H450) -> 0.051344469 | K450: =(1+J450)^(1/12)-1 -> 0.0041811996 | L450: 0 | M450: =IF($L450=0,0,SUMPRODUCT($E$3:$H$3,E450:H450)) -> 0 | N450: =1-(1-M450)^(1/12) -> 0 | O450: =SUMPRODUCT($E$2:$H$2,E450:H450) -> 0.0048913583 | P450: =1-(1-O450)^(1/12) -> 0.00040852988 | R450: Autopilot | S450: Balanced | T450: =R450&"_"&S450&"_"&U450 -> Autopilot_Balanced_95 | U450: 95 | V450: =VLOOKUP($U450,'[2]AP Balanced'!$Q$1:$T$542,2,FALSE) -> 0.038726933 | W450: =VLOOKUP($U450,'[2]AP Balanced'!$Q$1:$T$542,3,FALSE) -> 0.96127307 | X450: =VLOOKUP($U450,'[2]AP Balanced'!$Q$1:$T$542,4,FALSE) -> 0 | Y450: =SUM(V450:X450) -> 1 | Z450: =SUMPRODUCT($V$1:$X$1,V450:X450) -> 0.0518641 | AA450: =(1+Z450)^(1/12)-1 -> 0.0042225502 | AB450: 1 | AC450: =IF($AB450=0,0,SUMPRODUCT($V$3:$X$3,V450:X450)) -> 0.0065774539 | AD450: =1-(1-AC450)^(1/12) -> 0.00054978054 | AE450: =SUMPRODUCT($V$2:$X$2,V450:X450) -> 0.0025 | AF450: =1-(1-AE450)^(1/12) -> 0.00020857243 | AH450: Lifecycle | AI450: Balanced | AJ450: =AH450&"_"&AI450&"_"&AK450 -> Lifecycle_Balanced_95 | AK450: 95 | AL450: =VLOOKUP($U450,[2]Standard_Balanced!$Q$1:$T$542,2,FALSE) -> 0.035917433 | AM450: =VLOOKUP($U450,[2]Standard_Balanced!$Q$1:$T$542,3,FALSE) -> 0.96408257 | AN450: =VLOOKUP($U450,[2]Standard_Balanced!$Q$1:$T$542,4,FALSE) -> 0 | AO450: =SUM(AL450:AN450) -> 1 | AP450: =SUMPRODUCT($AL$1:$AN$1,AL450:AN450) -> 0.051826804 | AQ450: =(1+AP450)^(1/12)-1 -> 0.004219583 | AR450: 0 | AS450: =IF(AR450=0,0,SUMPRODUCT($AL$3:$AN$3,AL450:AN450)) -> 0 | AT450: =1-(1-AS450)^(1/12) -> 0 | AU450: =SUMPRODUCT($AL$2:$AN$2,AL450:AN450) -> 0.0025 | AV450: =1-(1-AU450)^(1/12) -> 0.00020857243 | AX450: DIS | AY450: Non-Standard | AZ450: =AX450&"_"&AY450&"_"&BA450 -> DIS_Non-Standard_95 | BA450: 95 | BB450: =VLOOKUP($BA450,'[2]NonStandard DIS'!$Q$1:$X$542,2,FALSE) -> 0 | BC450: =VLOOKUP($BA450,'[2]NonStandard DIS'!$Q$1:$X$542,3,FALSE) -> 0 | BD450: =VLOOKUP($BA450,'[2]NonStandard DIS'!$Q$1:$X$542,4,FALSE) -> 0 | BE450: =VLOOKUP($BA450,'[2]NonStandard DIS'!$Q$1:$X$542,5,FALSE) -> 0 | BF450: =VLOOKUP($BA450,'[2]NonStandard DIS'!$Q$1:$X$542,6,FALSE) -> 0 | BG450: =VLOOKUP($BA450,'[2]NonStandard DIS'!$Q$1:$X$542,7,FALSE) -> 1 | BH450: =VLOOKUP($BA450,'[2]NonStandard DIS'!$Q$1:$X$542,8,FALSE) -> 0 | BI450: =SUM(BB450:BH450) -> 1 | BJ450: =SUMPRODUCT($BB$1:$BH$1,BB450:BH450) -> 0.05725 | BK450: =(1+BJ450)^(1/12)-1 -> 0.0046500445 | BL450: 1 | BM450: =IF(BL450=0,0,SUMPRODUCT($BB$3:$BH$3,BB450:BH450)) -> 0.0075 | BN450: =(1+BM450)^(1/12)-1 -> 0.0006228618 | BO450: =SUMPRODUCT($BB$2:$BH$2,BB450:BH450) -> 0.0025 | BP450: =(1+BO450)^(1/12)-1 -> 0.000208095
A451: Lifecycle | B451: Balanced | C451: =A451&"_"&B451&"_"&D451 -> Lifecycle_Balanced_94 | D451: 94 | E451: =VLOOKUP($D451,'[2]LC Balanced'!$Q$2:$U$542,2,FALSE) -> 0.42283333 | F451: =VLOOKUP($D451,'[2]LC Balanced'!$Q$2:$U$542,3,FALSE) -> 0.22383333 | G451: =VLOOKUP($D451,'[2]LC Balanced'!$Q$2:$U$542,4,FALSE) -> 0.35333333 | H451: =VLOOKUP($D451,'[2]LC Balanced'!$Q$2:$U$542,5,FALSE) -> 0 | I451: =SUM(E451:H451) -> 1 | J451: =SUMPRODUCT($E$1:$H$1,E451:H451) -> 0.051307962 | K451: =(1+J451)^(1/12)-1 -> 0.0041782938 | L451: 0 | M451: =IF($L451=0,0,SUMPRODUCT($E$3:$H$3,E451:H451)) -> 0 | N451: =1-(1-M451)^(1/12) -> 0 | O451: =SUMPRODUCT($E$2:$H$2,E451:H451) -> 0.0048794167 | P451: =1-(1-O451)^(1/12) -> 0.00040753026 | R451: Autopilot | S451: Balanced | T451: =R451&"_"&S451&"_"&U451 -> Autopilot_Balanced_94 | U451: 94 | V451: =VLOOKUP($U451,'[2]AP Balanced'!$Q$1:$T$542,2,FALSE) -> 0.038726933 | W451: =VLOOKUP($U451,'[2]AP Balanced'!$Q$1:$T$542,3,FALSE) -> 0.96127307 | X451: =VLOOKUP($U451,'[2]AP Balanced'!$Q$1:$T$542,4,FALSE) -> 0 | Y451: =SUM(V451:X451) -> 1 | Z451: =SUMPRODUCT($V$1:$X$1,V451:X451) -> 0.0518641 | AA451: =(1+Z451)^(1/12)-1 -> 0.0042225502 | AB451: 1 | AC451: =IF($AB451=0,0,SUMPRODUCT($V$3:$X$3,V451:X451)) -> 0.0065774539 | AD451: =1-(1-AC451)^(1/12) -> 0.00054978054 | AE451: =SUMPRODUCT($V$2:$X$2,V451:X451) -> 0.0025 | AF451: =1-(1-AE451)^(1/12) -> 0.00020857243 | AH451: Lifecycle | AI451: Balanced | AJ451: =AH451&"_"&AI451&"_"&AK451 -> Lifecycle_Balanced_94 | AK451: 94 | AL451: =VLOOKUP($U451,[2]Standard_Balanced!$Q$1:$T$542,2,FALSE) -> 0.033107933 | AM451: =VLOOKUP($U451,[2]Standard_Balanced!$Q$1:$T$542,3,FALSE) -> 0.96689207 | AN451: =VLOOKUP($U451,[2]Standard_Balanced!$Q$1:$T$542,4,FALSE) -> 0 | AO451: =SUM(AL451:AN451) -> 1 | AP451: =SUMPRODUCT($AL$1:$AN$1,AL451:AN451) -> 0.051789508 | AQ451: =(1+AP451)^(1/12)-1 -> 0.0042166156 | AR451: 0 | AS451: =IF(AR451=0,0,SUMPRODUCT($AL$3:$AN$3,AL451:AN451)) -> 0 | AT451: =1-(1-AS451)^(1/12) -> 0 | AU451: =SUMPRODUCT($AL$2:$AN$2,AL451:AN451) -> 0.0025 | AV451: =1-(1-AU451)^(1/12) -> 0.00020857243 | AX451: DIS | AY451: Non-Standard | AZ451: =AX451&"_"&AY451&"_"&BA451 -> DIS_Non-Standard_94 | BA451: 94 | BB451: =VLOOKUP($BA451,'[2]NonStandard DIS'!$Q$1:$X$542,2,FALSE) -> 0 | BC451: =VLOOKUP($BA451,'[2]NonStandard DIS'!$Q$1:$X$542,3,FALSE) -> 0 | BD451: =VLOOKUP($BA451,'[2]NonStandard DIS'!$Q$1:$X$542,4,FALSE) -> 0 | BE451: =VLOOKUP($BA451,'[2]NonStandard DIS'!$Q$1:$X$542,5,FALSE) -> 0 | BF451: =VLOOKUP($BA451,'[2]NonStandard DIS'!$Q$1:$X$542,6,FALSE) -> 0 | BG451: =VLOOKUP($BA451,'[2]NonStandard DIS'!$Q$1:$X$542,7,FALSE) -> 1 | BH451: =VLOOKUP($BA451,'[2]NonStandard DIS'!$Q$1:$X$542,8,FALSE) -> 0 | BI451: =SUM(BB451:BH451) -> 1 | BJ451: =SUMPRODUCT($BB$1:$BH$1,BB451:BH451) -> 0.05725 | BK451: =(1+BJ451)^(1/12)-1 -> 0.0046500445 | BL451: 1 | BM451: =IF(BL451=0,0,SUMPRODUCT($BB$3:$BH$3,BB451:BH451)) -> 0.0075 | BN451: =(1+BM451)^(1/12)-1 -> 0.0006228618 | BO451: =SUMPRODUCT($BB$2:$BH$2,BB451:BH451) -> 0.0025 | BP451: =(1+BO451)^(1/12)-1 -> 0.000208095
A452: Lifecycle | B452: Balanced | C452: =A452&"_"&B452&"_"&D452 -> Lifecycle_Balanced_93 | D452: 93 | E452: =VLOOKUP($D452,'[2]LC Balanced'!$Q$2:$U$542,2,FALSE) -> 0.42575 | F452: =VLOOKUP($D452,'[2]LC Balanced'!$Q$2:$U$542,3,FALSE) -> 0.22225 | G452: =VLOOKUP($D452,'[2]LC Balanced'!$Q$2:$U$542,4,FALSE) -> 0.352 | H452: =VLOOKUP($D452,'[2]LC Balanced'!$Q$2:$U$542,5,FALSE) -> 0 | I452: =SUM(E452:H452) -> 1 | J452: =SUMPRODUCT($E$1:$H$1,E452:H452) -> 0.051271456 | K452: =(1+J452)^(1/12)-1 -> 0.0041753879 | L452: 0 | M452: =IF($L452=0,0,SUMPRODUCT($E$3:$H$3,E452:H452)) -> 0 | N452: =1-(1-M452)^(1/12) -> 0 | O452: =SUMPRODUCT($E$2:$H$2,E452:H452) -> 0.004867475 | P452: =1-(1-O452)^(1/12) -> 0.00040653066 | R452: Autopilot | S452: Balanced | T452: =R452&"_"&S452&"_"&U452 -> Autopilot_Balanced_93 | U452: 93 | V452: =VLOOKUP($U452,'[2]AP Balanced'!$Q$1:$T$542,2,FALSE) -> 0.038726933 | W452: =VLOOKUP($U452,'[2]AP Balanced'!$Q$1:$T$542,3,FALSE) -> 0.96127307 | X452: =VLOOKUP($U452,'[2]AP Balanced'!$Q$1:$T$542,4,FALSE) -> 0 | Y452: =SUM(V452:X452) -> 1 | Z452: =SUMPRODUCT($V$1:$X$1,V452:X452) -> 0.0518641 | AA452: =(1+Z452)^(1/12)-1 -> 0.0042225502 | AB452: 1 | AC452: =IF($AB452=0,0,SUMPRODUCT($V$3:$X$3,V452:X452)) -> 0.0065774539 | AD452: =1-(1-AC452)^(1/12) -> 0.00054978054 | AE452: =SUMPRODUCT($V$2:$X$2,V452:X452) -> 0.0025 | AF452: =1-(1-AE452)^(1/12) -> 0.00020857243 | AH452: Lifecycle | AI452: Balanced | AJ452: =AH452&"_"&AI452&"_"&AK452 -> Lifecycle_Balanced_93 | AK452: 93 | AL452: =VLOOKUP($U452,[2]Standard_Balanced!$Q$1:$T$542,2,FALSE) -> 0.030298433 | AM452: =VLOOKUP($U452,[2]Standard_Balanced!$Q$1:$T$542,3,FALSE) -> 0.96970157 | AN452: =VLOOKUP($U452,[2]Standard_Balanced!$Q$1:$T$542,4,FALSE) -> 0 | AO452: =SUM(AL452:AN452) -> 1 | AP452: =SUMPRODUCT($AL$1:$AN$1,AL452:AN452) -> 0.051752212 | AQ452: =(1+AP452)^(1/12)-1 -> 0.0042136481 | AR452: 0 | AS452: =IF(AR452=0,0,SUMPRODUCT($AL$3:$AN$3,AL452:AN452)) -> 0 | AT452: =1-(1-AS452)^(1/12) -> 0 | AU452: =SUMPRODUCT($AL$2:$AN$2,AL452:AN452) -> 0.0025 | AV452: =1-(1-AU452)^(1/12) -> 0.00020857243 | AX452: DIS | AY452: Non-Standard | AZ452: =AX452&"_"&AY452&"_"&BA452 -> DIS_Non-Standard_93 | BA452: 93 | BB452: =VLOOKUP($BA452,'[2]NonStandard DIS'!$Q$1:$X$542,2,FALSE) -> 0 | BC452: =VLOOKUP($BA452,'[2]NonStandard DIS'!$Q$1:$X$542,3,FALSE) -> 0 | BD452: =VLOOKUP($BA452,'[2]NonStandard DIS'!$Q$1:$X$542,4,FALSE) -> 0 | BE452: =VLOOKUP($BA452,'[2]NonStandard DIS'!$Q$1:$X$542,5,FALSE) -> 0 | BF452: =VLOOKUP($BA452,'[2]NonStandard DIS'!$Q$1:$X$542,6,FALSE) -> 0 | BG452: =VLOOKUP($BA452,'[2]NonStandard DIS'!$Q$1:$X$542,7,FALSE) -> 1 | BH452: =VLOOKUP($BA452,'[2]NonStandard DIS'!$Q$1:$X$542,8,FALSE) -> 0 | BI452: =SUM(BB452:BH452) -> 1 | BJ452: =SUMPRODUCT($BB$1:$BH$1,BB452:BH452) -> 0.05725 | BK452: =(1+BJ452)^(1/12)-1 -> 0.0046500445 | BL452: 1 | BM452: =IF(BL452=0,0,SUMPRODUCT($BB$3:$BH$3,BB452:BH452)) -> 0.0075 | BN452: =(1+BM452)^(1/12)-1 -> 0.0006228618 | BO452: =SUMPRODUCT($BB$2:$BH$2,BB452:BH452) -> 0.0025 | BP452: =(1+BO452)^(1/12)-1 -> 0.000208095
A453: Lifecycle | B453: Balanced | C453: =A453&"_"&B453&"_"&D453 -> Lifecycle_Balanced_92 | D453: 92 | E453: =VLOOKUP($D453,'[2]LC Balanced'!$Q$2:$U$542,2,FALSE) -> 0.42866667 | F453: =VLOOKUP($D453,'[2]LC Balanced'!$Q$2:$U$542,3,FALSE) -> 0.22066667 | G453: =VLOOKUP($D453,'[2]LC Balanced'!$Q$2:$U$542,4,FALSE) -> 0.35066667 | H453: =VLOOKUP($D453,'[2]LC Balanced'!$Q$2:$U$542,5,FALSE) -> 0 | I453: =SUM(E453:H453) -> 1 | J453: =SUMPRODUCT($E$1:$H$1,E453:H453) -> 0.05123495 | K453: =(1+J453)^(1/12)-1 -> 0.004172482 | L453: 0 | M453: =IF($L453=0,0,SUMPRODUCT($E$3:$H$3,E453:H453)) -> 0 | N453: =1-(1-M453)^(1/12) -> 0 | O453: =SUMPRODUCT($E$2:$H$2,E453:H453) -> 0.0048555333 | P453: =1-(1-O453)^(1/12) -> 0.00040553106 | R453: Autopilot | S453: Balanced | T453: =R453&"_"&S453&"_"&U453 -> Autopilot_Balanced_92 | U453: 92 | V453: =VLOOKUP($U453,'[2]AP Balanced'!$Q$1:$T$542,2,FALSE) -> 0.038726933 | W453: =VLOOKUP($U453,'[2]AP Balanced'!$Q$1:$T$542,3,FALSE) -> 0.96127307 | X453: =VLOOKUP($U453,'[2]AP Balanced'!$Q$1:$T$542,4,FALSE) -> 0 | Y453: =SUM(V453:X453) -> 1 | Z453: =SUMPRODUCT($V$1:$X$1,V453:X453) -> 0.0518641 | AA453: =(1+Z453)^(1/12)-1 -> 0.0042225502 | AB453: 1 | AC453: =IF($AB453=0,0,SUMPRODUCT($V$3:$X$3,V453:X453)) -> 0.0065774539 | AD453: =1-(1-AC453)^(1/12) -> 0.00054978054 | AE453: =SUMPRODUCT($V$2:$X$2,V453:X453) -> 0.0025 | AF453: =1-(1-AE453)^(1/12) -> 0.00020857243 | AH453: Lifecycle | AI453: Balanced | AJ453: =AH453&"_"&AI453&"_"&AK453 -> Lifecycle_Balanced_92 | AK453: 92 | AL453: =VLOOKUP($U453,[2]Standard_Balanced!$Q$1:$T$542,2,FALSE) -> 0.027488933 | AM453: =VLOOKUP($U453,[2]Standard_Balanced!$Q$1:$T$542,3,FALSE) -> 0.97251107 | AN453: =VLOOKUP($U453,[2]Standard_Balanced!$Q$1:$T$542,4,FALSE) -> 0 | AO453: =SUM(AL453:AN453) -> 1 | AP453: =SUMPRODUCT($AL$1:$AN$1,AL453:AN453) -> 0.051714916 | AQ453: =(1+AP453)^(1/12)-1 -> 0.0042106805 | AR453: 0 | AS453: =IF(AR453=0,0,SUMPRODUCT($AL$3:$AN$3,AL453:AN453)) -> 0 | AT453: =1-(1-AS453)^(1/12) -> 0 | AU453: =SUMPRODUCT($AL$2:$AN$2,AL453:AN453) -> 0.0025 | AV453: =1-(1-AU453)^(1/12) -> 0.00020857243 | AX453: DIS | AY453: Non-Standard | AZ453: =AX453&"_"&AY453&"_"&BA453 -> DIS_Non-Standard_92 | BA453: 92 | BB453: =VLOOKUP($BA453,'[2]NonStandard DIS'!$Q$1:$X$542,2,FALSE) -> 0 | BC453: =VLOOKUP($BA453,'[2]NonStandard DIS'!$Q$1:$X$542,3,FALSE) -> 0 | BD453: =VLOOKUP($BA453,'[2]NonStandard DIS'!$Q$1:$X$542,4,FALSE) -> 0 | BE453: =VLOOKUP($BA453,'[2]NonStandard DIS'!$Q$1:$X$542,5,FALSE) -> 0 | BF453: =VLOOKUP($BA453,'[2]NonStandard DIS'!$Q$1:$X$542,6,FALSE) -> 0 | BG453: =VLOOKUP($BA453,'[2]NonStandard DIS'!$Q$1:$X$542,7,FALSE) -> 1 | BH453: =VLOOKUP($BA453,'[2]NonStandard DIS'!$Q$1:$X$542,8,FALSE) -> 0 | BI453: =SUM(BB453:BH453) -> 1 | BJ453: =SUMPRODUCT($BB$1:$BH$1,BB453:BH453) -> 0.05725 | BK453: =(1+BJ453)^(1/12)-1 -> 0.0046500445 | BL453: 1 | BM453: =IF(BL453=0,0,SUMPRODUCT($BB$3:$BH$3,BB453:BH453)) -> 0.0075 | BN453: =(1+BM453)^(1/12)-1 -> 0.0006228618 | BO453: =SUMPRODUCT($BB$2:$BH$2,BB453:BH453) -> 0.0025 | BP453: =(1+BO453)^(1/12)-1 -> 0.000208095
A454: Lifecycle | B454: Balanced | C454: =A454&"_"&B454&"_"&D454 -> Lifecycle_Balanced_91 | D454: 91 | E454: =VLOOKUP($D454,'[2]LC Balanced'!$Q$2:$U$542,2,FALSE) -> 0.43158333 | F454: =VLOOKUP($D454,'[2]LC Balanced'!$Q$2:$U$542,3,FALSE) -> 0.21908333 | G454: =VLOOKUP($D454,'[2]LC Balanced'!$Q$2:$U$542,4,FALSE) -> 0.34933333 | H454: =VLOOKUP($D454,'[2]LC Balanced'!$Q$2:$U$542,5,FALSE) -> 0 | I454: =SUM(E454:H454) -> 1 | J454: =SUMPRODUCT($E$1:$H$1,E454:H454) -> 0.051198444 | K454: =(1+J454)^(1/12)-1 -> 0.004169576 | L454: 0 | M454: =IF($L454=0,0,SUMPRODUCT($E$3:$H$3,E454:H454)) -> 0 | N454: =1-(1-M454)^(1/12) -> 0 | O454: =SUMPRODUCT($E$2:$H$2,E454:H454) -> 0.0048435917 | P454: =1-(1-O454)^(1/12) -> 0.00040453148 | R454: Autopilot | S454: Balanced | T454: =R454&"_"&S454&"_"&U454 -> Autopilot_Balanced_91 | U454: 91 | V454: =VLOOKUP($U454,'[2]AP Balanced'!$Q$1:$T$542,2,FALSE) -> 0.038726933 | W454: =VLOOKUP($U454,'[2]AP Balanced'!$Q$1:$T$542,3,FALSE) -> 0.96127307 | X454: =VLOOKUP($U454,'[2]AP Balanced'!$Q$1:$T$542,4,FALSE) -> 0 | Y454: =SUM(V454:X454) -> 1 | Z454: =SUMPRODUCT($V$1:$X$1,V454:X454) -> 0.0518641 | AA454: =(1+Z454)^(1/12)-1 -> 0.0042225502 | AB454: 1 | AC454: =IF($AB454=0,0,SUMPRODUCT($V$3:$X$3,V454:X454)) -> 0.0065774539 | AD454: =1-(1-AC454)^(1/12) -> 0.00054978054 | AE454: =SUMPRODUCT($V$2:$X$2,V454:X454) -> 0.0025 | AF454: =1-(1-AE454)^(1/12) -> 0.00020857243 | AH454: Lifecycle | AI454: Balanced | AJ454: =AH454&"_"&AI454&"_"&AK454 -> Lifecycle_Balanced_91 | AK454: 91 | AL454: =VLOOKUP($U454,[2]Standard_Balanced!$Q$1:$T$542,2,FALSE) -> 0.024679433 | AM454: =VLOOKUP($U454,[2]Standard_Balanced!$Q$1:$T$542,3,FALSE) -> 0.97532057 | AN454: =VLOOKUP($U454,[2]Standard_Balanced!$Q$1:$T$542,4,FALSE) -> 0 | AO454: =SUM(AL454:AN454) -> 1 | AP454: =SUMPRODUCT($AL$1:$AN$1,AL454:AN454) -> 0.051677619 | AQ454: =(1+AP454)^(1/12)-1 -> 0.0042077128 | AR454: 0 | AS454: =IF(AR454=0,0,SUMPRODUCT($AL$3:$AN$3,AL454:AN454)) -> 0 | AT454: =1-(1-AS454)^(1/12) -> 0 | AU454: =SUMPRODUCT($AL$2:$AN$2,AL454:AN454) -> 0.0025 | AV454: =1-(1-AU454)^(1/12) -> 0.00020857243 | AX454: DIS | AY454: Non-Standard | AZ454: =AX454&"_"&AY454&"_"&BA454 -> DIS_Non-Standard_91 | BA454: 91 | BB454: =VLOOKUP($BA454,'[2]NonStandard DIS'!$Q$1:$X$542,2,FALSE) -> 0 | BC454: =VLOOKUP($BA454,'[2]NonStandard DIS'!$Q$1:$X$542,3,FALSE) -> 0 | BD454: =VLOOKUP($BA454,'[2]NonStandard DIS'!$Q$1:$X$542,4,FALSE) -> 0 | BE454: =VLOOKUP($BA454,'[2]NonStandard DIS'!$Q$1:$X$542,5,FALSE) -> 0 | BF454: =VLOOKUP($BA454,'[2]NonStandard DIS'!$Q$1:$X$542,6,FALSE) -> 0 | BG454: =VLOOKUP($BA454,'[2]NonStandard DIS'!$Q$1:$X$542,7,FALSE) -> 1 | BH454: =VLOOKUP($BA454,'[2]NonStandard DIS'!$Q$1:$X$542,8,FALSE) -> 0 | BI454: =SUM(BB454:BH454) -> 1 | BJ454: =SUMPRODUCT($BB$1:$BH$1,BB454:BH454) -> 0.05725 | BK454: =(1+BJ454)^(1/12)-1 -> 0.0046500445 | BL454: 1 | BM454: =IF(BL454=0,0,SUMPRODUCT($BB$3:$BH$3,BB454:BH454)) -> 0.0075 | BN454: =(1+BM454)^(1/12)-1 -> 0.0006228618 | BO454: =SUMPRODUCT($BB$2:$BH$2,BB454:BH454) -> 0.0025 | BP454: =(1+BO454)^(1/12)-1 -> 0.000208095
A455: Lifecycle | B455: Balanced | C455: =A455&"_"&B455&"_"&D455 -> Lifecycle_Balanced_90 | D455: 90 | E455: =VLOOKUP($D455,'[2]LC Balanced'!$Q$2:$U$542,2,FALSE) -> 0.4345 | F455: =VLOOKUP($D455,'[2]LC Balanced'!$Q$2:$U$542,3,FALSE) -> 0.2175 | G455: =VLOOKUP($D455,'[2]LC Balanced'!$Q$2:$U$542,4,FALSE) -> 0.348 | H455: =VLOOKUP($D455,'[2]LC Balanced'!$Q$2:$U$542,5,FALSE) -> 0 | I455: =SUM(E455:H455) -> 1 | J455: =SUMPRODUCT($E$1:$H$1,E455:H455) -> 0.051161937 | K455: =(1+J455)^(1/12)-1 -> 0.0041666698 | L455: 0 | M455: =IF($L455=0,0,SUMPRODUCT($E$3:$H$3,E455:H455)) -> 0 | N455: =1-(1-M455)^(1/12) -> 0 | O455: =SUMPRODUCT($E$2:$H$2,E455:H455) -> 0.00483165 | P455: =1-(1-O455)^(1/12) -> 0.00040353191 | R455: Autopilot | S455: Balanced | T455: =R455&"_"&S455&"_"&U455 -> Autopilot_Balanced_90 | U455: 90 | V455: =VLOOKUP($U455,'[2]AP Balanced'!$Q$1:$T$542,2,FALSE) -> 0.038726933 | W455: =VLOOKUP($U455,'[2]AP Balanced'!$Q$1:$T$542,3,FALSE) -> 0.96127307 | X455: =VLOOKUP($U455,'[2]AP Balanced'!$Q$1:$T$542,4,FALSE) -> 0 | Y455: =SUM(V455:X455) -> 1 | Z455: =SUMPRODUCT($V$1:$X$1,V455:X455) -> 0.0518641 | AA455: =(1+Z455)^(1/12)-1 -> 0.0042225502 | AB455: 1 | AC455: =IF($AB455=0,0,SUMPRODUCT($V$3:$X$3,V455:X455)) -> 0.0065774539 | AD455: =1-(1-AC455)^(1/12) -> 0.00054978054 | AE455: =SUMPRODUCT($V$2:$X$2,V455:X455) -> 0.0025 | AF455: =1-(1-AE455)^(1/12) -> 0.00020857243 | AH455: Lifecycle | AI455: Balanced | AJ455: =AH455&"_"&AI455&"_"&AK455 -> Lifecycle_Balanced_90 | AK455: 90 | AL455: =VLOOKUP($U455,[2]Standard_Balanced!$Q$1:$T$542,2,FALSE) -> 0.021869933 | AM455: =VLOOKUP($U455,[2]Standard_Balanced!$Q$1:$T$542,3,FALSE) -> 0.97813007 | AN455: =VLOOKUP($U455,[2]Standard_Balanced!$Q$1:$T$542,4,FALSE) -> 0 | AO455: =SUM(AL455:AN455) -> 1 | AP455: =SUMPRODUCT($AL$1:$AN$1,AL455:AN455) -> 0.051640323 | AQ455: =(1+AP455)^(1/12)-1 -> 0.0042047451 | AR455: 0 | AS455: =IF(AR455=0,0,SUMPRODUCT($AL$3:$AN$3,AL455:AN455)) -> 0 | AT455: =1-(1-AS455)^(1/12) -> 0 | AU455: =SUMPRODUCT($AL$2:$AN$2,AL455:AN455) -> 0.0025 | AV455: =1-(1-AU455)^(1/12) -> 0.00020857243 | AX455: DIS | AY455: Non-Standard | AZ455: =AX455&"_"&AY455&"_"&BA455 -> DIS_Non-Standard_90 | BA455: 90 | BB455: =VLOOKUP($BA455,'[2]NonStandard DIS'!$Q$1:$X$542,2,FALSE) -> 0 | BC455: =VLOOKUP($BA455,'[2]NonStandard DIS'!$Q$1:$X$542,3,FALSE) -> 0 | BD455: =VLOOKUP($BA455,'[2]NonStandard DIS'!$Q$1:$X$542,4,FALSE) -> 0 | BE455: =VLOOKUP($BA455,'[2]NonStandard DIS'!$Q$1:$X$542,5,FALSE) -> 0 | BF455: =VLOOKUP($BA455,'[2]NonStandard DIS'!$Q$1:$X$542,6,FALSE) -> 0 | BG455: =VLOOKUP($BA455,'[2]NonStandard DIS'!$Q$1:$X$542,7,FALSE) -> 1 | BH455: =VLOOKUP($BA455,'[2]NonStandard DIS'!$Q$1:$X$542,8,FALSE) -> 0 | BI455: =SUM(BB455:BH455) -> 1 | BJ455: =SUMPRODUCT($BB$1:$BH$1,BB455:BH455) -> 0.05725 | BK455: =(1+BJ455)^(1/12)-1 -> 0.0046500445 | BL455: 1 | BM455: =IF(BL455=0,0,SUMPRODUCT($BB$3:$BH$3,BB455:BH455)) -> 0.0075 | BN455: =(1+BM455)^(1/12)-1 -> 0.0006228618 | BO455: =SUMPRODUCT($BB$2:$BH$2,BB455:BH455) -> 0.0025 | BP455: =(1+BO455)^(1/12)-1 -> 0.000208095
A456: Lifecycle | B456: Balanced | C456: =A456&"_"&B456&"_"&D456 -> Lifecycle_Balanced_89 | D456: 89 | E456: =VLOOKUP($D456,'[2]LC Balanced'!$Q$2:$U$542,2,FALSE) -> 0.43741667 | F456: =VLOOKUP($D456,'[2]LC Balanced'!$Q$2:$U$542,3,FALSE) -> 0.21591667 | G456: =VLOOKUP($D456,'[2]LC Balanced'!$Q$2:$U$542,4,FALSE) -> 0.34666667 | H456: =VLOOKUP($D456,'[2]LC Balanced'!$Q$2:$U$542,5,FALSE) -> 0 | I456: =SUM(E456:H456) -> 1 | J456: =SUMPRODUCT($E$1:$H$1,E456:H456) -> 0.051125431 | K456: =(1+J456)^(1/12)-1 -> 0.0041637636 | L456: 0 | M456: =IF($L456=0,0,SUMPRODUCT($E$3:$H$3,E456:H456)) -> 0 | N456: =1-(1-M456)^(1/12) -> 0 | O456: =SUMPRODUCT($E$2:$H$2,E456:H456) -> 0.0048197083 | P456: =1-(1-O456)^(1/12) -> 0.00040253234 | R456: Autopilot | S456: Balanced | T456: =R456&"_"&S456&"_"&U456 -> Autopilot_Balanced_89 | U456: 89 | V456: =VLOOKUP($U456,'[2]AP Balanced'!$Q$1:$T$542,2,FALSE) -> 0.038726933 | W456: =VLOOKUP($U456,'[2]AP Balanced'!$Q$1:$T$542,3,FALSE) -> 0.96127307 | X456: =VLOOKUP($U456,'[2]AP Balanced'!$Q$1:$T$542,4,FALSE) -> 0 | Y456: =SUM(V456:X456) -> 1 | Z456: =SUMPRODUCT($V$1:$X$1,V456:X456) -> 0.0518641 | AA456: =(1+Z456)^(1/12)-1 -> 0.0042225502 | AB456: 1 | AC456: =IF($AB456=0,0,SUMPRODUCT($V$3:$X$3,V456:X456)) -> 0.0065774539 | AD456: =1-(1-AC456)^(1/12) -> 0.00054978054 | AE456: =SUMPRODUCT($V$2:$X$2,V456:X456) -> 0.0025 | AF456: =1-(1-AE456)^(1/12) -> 0.00020857243 | AH456: Lifecycle | AI456: Balanced | AJ456: =AH456&"_"&AI456&"_"&AK456 -> Lifecycle_Balanced_89 | AK456: 89 | AL456: =VLOOKUP($U456,[2]Standard_Balanced!$Q$1:$T$542,2,FALSE) -> 0.019060433 | AM456: =VLOOKUP($U456,[2]Standard_Balanced!$Q$1:$T$542,3,FALSE) -> 0.98093957 | AN456: =VLOOKUP($U456,[2]Standard_Balanced!$Q$1:$T$542,4,FALSE) -> 0 | AO456: =SUM(AL456:AN456) -> 1 | AP456: =SUMPRODUCT($AL$1:$AN$1,AL456:AN456) -> 0.051603027 | AQ456: =(1+AP456)^(1/12)-1 -> 0.0042017772 | AR456: 0 | AS456: =IF(AR456=0,0,SUMPRODUCT($AL$3:$AN$3,AL456:AN456)) -> 0 | AT456: =1-(1-AS456)^(1/12) -> 0 | AU456: =SUMPRODUCT($AL$2:$AN$2,AL456:AN456) -> 0.0025 | AV456: =1-(1-AU456)^(1/12) -> 0.00020857243 | AX456: DIS | AY456: Non-Standard | AZ456: =AX456&"_"&AY456&"_"&BA456 -> DIS_Non-Standard_89 | BA456: 89 | BB456: =VLOOKUP($BA456,'[2]NonStandard DIS'!$Q$1:$X$542,2,FALSE) -> 0 | BC456: =VLOOKUP($BA456,'[2]NonStandard DIS'!$Q$1:$X$542,3,FALSE) -> 0 | BD456: =VLOOKUP($BA456,'[2]NonStandard DIS'!$Q$1:$X$542,4,FALSE) -> 0 | BE456: =VLOOKUP($BA456,'[2]NonStandard DIS'!$Q$1:$X$542,5,FALSE) -> 0 | BF456: =VLOOKUP($BA456,'[2]NonStandard DIS'!$Q$1:$X$542,6,FALSE) -> 0 | BG456: =VLOOKUP($BA456,'[2]NonStandard DIS'!$Q$1:$X$542,7,FALSE) -> 1 | BH456: =VLOOKUP($BA456,'[2]NonStandard DIS'!$Q$1:$X$542,8,FALSE) -> 0 | BI456: =SUM(BB456:BH456) -> 1 | BJ456: =SUMPRODUCT($BB$1:$BH$1,BB456:BH456) -> 0.05725 | BK456: =(1+BJ456)^(1/12)-1 -> 0.0046500445 | BL456: 1 | BM456: =IF(BL456=0,0,SUMPRODUCT($BB$3:$BH$3,BB456:BH456)) -> 0.0075 | BN456: =(1+BM456)^(1/12)-1 -> 0.0006228618 | BO456: =SUMPRODUCT($BB$2:$BH$2,BB456:BH456) -> 0.0025 | BP456: =(1+BO456)^(1/12)-1 -> 0.000208095
A457: Lifecycle | B457: Balanced | C457: =A457&"_"&B457&"_"&D457 -> Lifecycle_Balanced_88 | D457: 88 | E457: =VLOOKUP($D457,'[2]LC Balanced'!$Q$2:$U$542,2,FALSE) -> 0.44033333 | F457: =VLOOKUP($D457,'[2]LC Balanced'!$Q$2:$U$542,3,FALSE) -> 0.21433333 | G457: =VLOOKUP($D457,'[2]LC Balanced'!$Q$2:$U$542,4,FALSE) -> 0.34533333 | H457: =VLOOKUP($D457,'[2]LC Balanced'!$Q$2:$U$542,5,FALSE) -> 0 | I457: =SUM(E457:H457) -> 1 | J457: =SUMPRODUCT($E$1:$H$1,E457:H457) -> 0.051088925 | K457: =(1+J457)^(1/12)-1 -> 0.0041608573 | L457: 0 | M457: =IF($L457=0,0,SUMPRODUCT($E$3:$H$3,E457:H457)) -> 0 | N457: =1-(1-M457)^(1/12) -> 0 | O457: =SUMPRODUCT($E$2:$H$2,E457:H457) -> 0.0048077667 | P457: =1-(1-O457)^(1/12) -> 0.00040153279 | R457: Autopilot | S457: Balanced | T457: =R457&"_"&S457&"_"&U457 -> Autopilot_Balanced_88 | U457: 88 | V457: =VLOOKUP($U457,'[2]AP Balanced'!$Q$1:$T$542,2,FALSE) -> 0.038726933 | W457: =VLOOKUP($U457,'[2]AP Balanced'!$Q$1:$T$542,3,FALSE) -> 0.96127307 | X457: =VLOOKUP($U457,'[2]AP Balanced'!$Q$1:$T$542,4,FALSE) -> 0 | Y457: =SUM(V457:X457) -> 1 | Z457: =SUMPRODUCT($V$1:$X$1,V457:X457) -> 0.0518641 | AA457: =(1+Z457)^(1/12)-1 -> 0.0042225502 | AB457: 1 | AC457: =IF($AB457=0,0,SUMPRODUCT($V$3:$X$3,V457:X457)) -> 0.0065774539 | AD457: =1-(1-AC457)^(1/12) -> 0.00054978054 | AE457: =SUMPRODUCT($V$2:$X$2,V457:X457) -> 0.0025 | AF457: =1-(1-AE457)^(1/12) -> 0.00020857243 | AH457: Lifecycle | AI457: Balanced | AJ457: =AH457&"_"&AI457&"_"&AK457 -> Lifecycle_Balanced_88 | AK457: 88 | AL457: =VLOOKUP($U457,[2]Standard_Balanced!$Q$1:$T$542,2,FALSE) -> 0.016250933 | AM457: =VLOOKUP($U457,[2]Standard_Balanced!$Q$1:$T$542,3,FALSE) -> 0.98374907 | AN457: =VLOOKUP($U457,[2]Standard_Balanced!$Q$1:$T$542,4,FALSE) -> 0 | AO457: =SUM(AL457:AN457) -> 1 | AP457: =SUMPRODUCT($AL$1:$AN$1,AL457:AN457) -> 0.051565731 | AQ457: =(1+AP457)^(1/12)-1 -> 0.0041988092 | AR457: 0 | AS457: =IF(AR457=0,0,SUMPRODUCT($AL$3:$AN$3,AL457:AN457)) -> 0 | AT457: =1-(1-AS457)^(1/12) -> 0 | AU457: =SUMPRODUCT($AL$2:$AN$2,AL457:AN457) -> 0.0025 | AV457: =1-(1-AU457)^(1/12) -> 0.00020857243 | AX457: DIS | AY457: Non-Standard | AZ457: =AX457&"_"&AY457&"_"&BA457 -> DIS_Non-Standard_88 | BA457: 88 | BB457: =VLOOKUP($BA457,'[2]NonStandard DIS'!$Q$1:$X$542,2,FALSE) -> 0 | BC457: =VLOOKUP($BA457,'[2]NonStandard DIS'!$Q$1:$X$542,3,FALSE) -> 0 | BD457: =VLOOKUP($BA457,'[2]NonStandard DIS'!$Q$1:$X$542,4,FALSE) -> 0 | BE457: =VLOOKUP($BA457,'[2]NonStandard DIS'!$Q$1:$X$542,5,FALSE) -> 0 | BF457: =VLOOKUP($BA457,'[2]NonStandard DIS'!$Q$1:$X$542,6,FALSE) -> 0 | BG457: =VLOOKUP($BA457,'[2]NonStandard DIS'!$Q$1:$X$542,7,FALSE) -> 1 | BH457: =VLOOKUP($BA457,'[2]NonStandard DIS'!$Q$1:$X$542,8,FALSE) -> 0 | BI457: =SUM(BB457:BH457) -> 1 | BJ457: =SUMPRODUCT($BB$1:$BH$1,BB457:BH457) -> 0.05725 | BK457: =(1+BJ457)^(1/12)-1 -> 0.0046500445 | BL457: 1 | BM457: =IF(BL457=0,0,SUMPRODUCT($BB$3:$BH$3,BB457:BH457)) -> 0.0075 | BN457: =(1+BM457)^(1/12)-1 -> 0.0006228618 | BO457: =SUMPRODUCT($BB$2:$BH$2,BB457:BH457) -> 0.0025 | BP457: =(1+BO457)^(1/12)-1 -> 0.000208095
A458: Lifecycle | B458: Balanced | C458: =A458&"_"&B458&"_"&D458 -> Lifecycle_Balanced_87 | D458: 87 | E458: =VLOOKUP($D458,'[2]LC Balanced'!$Q$2:$U$542,2,FALSE) -> 0.44325 | F458: =VLOOKUP($D458,'[2]LC Balanced'!$Q$2:$U$542,3,FALSE) -> 0.21275 | G458: =VLOOKUP($D458,'[2]LC Balanced'!$Q$2:$U$542,4,FALSE) -> 0.344 | H458: =VLOOKUP($D458,'[2]LC Balanced'!$Q$2:$U$542,5,FALSE) -> 0 | I458: =SUM(E458:H458) -> 1 | J458: =SUMPRODUCT($E$1:$H$1,E458:H458) -> 0.051052419 | K458: =(1+J458)^(1/12)-1 -> 0.0041579509 | L458: 0 | M458: =IF($L458=0,0,SUMPRODUCT($E$3:$H$3,E458:H458)) -> 0 | N458: =1-(1-M458)^(1/12) -> 0 | O458: =SUMPRODUCT($E$2:$H$2,E458:H458) -> 0.004795825 | P458: =1-(1-O458)^(1/12) -> 0.00040053325 | R458: Autopilot | S458: Balanced | T458: =R458&"_"&S458&"_"&U458 -> Autopilot_Balanced_87 | U458: 87 | V458: =VLOOKUP($U458,'[2]AP Balanced'!$Q$1:$T$542,2,FALSE) -> 0.038726933 | W458: =VLOOKUP($U458,'[2]AP Balanced'!$Q$1:$T$542,3,FALSE) -> 0.96127307 | X458: =VLOOKUP($U458,'[2]AP Balanced'!$Q$1:$T$542,4,FALSE) -> 0 | Y458: =SUM(V458:X458) -> 1 | Z458: =SUMPRODUCT($V$1:$X$1,V458:X458) -> 0.0518641 | AA458: =(1+Z458)^(1/12)-1 -> 0.0042225502 | AB458: 1 | AC458: =IF($AB458=0,0,SUMPRODUCT($V$3:$X$3,V458:X458)) -> 0.0065774539 | AD458: =1-(1-AC458)^(1/12) -> 0.00054978054 | AE458: =SUMPRODUCT($V$2:$X$2,V458:X458) -> 0.0025 | AF458: =1-(1-AE458)^(1/12) -> 0.00020857243 | AH458: Lifecycle | AI458: Balanced | AJ458: =AH458&"_"&AI458&"_"&AK458 -> Lifecycle_Balanced_87 | AK458: 87 | AL458: =VLOOKUP($U458,[2]Standard_Balanced!$Q$1:$T$542,2,FALSE) -> 0.013441433 | AM458: =VLOOKUP($U458,[2]Standard_Balanced!$Q$1:$T$542,3,FALSE) -> 0.98655857 | AN458: =VLOOKUP($U458,[2]Standard_Balanced!$Q$1:$T$542,4,FALSE) -> 0 | AO458: =SUM(AL458:AN458) -> 1 | AP458: =SUMPRODUCT($AL$1:$AN$1,AL458:AN458) -> 0.051528435 | AQ458: =(1+AP458)^(1/12)-1 -> 0.0041958412 | AR458: 0 | AS458: =IF(AR458=0,0,SUMPRODUCT($AL$3:$AN$3,AL458:AN458)) -> 0 | AT458: =1-(1-AS458)^(1/12) -> 0 | AU458: =SUMPRODUCT($AL$2:$AN$2,AL458:AN458) -> 0.0025 | AV458: =1-(1-AU458)^(1/12) -> 0.00020857243 | AX458: DIS | AY458: Non-Standard | AZ458: =AX458&"_"&AY458&"_"&BA458 -> DIS_Non-Standard_87 | BA458: 87 | BB458: =VLOOKUP($BA458,'[2]NonStandard DIS'!$Q$1:$X$542,2,FALSE) -> 0 | BC458: =VLOOKUP($BA458,'[2]NonStandard DIS'!$Q$1:$X$542,3,FALSE) -> 0 | BD458: =VLOOKUP($BA458,'[2]NonStandard DIS'!$Q$1:$X$542,4,FALSE) -> 0 | BE458: =VLOOKUP($BA458,'[2]NonStandard DIS'!$Q$1:$X$542,5,FALSE) -> 0 | BF458: =VLOOKUP($BA458,'[2]NonStandard DIS'!$Q$1:$X$542,6,FALSE) -> 0 | BG458: =VLOOKUP($BA458,'[2]NonStandard DIS'!$Q$1:$X$542,7,FALSE) -> 1 | BH458: =VLOOKUP($BA458,'[2]NonStandard DIS'!$Q$1:$X$542,8,FALSE) -> 0 | BI458: =SUM(BB458:BH458) -> 1 | BJ458: =SUMPRODUCT($BB$1:$BH$1,BB458:BH458) -> 0.05725 | BK458: =(1+BJ458)^(1/12)-1 -> 0.0046500445 | BL458: 1 | BM458: =IF(BL458=0,0,SUMPRODUCT($BB$3:$BH$3,BB458:BH458)) -> 0.0075 | BN458: =(1+BM458)^(1/12)-1 -> 0.0006228618 | BO458: =SUMPRODUCT($BB$2:$BH$2,BB458:BH458) -> 0.0025 | BP458: =(1+BO458)^(1/12)-1 -> 0.000208095
A459: Lifecycle | B459: Balanced | C459: =A459&"_"&B459&"_"&D459 -> Lifecycle_Balanced_86 | D459: 86 | E459: =VLOOKUP($D459,'[2]LC Balanced'!$Q$2:$U$542,2,FALSE) -> 0.44616667 | F459: =VLOOKUP($D459,'[2]LC Balanced'!$Q$2:$U$542,3,FALSE) -> 0.21116667 | G459: =VLOOKUP($D459,'[2]LC Balanced'!$Q$2:$U$542,4,FALSE) -> 0.34266667 | H459: =VLOOKUP($D459,'[2]LC Balanced'!$Q$2:$U$542,5,FALSE) -> 0 | I459: =SUM(E459:H459) -> 1 | J459: =SUMPRODUCT($E$1:$H$1,E459:H459) -> 0.051015912 | K459: =(1+J459)^(1/12)-1 -> 0.0041550444 | L459: 0 | M459: =IF($L459=0,0,SUMPRODUCT($E$3:$H$3,E459:H459)) -> 0 | N459: =1-(1-M459)^(1/12) -> 0 | O459: =SUMPRODUCT($E$2:$H$2,E459:H459) -> 0.0047838833 | P459: =1-(1-O459)^(1/12) -> 0.00039953373 | R459: Autopilot | S459: Balanced | T459: =R459&"_"&S459&"_"&U459 -> Autopilot_Balanced_86 | U459: 86 | V459: =VLOOKUP($U459,'[2]AP Balanced'!$Q$1:$T$542,2,FALSE) -> 0.038726933 | W459: =VLOOKUP($U459,'[2]AP Balanced'!$Q$1:$T$542,3,FALSE) -> 0.96127307 | X459: =VLOOKUP($U459,'[2]AP Balanced'!$Q$1:$T$542,4,FALSE) -> 0 | Y459: =SUM(V459:X459) -> 1 | Z459: =SUMPRODUCT($V$1:$X$1,V459:X459) -> 0.0518641 | AA459: =(1+Z459)^(1/12)-1 -> 0.0042225502 | AB459: 1 | AC459: =IF($AB459=0,0,SUMPRODUCT($V$3:$X$3,V459:X459)) -> 0.0065774539 | AD459: =1-(1-AC459)^(1/12) -> 0.00054978054 | AE459: =SUMPRODUCT($V$2:$X$2,V459:X459) -> 0.0025 | AF459: =1-(1-AE459)^(1/12) -> 0.00020857243 | AH459: Lifecycle | AI459: Balanced | AJ459: =AH459&"_"&AI459&"_"&AK459 -> Lifecycle_Balanced_86 | AK459: 86 | AL459: =VLOOKUP($U459,[2]Standard_Balanced!$Q$1:$T$542,2,FALSE) -> 0.010631933 | AM459: =VLOOKUP($U459,[2]Standard_Balanced!$Q$1:$T$542,3,FALSE) -> 0.98936807 | AN459: =VLOOKUP($U459,[2]Standard_Balanced!$Q$1:$T$542,4,FALSE) -> 0 | AO459: =SUM(AL459:AN459) -> 1 | AP459: =SUMPRODUCT($AL$1:$AN$1,AL459:AN459) -> 0.051491139 | AQ459: =(1+AP459)^(1/12)-1 -> 0.004192873 | AR459: 0 | AS459: =IF(AR459=0,0,SUMPRODUCT($AL$3:$AN$3,AL459:AN459)) -> 0 | AT459: =1-(1-AS459)^(1/12) -> 0 | AU459: =SUMPRODUCT($AL$2:$AN$2,AL459:AN459) -> 0.0025 | AV459: =1-(1-AU459)^(1/12) -> 0.00020857243 | AX459: DIS | AY459: Non-Standard | AZ459: =AX459&"_"&AY459&"_"&BA459 -> DIS_Non-Standard_86 | BA459: 86 | BB459: =VLOOKUP($BA459,'[2]NonStandard DIS'!$Q$1:$X$542,2,FALSE) -> 0 | BC459: =VLOOKUP($BA459,'[2]NonStandard DIS'!$Q$1:$X$542,3,FALSE) -> 0 | BD459: =VLOOKUP($BA459,'[2]NonStandard DIS'!$Q$1:$X$542,4,FALSE) -> 0 | BE459: =VLOOKUP($BA459,'[2]NonStandard DIS'!$Q$1:$X$542,5,FALSE) -> 0 | BF459: =VLOOKUP($BA459,'[2]NonStandard DIS'!$Q$1:$X$542,6,FALSE) -> 0 | BG459: =VLOOKUP($BA459,'[2]NonStandard DIS'!$Q$1:$X$542,7,FALSE) -> 1 | BH459: =VLOOKUP($BA459,'[2]NonStandard DIS'!$Q$1:$X$542,8,FALSE) -> 0 | BI459: =SUM(BB459:BH459) -> 1 | BJ459: =SUMPRODUCT($BB$1:$BH$1,BB459:BH459) -> 0.05725 | BK459: =(1+BJ459)^(1/12)-1 -> 0.0046500445 | BL459: 1 | BM459: =IF(BL459=0,0,SUMPRODUCT($BB$3:$BH$3,BB459:BH459)) -> 0.0075 | BN459: =(1+BM459)^(1/12)-1 -> 0.0006228618 | BO459: =SUMPRODUCT($BB$2:$BH$2,BB459:BH459) -> 0.0025 | BP459: =(1+BO459)^(1/12)-1 -> 0.000208095
A460: Lifecycle | B460: Balanced | C460: =A460&"_"&B460&"_"&D460 -> Lifecycle_Balanced_85 | D460: 85 | E460: =VLOOKUP($D460,'[2]LC Balanced'!$Q$2:$U$542,2,FALSE) -> 0.44908333 | F460: =VLOOKUP($D460,'[2]LC Balanced'!$Q$2:$U$542,3,FALSE) -> 0.20958333 | G460: =VLOOKUP($D460,'[2]LC Balanced'!$Q$2:$U$542,4,FALSE) -> 0.34133333 | H460: =VLOOKUP($D460,'[2]LC Balanced'!$Q$2:$U$542,5,FALSE) -> 0 | I460: =SUM(E460:H460) -> 1 | J460: =SUMPRODUCT($E$1:$H$1,E460:H460) -> 0.050979406 | K460: =(1+J460)^(1/12)-1 -> 0.0041521378 | L460: 0 | M460: =IF($L460=0,0,SUMPRODUCT($E$3:$H$3,E460:H460)) -> 0 | N460: =1-(1-M460)^(1/12) -> 0 | O460: =SUMPRODUCT($E$2:$H$2,E460:H460) -> 0.0047719417 | P460: =1-(1-O460)^(1/12) -> 0.00039853421 | R460: Autopilot | S460: Balanced | T460: =R460&"_"&S460&"_"&U460 -> Autopilot_Balanced_85 | U460: 85 | V460: =VLOOKUP($U460,'[2]AP Balanced'!$Q$1:$T$542,2,FALSE) -> 0.038726933 | W460: =VLOOKUP($U460,'[2]AP Balanced'!$Q$1:$T$542,3,FALSE) -> 0.96127307 | X460: =VLOOKUP($U460,'[2]AP Balanced'!$Q$1:$T$542,4,FALSE) -> 0 | Y460: =SUM(V460:X460) -> 1 | Z460: =SUMPRODUCT($V$1:$X$1,V460:X460) -> 0.0518641 | AA460: =(1+Z460)^(1/12)-1 -> 0.0042225502 | AB460: 1 | AC460: =IF($AB460=0,0,SUMPRODUCT($V$3:$X$3,V460:X460)) -> 0.0065774539 | AD460: =1-(1-AC460)^(1/12) -> 0.00054978054 | AE460: =SUMPRODUCT($V$2:$X$2,V460:X460) -> 0.0025 | AF460: =1-(1-AE460)^(1/12) -> 0.00020857243 | AH460: Lifecycle | AI460: Balanced | AJ460: =AH460&"_"&AI460&"_"&AK460 -> Lifecycle_Balanced_85 | AK460: 85 | AL460: =VLOOKUP($U460,[2]Standard_Balanced!$Q$1:$T$542,2,FALSE) -> 0.0078224333 | AM460: =VLOOKUP($U460,[2]Standard_Balanced!$Q$1:$T$542,3,FALSE) -> 0.99217757 | AN460: =VLOOKUP($U460,[2]Standard_Balanced!$Q$1:$T$542,4,FALSE) -> 0 | AO460: =SUM(AL460:AN460) -> 1 | AP460: =SUMPRODUCT($AL$1:$AN$1,AL460:AN460) -> 0.051453843 | AQ460: =(1+AP460)^(1/12)-1 -> 0.0041899048 | AR460: 0 | AS460: =IF(AR460=0,0,SUMPRODUCT($AL$3:$AN$3,AL460:AN460)) -> 0 | AT460: =1-(1-AS460)^(1/12) -> 0 | AU460: =SUMPRODUCT($AL$2:$AN$2,AL460:AN460) -> 0.0025 | AV460: =1-(1-AU460)^(1/12) -> 0.00020857243 | AX460: DIS | AY460: Non-Standard | AZ460: =AX460&"_"&AY460&"_"&BA460 -> DIS_Non-Standard_85 | BA460: 85 | BB460: =VLOOKUP($BA460,'[2]NonStandard DIS'!$Q$1:$X$542,2,FALSE) -> 0 | BC460: =VLOOKUP($BA460,'[2]NonStandard DIS'!$Q$1:$X$542,3,FALSE) -> 0 | BD460: =VLOOKUP($BA460,'[2]NonStandard DIS'!$Q$1:$X$542,4,FALSE) -> 0 | BE460: =VLOOKUP($BA460,'[2]NonStandard DIS'!$Q$1:$X$542,5,FALSE) -> 0 | BF460: =VLOOKUP($BA460,'[2]NonStandard DIS'!$Q$1:$X$542,6,FALSE) -> 0 | BG460: =VLOOKUP($BA460,'[2]NonStandard DIS'!$Q$1:$X$542,7,FALSE) -> 1 | BH460: =VLOOKUP($BA460,'[2]NonStandard DIS'!$Q$1:$X$542,8,FALSE) -> 0 | BI460: =SUM(BB460:BH460) -> 1 | BJ460: =SUMPRODUCT($BB$1:$BH$1,BB460:BH460) -> 0.05725 | BK460: =(1+BJ460)^(1/12)-1 -> 0.0046500445 | BL460: 1 | BM460: =IF(BL460=0,0,SUMPRODUCT($BB$3:$BH$3,BB460:BH460)) -> 0.0075 | BN460: =(1+BM460)^(1/12)-1 -> 0.0006228618 | BO460: =SUMPRODUCT($BB$2:$BH$2,BB460:BH460) -> 0.0025 | BP460: =(1+BO460)^(1/12)-1 -> 0.000208095
... A545: Lifecycle | B545: Balanced | C545: =A545&"_"&B545&"_"&D545 -> Lifecycle_Balanced_0 | D545: 0 | E545: =VLOOKUP($D545,'[2]LC Balanced'!$Q$2:$U$542,2,FALSE) -> 0.616 | F545: =VLOOKUP($D545,'[2]LC Balanced'!$Q$2:$U$542,3,FALSE) -> 0.124 | G545: =VLOOKUP($D545,'[2]LC Balanced'!$Q$2:$U$542,4,FALSE) -> 0.26 | H545: =VLOOKUP($D545,'[2]LC Balanced'!$Q$2:$U$542,5,FALSE) -> 0 | I545: =SUM(E545:H545) -> 1 | J545: =SUMPRODUCT($E$1:$H$1,E545:H545) -> 0.0488012 | K545: =(1+J545)^(1/12)-1 -> 0.0039785433 | L545: 0 | M545: =IF($L545=0,0,SUMPRODUCT($E$3:$H$3,E545:H545)) -> 0 | N545: =1-(1-M545)^(1/12) -> 0 | O545: =SUMPRODUCT($E$2:$H$2,E545:H545) -> 0.004082 | P545: =1-(1-O545)^(1/12) -> 0.00034080475 | R545: Autopilot | S545: Balanced | T545: =R545&"_"&S545&"_"&U545 -> Autopilot_Balanced_0 | U545: 0 | V545: =VLOOKUP($U545,'[2]AP Balanced'!$Q$1:$T$542,2,FALSE) -> 0 | W545: =VLOOKUP($U545,'[2]AP Balanced'!$Q$1:$T$542,3,FALSE) -> 0.712 | X545: =VLOOKUP($U545,'[2]AP Balanced'!$Q$1:$T$542,4,FALSE) -> 0.288 | Y545: =SUM(V545:X545) -> 1 | Z545: =SUMPRODUCT($V$1:$X$1,V545:X545) -> 0.0488012 | AA545: =(1+Z545)^(1/12)-1 -> 0.0039785433 | AB545: 1 | AC545: =IF($AB545=0,0,SUMPRODUCT($V$3:$X$3,V545:X545)) -> 0.004628 | AD545: =1-(1-AC545)^(1/12) -> 0.00038648716 | AE545: =SUMPRODUCT($V$2:$X$2,V545:X545) -> 0.0024712 | AF545: =1-(1-AE545)^(1/12) -> 0.00020616695 | AH545: Lifecycle | AI545: Balanced | AJ545: =AH545&"_"&AI545&"_"&AK545 -> Lifecycle_Balanced_0 | AK545: 0 | AL545: =VLOOKUP($U545,[2]Standard_Balanced!$Q$1:$T$542,2,FALSE) -> 0 | AM545: =VLOOKUP($U545,[2]Standard_Balanced!$Q$1:$T$542,3,FALSE) -> 0.712 | AN545: =VLOOKUP($U545,[2]Standard_Balanced!$Q$1:$T$542,4,FALSE) -> 0.288 | AO545: =SUM(AL545:AN545) -> 1 | AP545: =SUMPRODUCT($AL$1:$AN$1,AL545:AN545) -> 0.0488012 | AQ545: =(1+AP545)^(1/12)-1 -> 0.0039785433 | AR545: 0 | AS545: =IF(AR545=0,0,SUMPRODUCT($AL$3:$AN$3,AL545:AN545)) -> 0 | AT545: =1-(1-AS545)^(1/12) -> 0 | AU545: =SUMPRODUCT($AL$2:$AN$2,AL545:AN545) -> 0.0024712 | AV545: =1-(1-AU545)^(1/12) -> 0.00020616695 | AX545: DIS | AY545: Non-Standard | AZ545: =AX545&"_"&AY545&"_"&BA545 -> DIS_Non-Standard_0 | BA545: 0 | BB545: =VLOOKUP($BA545,'[2]NonStandard DIS'!$Q$1:$X$542,2,FALSE) -> 0 | BC545: =VLOOKUP($BA545,'[2]NonStandard DIS'!$Q$1:$X$542,3,FALSE) -> 0 | BD545: =VLOOKUP($BA545,'[2]NonStandard DIS'!$Q$1:$X$542,4,FALSE) -> 0 | BE545: =VLOOKUP($BA545,'[2]NonStandard DIS'!$Q$1:$X$542,5,FALSE) -> 0 | BF545: =VLOOKUP($BA545,'[2]NonStandard DIS'!$Q$1:$X$542,6,FALSE) -> 0 | BG545: =VLOOKUP($BA545,'[2]NonStandard DIS'!$Q$1:$X$542,7,FALSE) -> 0 | BH545: =VLOOKUP($BA545,'[2]NonStandard DIS'!$Q$1:$X$542,8,FALSE) -> 1 | BI545: =SUM(BB545:BH545) -> 1 | BJ545: =SUMPRODUCT($BB$1:$BH$1,BB545:BH545) -> 0.05135 | BK545: =(1+BJ545)^(1/12)-1 -> 0.0041816398 | BL545: 1 | BM545: =IF(BL545=0,0,SUMPRODUCT($BB$3:$BH$3,BB545:BH545)) -> 0.0065 | BN545: =(1+BM545)^(1/12)-1 -> 0.00054005962 | BO545: =SUMPRODUCT($BB$2:$BH$2,BB545:BH545) -> 0.0025 | BP545: =(1+BO545)^(1/12)-1 -> 0.000208095
A547: Lifecycle | B547: Dynamic | C547: =A547&"_"&B547&"_"&D547 -> Lifecycle_Dynamic_540 | D547: 540 | E547: =VLOOKUP($D547,'[2]LC Dynamic'!$Q$2:$U$542,2,FALSE) -> 0 | F547: =VLOOKUP($D547,'[2]LC Dynamic'!$Q$2:$U$542,3,FALSE) -> 0 | G547: =VLOOKUP($D547,'[2]LC Dynamic'!$Q$2:$U$542,4,FALSE) -> 0.308 | H547: =VLOOKUP($D547,'[2]LC Dynamic'!$Q$2:$U$542,5,FALSE) -> 0.692 | I547: =SUM(E547:H547) -> 1 | J547: =SUMPRODUCT($E$1:$H$1,E547:H547) -> 0.0697285 | K547: =(1+J547)^(1/12)-1 -> 0.0056328785 | L547: 0 | M547: =IF($L547=0,0,SUMPRODUCT($E$3:$H$3,E547:H547)) -> 0 | N547: =1-(1-M547)^(1/12) -> 0 | O547: =SUMPRODUCT($E$2:$H$2,E547:H547) -> 0.0056776 | P547: =1-(1-O547)^(1/12) -> 0.00047436902 | R547: Autopilot | S547: Dynamic | T547: =R547&"_"&S547&"_"&U547 -> Autopilot_Dynamic_540 | U547: 540 | V547: =VLOOKUP($U547,'[2]AP Dynamic'!$Q$1:$T$542,2,FALSE) -> 0.88888889 | W547: =VLOOKUP($U547,'[2]AP Dynamic'!$Q$1:$T$542,3,FALSE) -> 0.11111111 | X547: =VLOOKUP($U547,'[2]AP Dynamic'!$Q$1:$T$542,4,FALSE) -> 0 | Y547: =SUM(V547:X547) -> 1 | Z547: =SUMPRODUCT($V$1:$X$1,V547:X547) -> 0.06315 | AA547: =(1+Z547)^(1/12)-1 -> 0.0051160592 | AB547: 1 | AC547: =IF($AB547=0,0,SUMPRODUCT($V$3:$X$3,V547:X547)) -> 0.0082777778 | AD547: =1-(1-AC547)^(1/12) -> 0.00069244588 | AE547: =SUMPRODUCT($V$2:$X$2,V547:X547) -> 0.0025 | AF547: =1-(1-AE547)^(1/12) -> 0.00020857243 | AH547: Lifecycle | AI547: Dynamic | AJ547: =AH547&"_"&AI547&"_"&AK547 -> Lifecycle_Dynamic_540 | AK547: 540 | AL547: =VLOOKUP($U547,[2]Standard_Dynamic!$Q$1:$T$542,2,FALSE) -> 0.88888889 | AM547: =VLOOKUP($U547,[2]Standard_Dynamic!$Q$1:$T$542,3,FALSE) -> 0.11111111 | AN547: =VLOOKUP($U547,[2]Standard_Dynamic!$Q$1:$T$542,4,FALSE) -> 0 | AO547: =SUM(AL547:AN547) -> 1 | AP547: =SUMPRODUCT($AL$1:$AN$1,AL547:AN547) -> 0.06315 | AQ547: =(1+AP547)^(1/12)-1 -> 0.0051160592 | AR547: 0 | AS547: =IF(AR547=0,0,SUMPRODUCT($AL$3:$AN$3,AL547:AN547)) -> 0 | AT547: =1-(1-AS547)^(1/12) -> 0 | AU547: =SUMPRODUCT($AL$2:$AN$2,AL547:AN547) -> 0.0025 | AV547: =1-(1-AU547)^(1/12) -> 0.00020857243 | AX547: DIS | AY547: Standard | AZ547: =AX547&"_"&AY547&"_"&BA547 -> DIS_Standard_540 | BA547: 540 | BB547: =VLOOKUP($BA547,'[2]Standard DIS'!$Q$1:$X$542,4,FALSE) -> 0 | BF547: =VLOOKUP($BA547,'[2]Standard DIS'!$Q$1:$X$542,2,FALSE) -> 0.88888889 | BH547: =VLOOKUP($BA547,'[2]Standard DIS'!$Q$1:$X$542,3,FALSE) -> 0.11111111 | BI547: =SUM(BB547:BH547) -> 1 | BJ547: =SUMPRODUCT($BB$1:$BH$1,BB547:BH547) -> 0.06315 | BK547: =(1+BJ547)^(1/12)-1 -> 0.0051160592 | BL547: 0 | BM547: =IF(BL547=0,0,SUMPRODUCT($BB$3:$BH$3,BB547:BH547)) -> 0 | BN547: =(1+BM547)^(1/12)-1 -> 0 | BO547: =SUMPRODUCT($BB$2:$BH$2,BB547:BH547) -> 0.0025 | BP547: =(1+BO547)^(1/12)-1 -> 0.000208095
A548: Lifecycle | B548: Dynamic | C548: =A548&"_"&B548&"_"&D548 -> Lifecycle_Dynamic_539 | D548: 539 | E548: =VLOOKUP($D548,'[2]LC Dynamic'!$Q$2:$U$542,2,FALSE) -> 0 | F548: =VLOOKUP($D548,'[2]LC Dynamic'!$Q$2:$U$542,3,FALSE) -> 0 | G548: =VLOOKUP($D548,'[2]LC Dynamic'!$Q$2:$U$542,4,FALSE) -> 0.308 | H548: =VLOOKUP($D548,'[2]LC Dynamic'!$Q$2:$U$542,5,FALSE) -> 0.692 | I548: =SUM(E548:H548) -> 1 | J548: =SUMPRODUCT($E$1:$H$1,E548:H548) -> 0.0697285 | K548: =(1+J548)^(1/12)-1 -> 0.0056328785 | L548: 0 | M548: =IF($L548=0,0,SUMPRODUCT($E$3:$H$3,E548:H548)) -> 0 | N548: =1-(1-M548)^(1/12) -> 0 | O548: =SUMPRODUCT($E$2:$H$2,E548:H548) -> 0.0056776 | P548: =1-(1-O548)^(1/12) -> 0.00047436902 | R548: Autopilot | S548: Dynamic | T548: =R548&"_"&S548&"_"&U548 -> Autopilot_Dynamic_539 | U548: 539 | V548: =VLOOKUP($U548,'[2]AP Dynamic'!$Q$1:$T$542,2,FALSE) -> 0.88888889 | W548: =VLOOKUP($U548,'[2]AP Dynamic'!$Q$1:$T$542,3,FALSE) -> 0.11111111 | X548: =VLOOKUP($U548,'[2]AP Dynamic'!$Q$1:$T$542,4,FALSE) -> 0 | Y548: =SUM(V548:X548) -> 1 | Z548: =SUMPRODUCT($V$1:$X$1,V548:X548) -> 0.06315 | AA548: =(1+Z548)^(1/12)-1 -> 0.0051160592 | AB548: 1 | AC548: =IF($AB548=0,0,SUMPRODUCT($V$3:$X$3,V548:X548)) -> 0.0082777778 | AD548: =1-(1-AC548)^(1/12) -> 0.00069244588 | AE548: =SUMPRODUCT($V$2:$X$2,V548:X548) -> 0.0025 | AF548: =1-(1-AE548)^(1/12) -> 0.00020857243 | AH548: Lifecycle | AI548: Dynamic | AJ548: =AH548&"_"&AI548&"_"&AK548 -> Lifecycle_Dynamic_539 | AK548: 539 | AL548: =VLOOKUP($U548,[2]Standard_Dynamic!$Q$1:$T$542,2,FALSE) -> 0.88888889 | AM548: =VLOOKUP($U548,[2]Standard_Dynamic!$Q$1:$T$542,3,FALSE) -> 0.11111111 | AN548: =VLOOKUP($U548,[2]Standard_Dynamic!$Q$1:$T$542,4,FALSE) -> 0 | AO548: =SUM(AL548:AN548) -> 1 | AP548: =SUMPRODUCT($AL$1:$AN$1,AL548:AN548) -> 0.06315 | AQ548: =(1+AP548)^(1/12)-1 -> 0.0051160592 | AR548: 0 | AS548: =IF(AR548=0,0,SUMPRODUCT($AL$3:$AN$3,AL548:AN548)) -> 0 | AT548: =1-(1-AS548)^(1/12) -> 0 | AU548: =SUMPRODUCT($AL$2:$AN$2,AL548:AN548) -> 0.0025 | AV548: =1-(1-AU548)^(1/12) -> 0.00020857243 | AX548: DIS | AY548: Standard | AZ548: =AX548&"_"&AY548&"_"&BA548 -> DIS_Standard_539 | BA548: 539 | BB548: =VLOOKUP($BA548,'[2]Standard DIS'!$Q$1:$X$542,4,FALSE) -> 0 | BF548: =VLOOKUP($BA548,'[2]Standard DIS'!$Q$1:$X$542,2,FALSE) -> 0.88888889 | BH548: =VLOOKUP($BA548,'[2]Standard DIS'!$Q$1:$X$542,3,FALSE) -> 0.11111111 | BI548: =SUM(BB548:BH548) -> 1 | BJ548: =SUMPRODUCT($BB$1:$BH$1,BB548:BH548) -> 0.06315 | BK548: =(1+BJ548)^(1/12)-1 -> 0.0051160592 | BL548: 0 | BM548: =IF(BL548=0,0,SUMPRODUCT($BB$3:$BH$3,BB548:BH548)) -> 0 | BN548: =(1+BM548)^(1/12)-1 -> 0 | BO548: =SUMPRODUCT($BB$2:$BH$2,BB548:BH548) -> 0.0025 | BP548: =(1+BO548)^(1/12)-1 -> 0.000208095
A549: Lifecycle | B549: Dynamic | C549: =A549&"_"&B549&"_"&D549 -> Lifecycle_Dynamic_538 | D549: 538 | E549: =VLOOKUP($D549,'[2]LC Dynamic'!$Q$2:$U$542,2,FALSE) -> 0 | F549: =VLOOKUP($D549,'[2]LC Dynamic'!$Q$2:$U$542,3,FALSE) -> 0 | G549: =VLOOKUP($D549,'[2]LC Dynamic'!$Q$2:$U$542,4,FALSE) -> 0.308 | H549: =VLOOKUP($D549,'[2]LC Dynamic'!$Q$2:$U$542,5,FALSE) -> 0.692 | I549: =SUM(E549:H549) -> 1 | J549: =SUMPRODUCT($E$1:$H$1,E549:H549) -> 0.0697285 | K549: =(1+J549)^(1/12)-1 -> 0.0056328785 | L549: 0 | M549: =IF($L549=0,0,SUMPRODUCT($E$3:$H$3,E549:H549)) -> 0 | N549: =1-(1-M549)^(1/12) -> 0 | O549: =SUMPRODUCT($E$2:$H$2,E549:H549) -> 0.0056776 | P549: =1-(1-O549)^(1/12) -> 0.00047436902 | R549: Autopilot | S549: Dynamic | T549: =R549&"_"&S549&"_"&U549 -> Autopilot_Dynamic_538 | U549: 538 | V549: =VLOOKUP($U549,'[2]AP Dynamic'!$Q$1:$T$542,2,FALSE) -> 0.88888889 | W549: =VLOOKUP($U549,'[2]AP Dynamic'!$Q$1:$T$542,3,FALSE) -> 0.11111111 | X549: =VLOOKUP($U549,'[2]AP Dynamic'!$Q$1:$T$542,4,FALSE) -> 0 | Y549: =SUM(V549:X549) -> 1 | Z549: =SUMPRODUCT($V$1:$X$1,V549:X549) -> 0.06315 | AA549: =(1+Z549)^(1/12)-1 -> 0.0051160592 | AB549: 1 | AC549: =IF($AB549=0,0,SUMPRODUCT($V$3:$X$3,V549:X549)) -> 0.0082777778 | AD549: =1-(1-AC549)^(1/12) -> 0.00069244588 | AE549: =SUMPRODUCT($V$2:$X$2,V549:X549) -> 0.0025 | AF549: =1-(1-AE549)^(1/12) -> 0.00020857243 | AH549: Lifecycle | AI549: Dynamic | AJ549: =AH549&"_"&AI549&"_"&AK549 -> Lifecycle_Dynamic_538 | AK549: 538 | AL549: =VLOOKUP($U549,[2]Standard_Dynamic!$Q$1:$T$542,2,FALSE) -> 0.88888889 | AM549: =VLOOKUP($U549,[2]Standard_Dynamic!$Q$1:$T$542,3,FALSE) -> 0.11111111 | AN549: =VLOOKUP($U549,[2]Standard_Dynamic!$Q$1:$T$542,4,FALSE) -> 0 | AO549: =SUM(AL549:AN549) -> 1 | AP549: =SUMPRODUCT($AL$1:$AN$1,AL549:AN549) -> 0.06315 | AQ549: =(1+AP549)^(1/12)-1 -> 0.0051160592 | AR549: 0 | AS549: =IF(AR549=0,0,SUMPRODUCT($AL$3:$AN$3,AL549:AN549)) -> 0 | AT549: =1-(1-AS549)^(1/12) -> 0 | AU549: =SUMPRODUCT($AL$2:$AN$2,AL549:AN549) -> 0.0025 | AV549: =1-(1-AU549)^(1/12) -> 0.00020857243 | AX549: DIS | AY549: Standard | AZ549: =AX549&"_"&AY549&"_"&BA549 -> DIS_Standard_538 | BA549: 538 | BB549: =VLOOKUP($BA549,'[2]Standard DIS'!$Q$1:$X$542,4,FALSE) -> 0 | BF549: =VLOOKUP($BA549,'[2]Standard DIS'!$Q$1:$X$542,2,FALSE) -> 0.88888889 | BH549: =VLOOKUP($BA549,'[2]Standard DIS'!$Q$1:$X$542,3,FALSE) -> 0.11111111 | BI549: =SUM(BB549:BH549) -> 1 | BJ549: =SUMPRODUCT($BB$1:$BH$1,BB549:BH549) -> 0.06315 | BK549: =(1+BJ549)^(1/12)-1 -> 0.0051160592 | BL549: 0 | BM549: =IF(BL549=0,0,SUMPRODUCT($BB$3:$BH$3,BB549:BH549)) -> 0 | BN549: =(1+BM549)^(1/12)-1 -> 0 | BO549: =SUMPRODUCT($BB$2:$BH$2,BB549:BH549) -> 0.0025 | BP549: =(1+BO549)^(1/12)-1 -> 0.000208095
A550: Lifecycle | B550: Dynamic | C550: =A550&"_"&B550&"_"&D550 -> Lifecycle_Dynamic_537 | D550: 537 | E550: =VLOOKUP($D550,'[2]LC Dynamic'!$Q$2:$U$542,2,FALSE) -> 0 | F550: =VLOOKUP($D550,'[2]LC Dynamic'!$Q$2:$U$542,3,FALSE) -> 0 | G550: =VLOOKUP($D550,'[2]LC Dynamic'!$Q$2:$U$542,4,FALSE) -> 0.308 | H550: =VLOOKUP($D550,'[2]LC Dynamic'!$Q$2:$U$542,5,FALSE) -> 0.692 | I550: =SUM(E550:H550) -> 1 | J550: =SUMPRODUCT($E$1:$H$1,E550:H550) -> 0.0697285 | K550: =(1+J550)^(1/12)-1 -> 0.0056328785 | L550: 0 | M550: =IF($L550=0,0,SUMPRODUCT($E$3:$H$3,E550:H550)) -> 0 | N550: =1-(1-M550)^(1/12) -> 0 | O550: =SUMPRODUCT($E$2:$H$2,E550:H550) -> 0.0056776 | P550: =1-(1-O550)^(1/12) -> 0.00047436902 | R550: Autopilot | S550: Dynamic | T550: =R550&"_"&S550&"_"&U550 -> Autopilot_Dynamic_537 | U550: 537 | V550: =VLOOKUP($U550,'[2]AP Dynamic'!$Q$1:$T$542,2,FALSE) -> 0.88888889 | W550: =VLOOKUP($U550,'[2]AP Dynamic'!$Q$1:$T$542,3,FALSE) -> 0.11111111 | X550: =VLOOKUP($U550,'[2]AP Dynamic'!$Q$1:$T$542,4,FALSE) -> 0 | Y550: =SUM(V550:X550) -> 1 | Z550: =SUMPRODUCT($V$1:$X$1,V550:X550) -> 0.06315 | AA550: =(1+Z550)^(1/12)-1 -> 0.0051160592 | AB550: 1 | AC550: =IF($AB550=0,0,SUMPRODUCT($V$3:$X$3,V550:X550)) -> 0.0082777778 | AD550: =1-(1-AC550)^(1/12) -> 0.00069244588 | AE550: =SUMPRODUCT($V$2:$X$2,V550:X550) -> 0.0025 | AF550: =1-(1-AE550)^(1/12) -> 0.00020857243 | AH550: Lifecycle | AI550: Dynamic | AJ550: =AH550&"_"&AI550&"_"&AK550 -> Lifecycle_Dynamic_537 | AK550: 537 | AL550: =VLOOKUP($U550,[2]Standard_Dynamic!$Q$1:$T$542,2,FALSE) -> 0.88888889 | AM550: =VLOOKUP($U550,[2]Standard_Dynamic!$Q$1:$T$542,3,FALSE) -> 0.11111111 | AN550: =VLOOKUP($U550,[2]Standard_Dynamic!$Q$1:$T$542,4,FALSE) -> 0 | AO550: =SUM(AL550:AN550) -> 1 | AP550: =SUMPRODUCT($AL$1:$AN$1,AL550:AN550) -> 0.06315 | AQ550: =(1+AP550)^(1/12)-1 -> 0.0051160592 | AR550: 0 | AS550: =IF(AR550=0,0,SUMPRODUCT($AL$3:$AN$3,AL550:AN550)) -> 0 | AT550: =1-(1-AS550)^(1/12) -> 0 | AU550: =SUMPRODUCT($AL$2:$AN$2,AL550:AN550) -> 0.0025 | AV550: =1-(1-AU550)^(1/12) -> 0.00020857243 | AX550: DIS | AY550: Standard | AZ550: =AX550&"_"&AY550&"_"&BA550 -> DIS_Standard_537 | BA550: 537 | BB550: =VLOOKUP($BA550,'[2]Standard DIS'!$Q$1:$X$542,4,FALSE) -> 0 | BF550: =VLOOKUP($BA550,'[2]Standard DIS'!$Q$1:$X$542,2,FALSE) -> 0.88888889 | BH550: =VLOOKUP($BA550,'[2]Standard DIS'!$Q$1:$X$542,3,FALSE) -> 0.11111111 | BI550: =SUM(BB550:BH550) -> 1 | BJ550: =SUMPRODUCT($BB$1:$BH$1,BB550:BH550) -> 0.06315 | BK550: =(1+BJ550)^(1/12)-1 -> 0.0051160592 | BL550: 0 | BM550: =IF(BL550=0,0,SUMPRODUCT($BB$3:$BH$3,BB550:BH550)) -> 0 | BN550: =(1+BM550)^(1/12)-1 -> 0 | BO550: =SUMPRODUCT($BB$2:$BH$2,BB550:BH550) -> 0.0025 | BP550: =(1+BO550)^(1/12)-1 -> 0.000208095
A551: Lifecycle | B551: Dynamic | C551: =A551&"_"&B551&"_"&D551 -> Lifecycle_Dynamic_536 | D551: 536 | E551: =VLOOKUP($D551,'[2]LC Dynamic'!$Q$2:$U$542,2,FALSE) -> 0 | F551: =VLOOKUP($D551,'[2]LC Dynamic'!$Q$2:$U$542,3,FALSE) -> 0 | G551: =VLOOKUP($D551,'[2]LC Dynamic'!$Q$2:$U$542,4,FALSE) -> 0.308 | H551: =VLOOKUP($D551,'[2]LC Dynamic'!$Q$2:$U$542,5,FALSE) -> 0.692 | I551: =SUM(E551:H551) -> 1 | J551: =SUMPRODUCT($E$1:$H$1,E551:H551) -> 0.0697285 | K551: =(1+J551)^(1/12)-1 -> 0.0056328785 | L551: 0 | M551: =IF($L551=0,0,SUMPRODUCT($E$3:$H$3,E551:H551)) -> 0 | N551: =1-(1-M551)^(1/12) -> 0 | O551: =SUMPRODUCT($E$2:$H$2,E551:H551) -> 0.0056776 | P551: =1-(1-O551)^(1/12) -> 0.00047436902 | R551: Autopilot | S551: Dynamic | T551: =R551&"_"&S551&"_"&U551 -> Autopilot_Dynamic_536 | U551: 536 | V551: =VLOOKUP($U551,'[2]AP Dynamic'!$Q$1:$T$542,2,FALSE) -> 0.88888889 | W551: =VLOOKUP($U551,'[2]AP Dynamic'!$Q$1:$T$542,3,FALSE) -> 0.11111111 | X551: =VLOOKUP($U551,'[2]AP Dynamic'!$Q$1:$T$542,4,FALSE) -> 0 | Y551: =SUM(V551:X551) -> 1 | Z551: =SUMPRODUCT($V$1:$X$1,V551:X551) -> 0.06315 | AA551: =(1+Z551)^(1/12)-1 -> 0.0051160592 | AB551: 1 | AC551: =IF($AB551=0,0,SUMPRODUCT($V$3:$X$3,V551:X551)) -> 0.0082777778 | AD551: =1-(1-AC551)^(1/12) -> 0.00069244588 | AE551: =SUMPRODUCT($V$2:$X$2,V551:X551) -> 0.0025 | AF551: =1-(1-AE551)^(1/12) -> 0.00020857243 | AH551: Lifecycle | AI551: Dynamic | AJ551: =AH551&"_"&AI551&"_"&AK551 -> Lifecycle_Dynamic_536 | AK551: 536 | AL551: =VLOOKUP($U551,[2]Standard_Dynamic!$Q$1:$T$542,2,FALSE) -> 0.88888889 | AM551: =VLOOKUP($U551,[2]Standard_Dynamic!$Q$1:$T$542,3,FALSE) -> 0.11111111 | AN551: =VLOOKUP($U551,[2]Standard_Dynamic!$Q$1:$T$542,4,FALSE) -> 0 | AO551: =SUM(AL551:AN551) -> 1 | AP551: =SUMPRODUCT($AL$1:$AN$1,AL551:AN551) -> 0.06315 | AQ551: =(1+AP551)^(1/12)-1 -> 0.0051160592 | AR551: 0 | AS551: =IF(AR551=0,0,SUMPRODUCT($AL$3:$AN$3,AL551:AN551)) -> 0 | AT551: =1-(1-AS551)^(1/12) -> 0 | AU551: =SUMPRODUCT($AL$2:$AN$2,AL551:AN551) -> 0.0025 | AV551: =1-(1-AU551)^(1/12) -> 0.00020857243 | AX551: DIS | AY551: Standard | AZ551: =AX551&"_"&AY551&"_"&BA551 -> DIS_Standard_536 | BA551: 536 | BB551: =VLOOKUP($BA551,'[2]Standard DIS'!$Q$1:$X$542,4,FALSE) -> 0 | BF551: =VLOOKUP($BA551,'[2]Standard DIS'!$Q$1:$X$542,2,FALSE) -> 0.88888889 | BH551: =VLOOKUP($BA551,'[2]Standard DIS'!$Q$1:$X$542,3,FALSE) -> 0.11111111 | BI551: =SUM(BB551:BH551) -> 1 | BJ551: =SUMPRODUCT($BB$1:$BH$1,BB551:BH551) -> 0.06315 | BK551: =(1+BJ551)^(1/12)-1 -> 0.0051160592 | BL551: 0 | BM551: =IF(BL551=0,0,SUMPRODUCT($BB$3:$BH$3,BB551:BH551)) -> 0 | BN551: =(1+BM551)^(1/12)-1 -> 0 | BO551: =SUMPRODUCT($BB$2:$BH$2,BB551:BH551) -> 0.0025 | BP551: =(1+BO551)^(1/12)-1 -> 0.000208095
A552: Lifecycle | B552: Dynamic | C552: =A552&"_"&B552&"_"&D552 -> Lifecycle_Dynamic_535 | D552: 535 | E552: =VLOOKUP($D552,'[2]LC Dynamic'!$Q$2:$U$542,2,FALSE) -> 0 | F552: =VLOOKUP($D552,'[2]LC Dynamic'!$Q$2:$U$542,3,FALSE) -> 0 | G552: =VLOOKUP($D552,'[2]LC Dynamic'!$Q$2:$U$542,4,FALSE) -> 0.308 | H552: =VLOOKUP($D552,'[2]LC Dynamic'!$Q$2:$U$542,5,FALSE) -> 0.692 | I552: =SUM(E552:H552) -> 1 | J552: =SUMPRODUCT($E$1:$H$1,E552:H552) -> 0.0697285 | K552: =(1+J552)^(1/12)-1 -> 0.0056328785 | L552: 0 | M552: =IF($L552=0,0,SUMPRODUCT($E$3:$H$3,E552:H552)) -> 0 | N552: =1-(1-M552)^(1/12) -> 0 | O552: =SUMPRODUCT($E$2:$H$2,E552:H552) -> 0.0056776 | P552: =1-(1-O552)^(1/12) -> 0.00047436902 | R552: Autopilot | S552: Dynamic | T552: =R552&"_"&S552&"_"&U552 -> Autopilot_Dynamic_535 | U552: 535 | V552: =VLOOKUP($U552,'[2]AP Dynamic'!$Q$1:$T$542,2,FALSE) -> 0.88888889 | W552: =VLOOKUP($U552,'[2]AP Dynamic'!$Q$1:$T$542,3,FALSE) -> 0.11111111 | X552: =VLOOKUP($U552,'[2]AP Dynamic'!$Q$1:$T$542,4,FALSE) -> 0 | Y552: =SUM(V552:X552) -> 1 | Z552: =SUMPRODUCT($V$1:$X$1,V552:X552) -> 0.06315 | AA552: =(1+Z552)^(1/12)-1 -> 0.0051160592 | AB552: 1 | AC552: =IF($AB552=0,0,SUMPRODUCT($V$3:$X$3,V552:X552)) -> 0.0082777778 | AD552: =1-(1-AC552)^(1/12) -> 0.00069244588 | AE552: =SUMPRODUCT($V$2:$X$2,V552:X552) -> 0.0025 | AF552: =1-(1-AE552)^(1/12) -> 0.00020857243 | AH552: Lifecycle | AI552: Dynamic | AJ552: =AH552&"_"&AI552&"_"&AK552 -> Lifecycle_Dynamic_535 | AK552: 535 | AL552: =VLOOKUP($U552,[2]Standard_Dynamic!$Q$1:$T$542,2,FALSE) -> 0.88888889 | AM552: =VLOOKUP($U552,[2]Standard_Dynamic!$Q$1:$T$542,3,FALSE) -> 0.11111111 | AN552: =VLOOKUP($U552,[2]Standard_Dynamic!$Q$1:$T$542,4,FALSE) -> 0 | AO552: =SUM(AL552:AN552) -> 1 | AP552: =SUMPRODUCT($AL$1:$AN$1,AL552:AN552) -> 0.06315 | AQ552: =(1+AP552)^(1/12)-1 -> 0.0051160592 | AR552: 0 | AS552: =IF(AR552=0,0,SUMPRODUCT($AL$3:$AN$3,AL552:AN552)) -> 0 | AT552: =1-(1-AS552)^(1/12) -> 0 | AU552: =SUMPRODUCT($AL$2:$AN$2,AL552:AN552) -> 0.0025 | AV552: =1-(1-AU552)^(1/12) -> 0.00020857243 | AX552: DIS | AY552: Standard | AZ552: =AX552&"_"&AY552&"_"&BA552 -> DIS_Standard_535 | BA552: 535 | BB552: =VLOOKUP($BA552,'[2]Standard DIS'!$Q$1:$X$542,4,FALSE) -> 0 | BF552: =VLOOKUP($BA552,'[2]Standard DIS'!$Q$1:$X$542,2,FALSE) -> 0.88888889 | BH552: =VLOOKUP($BA552,'[2]Standard DIS'!$Q$1:$X$542,3,FALSE) -> 0.11111111 | BI552: =SUM(BB552:BH552) -> 1 | BJ552: =SUMPRODUCT($BB$1:$BH$1,BB552:BH552) -> 0.06315 | BK552: =(1+BJ552)^(1/12)-1 -> 0.0051160592 | BL552: 0 | BM552: =IF(BL552=0,0,SUMPRODUCT($BB$3:$BH$3,BB552:BH552)) -> 0 | BN552: =(1+BM552)^(1/12)-1 -> 0 | BO552: =SUMPRODUCT($BB$2:$BH$2,BB552:BH552) -> 0.0025 | BP552: =(1+BO552)^(1/12)-1 -> 0.000208095
A553: Lifecycle | B553: Dynamic | C553: =A553&"_"&B553&"_"&D553 -> Lifecycle_Dynamic_534 | D553: 534 | E553: =VLOOKUP($D553,'[2]LC Dynamic'!$Q$2:$U$542,2,FALSE) -> 0 | F553: =VLOOKUP($D553,'[2]LC Dynamic'!$Q$2:$U$542,3,FALSE) -> 0 | G553: =VLOOKUP($D553,'[2]LC Dynamic'!$Q$2:$U$542,4,FALSE) -> 0.308 | H553: =VLOOKUP($D553,'[2]LC Dynamic'!$Q$2:$U$542,5,FALSE) -> 0.692 | I553: =SUM(E553:H553) -> 1 | J553: =SUMPRODUCT($E$1:$H$1,E553:H553) -> 0.0697285 | K553: =(1+J553)^(1/12)-1 -> 0.0056328785 | L553: 0 | M553: =IF($L553=0,0,SUMPRODUCT($E$3:$H$3,E553:H553)) -> 0 | N553: =1-(1-M553)^(1/12) -> 0 | O553: =SUMPRODUCT($E$2:$H$2,E553:H553) -> 0.0056776 | P553: =1-(1-O553)^(1/12) -> 0.00047436902 | R553: Autopilot | S553: Dynamic | T553: =R553&"_"&S553&"_"&U553 -> Autopilot_Dynamic_534 | U553: 534 | V553: =VLOOKUP($U553,'[2]AP Dynamic'!$Q$1:$T$542,2,FALSE) -> 0.88888889 | W553: =VLOOKUP($U553,'[2]AP Dynamic'!$Q$1:$T$542,3,FALSE) -> 0.11111111 | X553: =VLOOKUP($U553,'[2]AP Dynamic'!$Q$1:$T$542,4,FALSE) -> 0 | Y553: =SUM(V553:X553) -> 1 | Z553: =SUMPRODUCT($V$1:$X$1,V553:X553) -> 0.06315 | AA553: =(1+Z553)^(1/12)-1 -> 0.0051160592 | AB553: 1 | AC553: =IF($AB553=0,0,SUMPRODUCT($V$3:$X$3,V553:X553)) -> 0.0082777778 | AD553: =1-(1-AC553)^(1/12) -> 0.00069244588 | AE553: =SUMPRODUCT($V$2:$X$2,V553:X553) -> 0.0025 | AF553: =1-(1-AE553)^(1/12) -> 0.00020857243 | AH553: Lifecycle | AI553: Dynamic | AJ553: =AH553&"_"&AI553&"_"&AK553 -> Lifecycle_Dynamic_534 | AK553: 534 | AL553: =VLOOKUP($U553,[2]Standard_Dynamic!$Q$1:$T$542,2,FALSE) -> 0.88888889 | AM553: =VLOOKUP($U553,[2]Standard_Dynamic!$Q$1:$T$542,3,FALSE) -> 0.11111111 | AN553: =VLOOKUP($U553,[2]Standard_Dynamic!$Q$1:$T$542,4,FALSE) -> 0 | AO553: =SUM(AL553:AN553) -> 1 | AP553: =SUMPRODUCT($AL$1:$AN$1,AL553:AN553) -> 0.06315 | AQ553: =(1+AP553)^(1/12)-1 -> 0.0051160592 | AR553: 0 | AS553: =IF(AR553=0,0,SUMPRODUCT($AL$3:$AN$3,AL553:AN553)) -> 0 | AT553: =1-(1-AS553)^(1/12) -> 0 | AU553: =SUMPRODUCT($AL$2:$AN$2,AL553:AN553) -> 0.0025 | AV553: =1-(1-AU553)^(1/12) -> 0.00020857243 | AX553: DIS | AY553: Standard | AZ553: =AX553&"_"&AY553&"_"&BA553 -> DIS_Standard_534 | BA553: 534 | BB553: =VLOOKUP($BA553,'[2]Standard DIS'!$Q$1:$X$542,4,FALSE) -> 0 | BF553: =VLOOKUP($BA553,'[2]Standard DIS'!$Q$1:$X$542,2,FALSE) -> 0.88888889 | BH553: =VLOOKUP($BA553,'[2]Standard DIS'!$Q$1:$X$542,3,FALSE) -> 0.11111111 | BI553: =SUM(BB553:BH553) -> 1 | BJ553: =SUMPRODUCT($BB$1:$BH$1,BB553:BH553) -> 0.06315 | BK553: =(1+BJ553)^(1/12)-1 -> 0.0051160592 | BL553: 0 | BM553: =IF(BL553=0,0,SUMPRODUCT($BB$3:$BH$3,BB553:BH553)) -> 0 | BN553: =(1+BM553)^(1/12)-1 -> 0 | BO553: =SUMPRODUCT($BB$2:$BH$2,BB553:BH553) -> 0.0025 | BP553: =(1+BO553)^(1/12)-1 -> 0.000208095
A554: Lifecycle | B554: Dynamic | C554: =A554&"_"&B554&"_"&D554 -> Lifecycle_Dynamic_533 | D554: 533 | E554: =VLOOKUP($D554,'[2]LC Dynamic'!$Q$2:$U$542,2,FALSE) -> 0 | F554: =VLOOKUP($D554,'[2]LC Dynamic'!$Q$2:$U$542,3,FALSE) -> 0 | G554: =VLOOKUP($D554,'[2]LC Dynamic'!$Q$2:$U$542,4,FALSE) -> 0.308 | H554: =VLOOKUP($D554,'[2]LC Dynamic'!$Q$2:$U$542,5,FALSE) -> 0.692 | I554: =SUM(E554:H554) -> 1 | J554: =SUMPRODUCT($E$1:$H$1,E554:H554) -> 0.0697285 | K554: =(1+J554)^(1/12)-1 -> 0.0056328785 | L554: 0 | M554: =IF($L554=0,0,SUMPRODUCT($E$3:$H$3,E554:H554)) -> 0 | N554: =1-(1-M554)^(1/12) -> 0 | O554: =SUMPRODUCT($E$2:$H$2,E554:H554) -> 0.0056776 | P554: =1-(1-O554)^(1/12) -> 0.00047436902 | R554: Autopilot | S554: Dynamic | T554: =R554&"_"&S554&"_"&U554 -> Autopilot_Dynamic_533 | U554: 533 | V554: =VLOOKUP($U554,'[2]AP Dynamic'!$Q$1:$T$542,2,FALSE) -> 0.88888889 | W554: =VLOOKUP($U554,'[2]AP Dynamic'!$Q$1:$T$542,3,FALSE) -> 0.11111111 | X554: =VLOOKUP($U554,'[2]AP Dynamic'!$Q$1:$T$542,4,FALSE) -> 0 | Y554: =SUM(V554:X554) -> 1 | Z554: =SUMPRODUCT($V$1:$X$1,V554:X554) -> 0.06315 | AA554: =(1+Z554)^(1/12)-1 -> 0.0051160592 | AB554: 1 | AC554: =IF($AB554=0,0,SUMPRODUCT($V$3:$X$3,V554:X554)) -> 0.0082777778 | AD554: =1-(1-AC554)^(1/12) -> 0.00069244588 | AE554: =SUMPRODUCT($V$2:$X$2,V554:X554) -> 0.0025 | AF554: =1-(1-AE554)^(1/12) -> 0.00020857243 | AH554: Lifecycle | AI554: Dynamic | AJ554: =AH554&"_"&AI554&"_"&AK554 -> Lifecycle_Dynamic_533 | AK554: 533 | AL554: =VLOOKUP($U554,[2]Standard_Dynamic!$Q$1:$T$542,2,FALSE) -> 0.88888889 | AM554: =VLOOKUP($U554,[2]Standard_Dynamic!$Q$1:$T$542,3,FALSE) -> 0.11111111 | AN554: =VLOOKUP($U554,[2]Standard_Dynamic!$Q$1:$T$542,4,FALSE) -> 0 | AO554: =SUM(AL554:AN554) -> 1 | AP554: =SUMPRODUCT($AL$1:$AN$1,AL554:AN554) -> 0.06315 | AQ554: =(1+AP554)^(1/12)-1 -> 0.0051160592 | AR554: 0 | AS554: =IF(AR554=0,0,SUMPRODUCT($AL$3:$AN$3,AL554:AN554)) -> 0 | AT554: =1-(1-AS554)^(1/12) -> 0 | AU554: =SUMPRODUCT($AL$2:$AN$2,AL554:AN554) -> 0.0025 | AV554: =1-(1-AU554)^(1/12) -> 0.00020857243 | AX554: DIS | AY554: Standard | AZ554: =AX554&"_"&AY554&"_"&BA554 -> DIS_Standard_533 | BA554: 533 | BB554: =VLOOKUP($BA554,'[2]Standard DIS'!$Q$1:$X$542,4,FALSE) -> 0 | BF554: =VLOOKUP($BA554,'[2]Standard DIS'!$Q$1:$X$542,2,FALSE) -> 0.88888889 | BH554: =VLOOKUP($BA554,'[2]Standard DIS'!$Q$1:$X$542,3,FALSE) -> 0.11111111 | BI554: =SUM(BB554:BH554) -> 1 | BJ554: =SUMPRODUCT($BB$1:$BH$1,BB554:BH554) -> 0.06315 | BK554: =(1+BJ554)^(1/12)-1 -> 0.0051160592 | BL554: 0 | BM554: =IF(BL554=0,0,SUMPRODUCT($BB$3:$BH$3,BB554:BH554)) -> 0 | BN554: =(1+BM554)^(1/12)-1 -> 0 | BO554: =SUMPRODUCT($BB$2:$BH$2,BB554:BH554) -> 0.0025 | BP554: =(1+BO554)^(1/12)-1 -> 0.000208095
A555: Lifecycle | B555: Dynamic | C555: =A555&"_"&B555&"_"&D555 -> Lifecycle_Dynamic_532 | D555: 532 | E555: =VLOOKUP($D555,'[2]LC Dynamic'!$Q$2:$U$542,2,FALSE) -> 0 | F555: =VLOOKUP($D555,'[2]LC Dynamic'!$Q$2:$U$542,3,FALSE) -> 0 | G555: =VLOOKUP($D555,'[2]LC Dynamic'!$Q$2:$U$542,4,FALSE) -> 0.308 | H555: =VLOOKUP($D555,'[2]LC Dynamic'!$Q$2:$U$542,5,FALSE) -> 0.692 | I555: =SUM(E555:H555) -> 1 | J555: =SUMPRODUCT($E$1:$H$1,E555:H555) -> 0.0697285 | K555: =(1+J555)^(1/12)-1 -> 0.0056328785 | L555: 0 | M555: =IF($L555=0,0,SUMPRODUCT($E$3:$H$3,E555:H555)) -> 0 | N555: =1-(1-M555)^(1/12) -> 0 | O555: =SUMPRODUCT($E$2:$H$2,E555:H555) -> 0.0056776 | P555: =1-(1-O555)^(1/12) -> 0.00047436902 | R555: Autopilot | S555: Dynamic | T555: =R555&"_"&S555&"_"&U555 -> Autopilot_Dynamic_532 | U555: 532 | V555: =VLOOKUP($U555,'[2]AP Dynamic'!$Q$1:$T$542,2,FALSE) -> 0.88888889 | W555: =VLOOKUP($U555,'[2]AP Dynamic'!$Q$1:$T$542,3,FALSE) -> 0.11111111 | X555: =VLOOKUP($U555,'[2]AP Dynamic'!$Q$1:$T$542,4,FALSE) -> 0 | Y555: =SUM(V555:X555) -> 1 | Z555: =SUMPRODUCT($V$1:$X$1,V555:X555) -> 0.06315 | AA555: =(1+Z555)^(1/12)-1 -> 0.0051160592 | AB555: 1 | AC555: =IF($AB555=0,0,SUMPRODUCT($V$3:$X$3,V555:X555)) -> 0.0082777778 | AD555: =1-(1-AC555)^(1/12) -> 0.00069244588 | AE555: =SUMPRODUCT($V$2:$X$2,V555:X555) -> 0.0025 | AF555: =1-(1-AE555)^(1/12) -> 0.00020857243 | AH555: Lifecycle | AI555: Dynamic | AJ555: =AH555&"_"&AI555&"_"&AK555 -> Lifecycle_Dynamic_532 | AK555: 532 | AL555: =VLOOKUP($U555,[2]Standard_Dynamic!$Q$1:$T$542,2,FALSE) -> 0.88888889 | AM555: =VLOOKUP($U555,[2]Standard_Dynamic!$Q$1:$T$542,3,FALSE) -> 0.11111111 | AN555: =VLOOKUP($U555,[2]Standard_Dynamic!$Q$1:$T$542,4,FALSE) -> 0 | AO555: =SUM(AL555:AN555) -> 1 | AP555: =SUMPRODUCT($AL$1:$AN$1,AL555:AN555) -> 0.06315 | AQ555: =(1+AP555)^(1/12)-1 -> 0.0051160592 | AR555: 0 | AS555: =IF(AR555=0,0,SUMPRODUCT($AL$3:$AN$3,AL555:AN555)) -> 0 | AT555: =1-(1-AS555)^(1/12) -> 0 | AU555: =SUMPRODUCT($AL$2:$AN$2,AL555:AN555) -> 0.0025 | AV555: =1-(1-AU555)^(1/12) -> 0.00020857243 | AX555: DIS | AY555: Standard | AZ555: =AX555&"_"&AY555&"_"&BA555 -> DIS_Standard_532 | BA555: 532 | BB555: =VLOOKUP($BA555,'[2]Standard DIS'!$Q$1:$X$542,4,FALSE) -> 0 | BF555: =VLOOKUP($BA555,'[2]Standard DIS'!$Q$1:$X$542,2,FALSE) -> 0.88888889 | BH555: =VLOOKUP($BA555,'[2]Standard DIS'!$Q$1:$X$542,3,FALSE) -> 0.11111111 | BI555: =SUM(BB555:BH555) -> 1 | BJ555: =SUMPRODUCT($BB$1:$BH$1,BB555:BH555) -> 0.06315 | BK555: =(1+BJ555)^(1/12)-1 -> 0.0051160592 | BL555: 0 | BM555: =IF(BL555=0,0,SUMPRODUCT($BB$3:$BH$3,BB555:BH555)) -> 0 | BN555: =(1+BM555)^(1/12)-1 -> 0 | BO555: =SUMPRODUCT($BB$2:$BH$2,BB555:BH555) -> 0.0025 | BP555: =(1+BO555)^(1/12)-1 -> 0.000208095
A556: Lifecycle | B556: Dynamic | C556: =A556&"_"&B556&"_"&D556 -> Lifecycle_Dynamic_531 | D556: 531 | E556: =VLOOKUP($D556,'[2]LC Dynamic'!$Q$2:$U$542,2,FALSE) -> 0 | F556: =VLOOKUP($D556,'[2]LC Dynamic'!$Q$2:$U$542,3,FALSE) -> 0 | G556: =VLOOKUP($D556,'[2]LC Dynamic'!$Q$2:$U$542,4,FALSE) -> 0.308 | H556: =VLOOKUP($D556,'[2]LC Dynamic'!$Q$2:$U$542,5,FALSE) -> 0.692 | I556: =SUM(E556:H556) -> 1 | J556: =SUMPRODUCT($E$1:$H$1,E556:H556) -> 0.0697285 | K556: =(1+J556)^(1/12)-1 -> 0.0056328785 | L556: 0 | M556: =IF($L556=0,0,SUMPRODUCT($E$3:$H$3,E556:H556)) -> 0 | N556: =1-(1-M556)^(1/12) -> 0 | O556: =SUMPRODUCT($E$2:$H$2,E556:H556) -> 0.0056776 | P556: =1-(1-O556)^(1/12) -> 0.00047436902 | R556: Autopilot | S556: Dynamic | T556: =R556&"_"&S556&"_"&U556 -> Autopilot_Dynamic_531 | U556: 531 | V556: =VLOOKUP($U556,'[2]AP Dynamic'!$Q$1:$T$542,2,FALSE) -> 0.88888889 | W556: =VLOOKUP($U556,'[2]AP Dynamic'!$Q$1:$T$542,3,FALSE) -> 0.11111111 | X556: =VLOOKUP($U556,'[2]AP Dynamic'!$Q$1:$T$542,4,FALSE) -> 0 | Y556: =SUM(V556:X556) -> 1 | Z556: =SUMPRODUCT($V$1:$X$1,V556:X556) -> 0.06315 | AA556: =(1+Z556)^(1/12)-1 -> 0.0051160592 | AB556: 1 | AC556: =IF($AB556=0,0,SUMPRODUCT($V$3:$X$3,V556:X556)) -> 0.0082777778 | AD556: =1-(1-AC556)^(1/12) -> 0.00069244588 | AE556: =SUMPRODUCT($V$2:$X$2,V556:X556) -> 0.0025 | AF556: =1-(1-AE556)^(1/12) -> 0.00020857243 | AH556: Lifecycle | AI556: Dynamic | AJ556: =AH556&"_"&AI556&"_"&AK556 -> Lifecycle_Dynamic_531 | AK556: 531 | AL556: =VLOOKUP($U556,[2]Standard_Dynamic!$Q$1:$T$542,2,FALSE) -> 0.88888889 | AM556: =VLOOKUP($U556,[2]Standard_Dynamic!$Q$1:$T$542,3,FALSE) -> 0.11111111 | AN556: =VLOOKUP($U556,[2]Standard_Dynamic!$Q$1:$T$542,4,FALSE) -> 0 | AO556: =SUM(AL556:AN556) -> 1 | AP556: =SUMPRODUCT($AL$1:$AN$1,AL556:AN556) -> 0.06315 | AQ556: =(1+AP556)^(1/12)-1 -> 0.0051160592 | AR556: 0 | AS556: =IF(AR556=0,0,SUMPRODUCT($AL$3:$AN$3,AL556:AN556)) -> 0 | AT556: =1-(1-AS556)^(1/12) -> 0 | AU556: =SUMPRODUCT($AL$2:$AN$2,AL556:AN556) -> 0.0025 | AV556: =1-(1-AU556)^(1/12) -> 0.00020857243 | AX556: DIS | AY556: Standard | AZ556: =AX556&"_"&AY556&"_"&BA556 -> DIS_Standard_531 | BA556: 531 | BB556: =VLOOKUP($BA556,'[2]Standard DIS'!$Q$1:$X$542,4,FALSE) -> 0 | BF556: =VLOOKUP($BA556,'[2]Standard DIS'!$Q$1:$X$542,2,FALSE) -> 0.88888889 | BH556: =VLOOKUP($BA556,'[2]Standard DIS'!$Q$1:$X$542,3,FALSE) -> 0.11111111 | BI556: =SUM(BB556:BH556) -> 1 | BJ556: =SUMPRODUCT($BB$1:$BH$1,BB556:BH556) -> 0.06315 | BK556: =(1+BJ556)^(1/12)-1 -> 0.0051160592 | BL556: 0 | BM556: =IF(BL556=0,0,SUMPRODUCT($BB$3:$BH$3,BB556:BH556)) -> 0 | BN556: =(1+BM556)^(1/12)-1 -> 0 | BO556: =SUMPRODUCT($BB$2:$BH$2,BB556:BH556) -> 0.0025 | BP556: =(1+BO556)^(1/12)-1 -> 0.000208095
A557: Lifecycle | B557: Dynamic | C557: =A557&"_"&B557&"_"&D557 -> Lifecycle_Dynamic_530 | D557: 530 | E557: =VLOOKUP($D557,'[2]LC Dynamic'!$Q$2:$U$542,2,FALSE) -> 0 | F557: =VLOOKUP($D557,'[2]LC Dynamic'!$Q$2:$U$542,3,FALSE) -> 0 | G557: =VLOOKUP($D557,'[2]LC Dynamic'!$Q$2:$U$542,4,FALSE) -> 0.308 | H557: =VLOOKUP($D557,'[2]LC Dynamic'!$Q$2:$U$542,5,FALSE) -> 0.692 | I557: =SUM(E557:H557) -> 1 | J557: =SUMPRODUCT($E$1:$H$1,E557:H557) -> 0.0697285 | K557: =(1+J557)^(1/12)-1 -> 0.0056328785 | L557: 0 | M557: =IF($L557=0,0,SUMPRODUCT($E$3:$H$3,E557:H557)) -> 0 | N557: =1-(1-M557)^(1/12) -> 0 | O557: =SUMPRODUCT($E$2:$H$2,E557:H557) -> 0.0056776 | P557: =1-(1-O557)^(1/12) -> 0.00047436902 | R557: Autopilot | S557: Dynamic | T557: =R557&"_"&S557&"_"&U557 -> Autopilot_Dynamic_530 | U557: 530 | V557: =VLOOKUP($U557,'[2]AP Dynamic'!$Q$1:$T$542,2,FALSE) -> 0.88888889 | W557: =VLOOKUP($U557,'[2]AP Dynamic'!$Q$1:$T$542,3,FALSE) -> 0.11111111 | X557: =VLOOKUP($U557,'[2]AP Dynamic'!$Q$1:$T$542,4,FALSE) -> 0 | Y557: =SUM(V557:X557) -> 1 | Z557: =SUMPRODUCT($V$1:$X$1,V557:X557) -> 0.06315 | AA557: =(1+Z557)^(1/12)-1 -> 0.0051160592 | AB557: 1 | AC557: =IF($AB557=0,0,SUMPRODUCT($V$3:$X$3,V557:X557)) -> 0.0082777778 | AD557: =1-(1-AC557)^(1/12) -> 0.00069244588 | AE557: =SUMPRODUCT($V$2:$X$2,V557:X557) -> 0.0025 | AF557: =1-(1-AE557)^(1/12) -> 0.00020857243 | AH557: Lifecycle | AI557: Dynamic | AJ557: =AH557&"_"&AI557&"_"&AK557 -> Lifecycle_Dynamic_530 | AK557: 530 | AL557: =VLOOKUP($U557,[2]Standard_Dynamic!$Q$1:$T$542,2,FALSE) -> 0.88888889 | AM557: =VLOOKUP($U557,[2]Standard_Dynamic!$Q$1:$T$542,3,FALSE) -> 0.11111111 | AN557: =VLOOKUP($U557,[2]Standard_Dynamic!$Q$1:$T$542,4,FALSE) -> 0 | AO557: =SUM(AL557:AN557) -> 1 | AP557: =SUMPRODUCT($AL$1:$AN$1,AL557:AN557) -> 0.06315 | AQ557: =(1+AP557)^(1/12)-1 -> 0.0051160592 | AR557: 0 | AS557: =IF(AR557=0,0,SUMPRODUCT($AL$3:$AN$3,AL557:AN557)) -> 0 | AT557: =1-(1-AS557)^(1/12) -> 0 | AU557: =SUMPRODUCT($AL$2:$AN$2,AL557:AN557) -> 0.0025 | AV557: =1-(1-AU557)^(1/12) -> 0.00020857243 | AX557: DIS | AY557: Standard | AZ557: =AX557&"_"&AY557&"_"&BA557 -> DIS_Standard_530 | BA557: 530 | BB557: =VLOOKUP($BA557,'[2]Standard DIS'!$Q$1:$X$542,4,FALSE) -> 0 | BF557: =VLOOKUP($BA557,'[2]Standard DIS'!$Q$1:$X$542,2,FALSE) -> 0.88888889 | BH557: =VLOOKUP($BA557,'[2]Standard DIS'!$Q$1:$X$542,3,FALSE) -> 0.11111111 | BI557: =SUM(BB557:BH557) -> 1 | BJ557: =SUMPRODUCT($BB$1:$BH$1,BB557:BH557) -> 0.06315 | BK557: =(1+BJ557)^(1/12)-1 -> 0.0051160592 | BL557: 0 | BM557: =IF(BL557=0,0,SUMPRODUCT($BB$3:$BH$3,BB557:BH557)) -> 0 | BN557: =(1+BM557)^(1/12)-1 -> 0 | BO557: =SUMPRODUCT($BB$2:$BH$2,BB557:BH557) -> 0.0025 | BP557: =(1+BO557)^(1/12)-1 -> 0.000208095
A558: Lifecycle | B558: Dynamic | C558: =A558&"_"&B558&"_"&D558 -> Lifecycle_Dynamic_529 | D558: 529 | E558: =VLOOKUP($D558,'[2]LC Dynamic'!$Q$2:$U$542,2,FALSE) -> 0 | F558: =VLOOKUP($D558,'[2]LC Dynamic'!$Q$2:$U$542,3,FALSE) -> 0 | G558: =VLOOKUP($D558,'[2]LC Dynamic'!$Q$2:$U$542,4,FALSE) -> 0.308 | H558: =VLOOKUP($D558,'[2]LC Dynamic'!$Q$2:$U$542,5,FALSE) -> 0.692 | I558: =SUM(E558:H558) -> 1 | J558: =SUMPRODUCT($E$1:$H$1,E558:H558) -> 0.0697285 | K558: =(1+J558)^(1/12)-1 -> 0.0056328785 | L558: 0 | M558: =IF($L558=0,0,SUMPRODUCT($E$3:$H$3,E558:H558)) -> 0 | N558: =1-(1-M558)^(1/12) -> 0 | O558: =SUMPRODUCT($E$2:$H$2,E558:H558) -> 0.0056776 | P558: =1-(1-O558)^(1/12) -> 0.00047436902 | R558: Autopilot | S558: Dynamic | T558: =R558&"_"&S558&"_"&U558 -> Autopilot_Dynamic_529 | U558: 529 | V558: =VLOOKUP($U558,'[2]AP Dynamic'!$Q$1:$T$542,2,FALSE) -> 0.88888889 | W558: =VLOOKUP($U558,'[2]AP Dynamic'!$Q$1:$T$542,3,FALSE) -> 0.11111111 | X558: =VLOOKUP($U558,'[2]AP Dynamic'!$Q$1:$T$542,4,FALSE) -> 0 | Y558: =SUM(V558:X558) -> 1 | Z558: =SUMPRODUCT($V$1:$X$1,V558:X558) -> 0.06315 | AA558: =(1+Z558)^(1/12)-1 -> 0.0051160592 | AB558: 1 | AC558: =IF($AB558=0,0,SUMPRODUCT($V$3:$X$3,V558:X558)) -> 0.0082777778 | AD558: =1-(1-AC558)^(1/12) -> 0.00069244588 | AE558: =SUMPRODUCT($V$2:$X$2,V558:X558) -> 0.0025 | AF558: =1-(1-AE558)^(1/12) -> 0.00020857243 | AH558: Lifecycle | AI558: Dynamic | AJ558: =AH558&"_"&AI558&"_"&AK558 -> Lifecycle_Dynamic_529 | AK558: 529 | AL558: =VLOOKUP($U558,[2]Standard_Dynamic!$Q$1:$T$542,2,FALSE) -> 0.88888889 | AM558: =VLOOKUP($U558,[2]Standard_Dynamic!$Q$1:$T$542,3,FALSE) -> 0.11111111 | AN558: =VLOOKUP($U558,[2]Standard_Dynamic!$Q$1:$T$542,4,FALSE) -> 0 | AO558: =SUM(AL558:AN558) -> 1 | AP558: =SUMPRODUCT($AL$1:$AN$1,AL558:AN558) -> 0.06315 | AQ558: =(1+AP558)^(1/12)-1 -> 0.0051160592 | AR558: 0 | AS558: =IF(AR558=0,0,SUMPRODUCT($AL$3:$AN$3,AL558:AN558)) -> 0 | AT558: =1-(1-AS558)^(1/12) -> 0 | AU558: =SUMPRODUCT($AL$2:$AN$2,AL558:AN558) -> 0.0025 | AV558: =1-(1-AU558)^(1/12) -> 0.00020857243 | AX558: DIS | AY558: Standard | AZ558: =AX558&"_"&AY558&"_"&BA558 -> DIS_Standard_529 | BA558: 529 | BB558: =VLOOKUP($BA558,'[2]Standard DIS'!$Q$1:$X$542,4,FALSE) -> 0 | BF558: =VLOOKUP($BA558,'[2]Standard DIS'!$Q$1:$X$542,2,FALSE) -> 0.88888889 | BH558: =VLOOKUP($BA558,'[2]Standard DIS'!$Q$1:$X$542,3,FALSE) -> 0.11111111 | BI558: =SUM(BB558:BH558) -> 1 | BJ558: =SUMPRODUCT($BB$1:$BH$1,BB558:BH558) -> 0.06315 | BK558: =(1+BJ558)^(1/12)-1 -> 0.0051160592 | BL558: 0 | BM558: =IF(BL558=0,0,SUMPRODUCT($BB$3:$BH$3,BB558:BH558)) -> 0 | BN558: =(1+BM558)^(1/12)-1 -> 0 | BO558: =SUMPRODUCT($BB$2:$BH$2,BB558:BH558) -> 0.0025 | BP558: =(1+BO558)^(1/12)-1 -> 0.000208095
... A1087: Lifecycle | B1087: Dynamic | C1087: =A1087&"_"&B1087&"_"&D1087 -> Lifecycle_Dynamic_0 | D1087: 0 | E1087: =VLOOKUP($D1087,'[2]LC Dynamic'!$Q$2:$U$542,2,FALSE) -> 0.331 | F1087: =VLOOKUP($D1087,'[2]LC Dynamic'!$Q$2:$U$542,3,FALSE) -> 0.271 | G1087: =VLOOKUP($D1087,'[2]LC Dynamic'!$Q$2:$U$542,4,FALSE) -> 0.398 | H1087: =VLOOKUP($D1087,'[2]LC Dynamic'!$Q$2:$U$542,5,FALSE) -> 0 | I1087: =SUM(E1087:H1087) -> 1 | J1087: =SUMPRODUCT($E$1:$H$1,E1087:H1087) -> 0.052504925 | K1087: =(1+J1087)^(1/12)-1 -> 0.0042735194 | L1087: 0 | M1087: =IF($L1087=0,0,SUMPRODUCT($E$3:$H$3,E1087:H1087)) -> 0 | N1087: =1-(1-M1087)^(1/12) -> 0 | O1087: =SUMPRODUCT($E$2:$H$2,E1087:H1087) -> 0.0052589 | P1087: =1-(1-O1087)^(1/12) -> 0.00043930154 | R1087: Autopilot | S1087: Dynamic | T1087: =R1087&"_"&S1087&"_"&U1087 -> Autopilot_Dynamic_0 | U1087: 0 | V1087: =VLOOKUP($U1087,'[2]AP Dynamic'!$Q$1:$T$542,2,FALSE) -> 0 | W1087: =VLOOKUP($U1087,'[2]AP Dynamic'!$Q$1:$T$542,3,FALSE) -> 1 | X1087: =VLOOKUP($U1087,'[2]AP Dynamic'!$Q$1:$T$542,4,FALSE) -> 0 | Y1087: =SUM(V1087:X1087) -> 1 | Z1087: =SUMPRODUCT($V$1:$X$1,V1087:X1087) -> 0.05135 | AA1087: =(1+Z1087)^(1/12)-1 -> 0.0041816398 | AB1087: 1 | AC1087: =IF($AB1087=0,0,SUMPRODUCT($V$3:$X$3,V1087:X1087)) -> 0.0065 | AD1087: =1-(1-AC1087)^(1/12) -> 0.00054328712 | AE1087: =SUMPRODUCT($V$2:$X$2,V1087:X1087) -> 0.0025 | AF1087: =1-(1-AE1087)^(1/12) -> 0.00020857243 | AH1087: Lifecycle | AI1087: Dynamic | AJ1087: =AH1087&"_"&AI1087&"_"&AK1087 -> Lifecycle_Dynamic_0 | AK1087: 0 | AL1087: =VLOOKUP($U1087,[2]Standard_Dynamic!$Q$1:$T$542,2,FALSE) -> 0 | AM1087: =VLOOKUP($U1087,[2]Standard_Dynamic!$Q$1:$T$542,3,FALSE) -> 1 | AN1087: =VLOOKUP($U1087,[2]Standard_Dynamic!$Q$1:$T$542,4,FALSE) -> 0 | AO1087: =SUM(AL1087:AN1087) -> 1 | AP1087: =SUMPRODUCT($AL$1:$AN$1,AL1087:AN1087) -> 0.05135 | AQ1087: =(1+AP1087)^(1/12)-1 -> 0.0041816398 | AR1087: 0 | AS1087: =IF(AR1087=0,0,SUMPRODUCT($AL$3:$AN$3,AL1087:AN1087)) -> 0 | AT1087: =1-(1-AS1087)^(1/12) -> 0 | AU1087: =SUMPRODUCT($AL$2:$AN$2,AL1087:AN1087) -> 0.0025 | AV1087: =1-(1-AU1087)^(1/12) -> 0.00020857243 | AX1087: DIS | AY1087: Standard | AZ1087: =AX1087&"_"&AY1087&"_"&BA1087 -> DIS_Standard_0 | BA1087: 0 | BB1087: =VLOOKUP($BA1087,'[2]Standard DIS'!$Q$1:$X$542,4,FALSE) -> 0 | BF1087: =VLOOKUP($BA1087,'[2]Standard DIS'!$Q$1:$X$542,2,FALSE) -> 0 | BH1087: =VLOOKUP($BA1087,'[2]Standard DIS'!$Q$1:$X$542,3,FALSE) -> 1 | BI1087: =SUM(BB1087:BH1087) -> 1 | BJ1087: =SUMPRODUCT($BB$1:$BH$1,BB1087:BH1087) -> 0.05135 | BK1087: =(1+BJ1087)^(1/12)-1 -> 0.0041816398 | BL1087: 0 | BM1087: =IF(BL1087=0,0,SUMPRODUCT($BB$3:$BH$3,BB1087:BH1087)) -> 0 | BN1087: =(1+BM1087)^(1/12)-1 -> 0 | BO1087: =SUMPRODUCT($BB$2:$BH$2,BB1087:BH1087) -> 0.0025 | BP1087: =(1+BO1087)^(1/12)-1 -> 0.000208095
A1089: Lifecycle | B1089: Opportunity | C1089: =A1089&"_"&B1089&"_"&D1089 -> Lifecycle_Opportunity_540 | D1089: 540 | E1089: =VLOOKUP($D1089,'[2]LC Opportunity'!$Q$2:$U$542,2,FALSE) -> 0 | F1089: =VLOOKUP($D1089,'[2]LC Opportunity'!$Q$2:$U$542,3,FALSE) -> 0 | G1089: =VLOOKUP($D1089,'[2]LC Opportunity'!$Q$2:$U$542,4,FALSE) -> 0 | H1089: =VLOOKUP($D1089,'[2]LC Opportunity'!$Q$2:$U$542,5,FALSE) -> 1 | I1089: =SUM(E1089:H1089) -> 1 | J1089: =SUMPRODUCT($E$1:$H$1,E1089:H1089) -> 0.072 | K1089: =(1+J1089)^(1/12)-1 -> 0.0058106553 | L1089: 0 | M1089: =IF($L1089=0,0,SUMPRODUCT($E$3:$H$3,E1089:H1089)) -> 0 | N1089: =1-(1-M1089)^(1/12) -> 0 | O1089: =SUMPRODUCT($E$2:$H$2,E1089:H1089) -> 0.005 | P1089: =1-(1-O1089)^(1/12) -> 0.00041762459 | R1089: Autopilot | S1089: Opportunity | T1089: =R1089&"_"&S1089&"_"&U1089 -> Autopilot_Opportunity_540 | U1089: 540 | V1089: =VLOOKUP($U1089,'[2]AP Opportunity'!$Q$1:$T$542,2,FALSE) -> 0.99999998 | W1089: =VLOOKUP($U1089,'[2]AP Opportunity'!$Q$1:$T$542,3,FALSE) -> 2.2222222e-08 | X1089: =VLOOKUP($U1089,'[2]AP Opportunity'!$Q$1:$T$542,4,FALSE) -> 0 | Y1089: =SUM(V1089:X1089) -> 1 | Z1089: =SUMPRODUCT($V$1:$X$1,V1089:X1089) -> 0.064625 | AA1089: =(1+Z1089)^(1/12)-1 -> 0.0052321924 | AB1089: 1 | AC1089: =IF($AB1089=0,0,SUMPRODUCT($V$3:$X$3,V1089:X1089)) -> 0.0085 | AD1089: =1-(1-AC1089)^(1/12) -> 0.00071110796 | AE1089: =SUMPRODUCT($V$2:$X$2,V1089:X1089) -> 0.0025 | AF1089: =1-(1-AE1089)^(1/12) -> 0.00020857243 | AH1089: Lifecycle | AI1089: Opportunity | AJ1089: =AH1089&"_"&AI1089&"_"&AK1089 -> Lifecycle_Opportunity_540 | AK1089: 540 | AL1089: =VLOOKUP($U1089,[2]Standard_Opportunity!$Q$1:$T$542,2,FALSE) -> 0.99999998 | AM1089: =VLOOKUP($U1089,[2]Standard_Opportunity!$Q$1:$T$542,3,FALSE) -> 2.2222222e-08 | AN1089: =VLOOKUP($U1089,[2]Standard_Opportunity!$Q$1:$T$542,4,FALSE) -> 0 | AO1089: =SUM(AL1089:AN1089) -> 1 | AP1089: =SUMPRODUCT($AL$1:$AN$1,AL1089:AN1089) -> 0.064625 | AQ1089: =(1+AP1089)^(1/12)-1 -> 0.0052321924 | AR1089: 0 | AS1089: =IF(AR1089=0,0,SUMPRODUCT($AL$3:$AN$3,AL1089:AN1089)) -> 0 | AT1089: =(1+AS1089)^(1/12)-1 -> 0 | AU1089: =SUMPRODUCT($AL$2:$AN$2,AL1089:AN1089) -> 0.0025 | AV1089: =(1+AU1089)^(1/12)-1 -> 0.000208095
A1090: Lifecycle | B1090: Opportunity | C1090: =A1090&"_"&B1090&"_"&D1090 -> Lifecycle_Opportunity_539 | D1090: 539 | E1090: =VLOOKUP($D1090,'[2]LC Opportunity'!$Q$2:$U$542,2,FALSE) -> 0 | F1090: =VLOOKUP($D1090,'[2]LC Opportunity'!$Q$2:$U$542,3,FALSE) -> 0 | G1090: =VLOOKUP($D1090,'[2]LC Opportunity'!$Q$2:$U$542,4,FALSE) -> 0 | H1090: =VLOOKUP($D1090,'[2]LC Opportunity'!$Q$2:$U$542,5,FALSE) -> 1 | I1090: =SUM(E1090:H1090) -> 1 | J1090: =SUMPRODUCT($E$1:$H$1,E1090:H1090) -> 0.072 | K1090: =(1+J1090)^(1/12)-1 -> 0.0058106553 | L1090: 0 | M1090: =IF($L1090=0,0,SUMPRODUCT($E$3:$H$3,E1090:H1090)) -> 0 | N1090: =1-(1-M1090)^(1/12) -> 0 | O1090: =SUMPRODUCT($E$2:$H$2,E1090:H1090) -> 0.005 | P1090: =1-(1-O1090)^(1/12) -> 0.00041762459 | R1090: Autopilot | S1090: Opportunity | T1090: =R1090&"_"&S1090&"_"&U1090 -> Autopilot_Opportunity_539 | U1090: 539 | V1090: =VLOOKUP($U1090,'[2]AP Opportunity'!$Q$1:$T$542,2,FALSE) -> 0.99999998 | W1090: =VLOOKUP($U1090,'[2]AP Opportunity'!$Q$1:$T$542,3,FALSE) -> 2.2222222e-08 | X1090: =VLOOKUP($U1090,'[2]AP Opportunity'!$Q$1:$T$542,4,FALSE) -> 0 | Y1090: =SUM(V1090:X1090) -> 1 | Z1090: =SUMPRODUCT($V$1:$X$1,V1090:X1090) -> 0.064625 | AA1090: =(1+Z1090)^(1/12)-1 -> 0.0052321924 | AB1090: 1 | AC1090: =IF($AB1090=0,0,SUMPRODUCT($V$3:$X$3,V1090:X1090)) -> 0.0085 | AD1090: =1-(1-AC1090)^(1/12) -> 0.00071110796 | AE1090: =SUMPRODUCT($V$2:$X$2,V1090:X1090) -> 0.0025 | AF1090: =1-(1-AE1090)^(1/12) -> 0.00020857243 | AH1090: Lifecycle | AI1090: Opportunity | AJ1090: =AH1090&"_"&AI1090&"_"&AK1090 -> Lifecycle_Opportunity_539 | AK1090: 539 | AL1090: =VLOOKUP($U1090,[2]Standard_Opportunity!$Q$1:$T$542,2,FALSE) -> 0.99999998 | AM1090: =VLOOKUP($U1090,[2]Standard_Opportunity!$Q$1:$T$542,3,FALSE) -> 2.2222222e-08 | AN1090: =VLOOKUP($U1090,[2]Standard_Opportunity!$Q$1:$T$542,4,FALSE) -> 0 | AO1090: =SUM(AL1090:AN1090) -> 1 | AP1090: =SUMPRODUCT($AL$1:$AN$1,AL1090:AN1090) -> 0.064625 | AQ1090: =(1+AP1090)^(1/12)-1 -> 0.0052321924 | AR1090: 0 | AS1090: =IF(AR1090=0,0,SUMPRODUCT($AL$3:$AN$3,AL1090:AN1090)) -> 0 | AT1090: =(1+AS1090)^(1/12)-1 -> 0 | AU1090: =SUMPRODUCT($AL$2:$AN$2,AL1090:AN1090) -> 0.0025 | AV1090: =(1+AU1090)^(1/12)-1 -> 0.000208095
A1091: Lifecycle | B1091: Opportunity | C1091: =A1091&"_"&B1091&"_"&D1091 -> Lifecycle_Opportunity_538 | D1091: 538 | E1091: =VLOOKUP($D1091,'[2]LC Opportunity'!$Q$2:$U$542,2,FALSE) -> 0 | F1091: =VLOOKUP($D1091,'[2]LC Opportunity'!$Q$2:$U$542,3,FALSE) -> 0 | G1091: =VLOOKUP($D1091,'[2]LC Opportunity'!$Q$2:$U$542,4,FALSE) -> 0 | H1091: =VLOOKUP($D1091,'[2]LC Opportunity'!$Q$2:$U$542,5,FALSE) -> 1 | I1091: =SUM(E1091:H1091) -> 1 | J1091: =SUMPRODUCT($E$1:$H$1,E1091:H1091) -> 0.072 | K1091: =(1+J1091)^(1/12)-1 -> 0.0058106553 | L1091: 0 | M1091: =IF($L1091=0,0,SUMPRODUCT($E$3:$H$3,E1091:H1091)) -> 0 | N1091: =1-(1-M1091)^(1/12) -> 0 | O1091: =SUMPRODUCT($E$2:$H$2,E1091:H1091) -> 0.005 | P1091: =1-(1-O1091)^(1/12) -> 0.00041762459 | R1091: Autopilot | S1091: Opportunity | T1091: =R1091&"_"&S1091&"_"&U1091 -> Autopilot_Opportunity_538 | U1091: 538 | V1091: =VLOOKUP($U1091,'[2]AP Opportunity'!$Q$1:$T$542,2,FALSE) -> 0.99999998 | W1091: =VLOOKUP($U1091,'[2]AP Opportunity'!$Q$1:$T$542,3,FALSE) -> 2.2222222e-08 | X1091: =VLOOKUP($U1091,'[2]AP Opportunity'!$Q$1:$T$542,4,FALSE) -> 0 | Y1091: =SUM(V1091:X1091) -> 1 | Z1091: =SUMPRODUCT($V$1:$X$1,V1091:X1091) -> 0.064625 | AA1091: =(1+Z1091)^(1/12)-1 -> 0.0052321924 | AB1091: 1 | AC1091: =IF($AB1091=0,0,SUMPRODUCT($V$3:$X$3,V1091:X1091)) -> 0.0085 | AD1091: =1-(1-AC1091)^(1/12) -> 0.00071110796 | AE1091: =SUMPRODUCT($V$2:$X$2,V1091:X1091) -> 0.0025 | AF1091: =1-(1-AE1091)^(1/12) -> 0.00020857243 | AH1091: Lifecycle | AI1091: Opportunity | AJ1091: =AH1091&"_"&AI1091&"_"&AK1091 -> Lifecycle_Opportunity_538 | AK1091: 538 | AL1091: =VLOOKUP($U1091,[2]Standard_Opportunity!$Q$1:$T$542,2,FALSE) -> 0.99999998 | AM1091: =VLOOKUP($U1091,[2]Standard_Opportunity!$Q$1:$T$542,3,FALSE) -> 2.2222222e-08 | AN1091: =VLOOKUP($U1091,[2]Standard_Opportunity!$Q$1:$T$542,4,FALSE) -> 0 | AO1091: =SUM(AL1091:AN1091) -> 1 | AP1091: =SUMPRODUCT($AL$1:$AN$1,AL1091:AN1091) -> 0.064625 | AQ1091: =(1+AP1091)^(1/12)-1 -> 0.0052321924 | AR1091: 0 | AS1091: =IF(AR1091=0,0,SUMPRODUCT($AL$3:$AN$3,AL1091:AN1091)) -> 0 | AT1091: =(1+AS1091)^(1/12)-1 -> 0 | AU1091: =SUMPRODUCT($AL$2:$AN$2,AL1091:AN1091) -> 0.0025 | AV1091: =(1+AU1091)^(1/12)-1 -> 0.000208095
A1092: Lifecycle | B1092: Opportunity | C1092: =A1092&"_"&B1092&"_"&D1092 -> Lifecycle_Opportunity_537 | D1092: 537 | E1092: =VLOOKUP($D1092,'[2]LC Opportunity'!$Q$2:$U$542,2,FALSE) -> 0 | F1092: =VLOOKUP($D1092,'[2]LC Opportunity'!$Q$2:$U$542,3,FALSE) -> 0 | G1092: =VLOOKUP($D1092,'[2]LC Opportunity'!$Q$2:$U$542,4,FALSE) -> 0 | H1092: =VLOOKUP($D1092,'[2]LC Opportunity'!$Q$2:$U$542,5,FALSE) -> 1 | I1092: =SUM(E1092:H1092) -> 1 | J1092: =SUMPRODUCT($E$1:$H$1,E1092:H1092) -> 0.072 | K1092: =(1+J1092)^(1/12)-1 -> 0.0058106553 | L1092: 0 | M1092: =IF($L1092=0,0,SUMPRODUCT($E$3:$H$3,E1092:H1092)) -> 0 | N1092: =1-(1-M1092)^(1/12) -> 0 | O1092: =SUMPRODUCT($E$2:$H$2,E1092:H1092) -> 0.005 | P1092: =1-(1-O1092)^(1/12) -> 0.00041762459 | R1092: Autopilot | S1092: Opportunity | T1092: =R1092&"_"&S1092&"_"&U1092 -> Autopilot_Opportunity_537 | U1092: 537 | V1092: =VLOOKUP($U1092,'[2]AP Opportunity'!$Q$1:$T$542,2,FALSE) -> 0.99999998 | W1092: =VLOOKUP($U1092,'[2]AP Opportunity'!$Q$1:$T$542,3,FALSE) -> 2.2222222e-08 | X1092: =VLOOKUP($U1092,'[2]AP Opportunity'!$Q$1:$T$542,4,FALSE) -> 0 | Y1092: =SUM(V1092:X1092) -> 1 | Z1092: =SUMPRODUCT($V$1:$X$1,V1092:X1092) -> 0.064625 | AA1092: =(1+Z1092)^(1/12)-1 -> 0.0052321924 | AB1092: 1 | AC1092: =IF($AB1092=0,0,SUMPRODUCT($V$3:$X$3,V1092:X1092)) -> 0.0085 | AD1092: =1-(1-AC1092)^(1/12) -> 0.00071110796 | AE1092: =SUMPRODUCT($V$2:$X$2,V1092:X1092) -> 0.0025 | AF1092: =1-(1-AE1092)^(1/12) -> 0.00020857243 | AH1092: Lifecycle | AI1092: Opportunity | AJ1092: =AH1092&"_"&AI1092&"_"&AK1092 -> Lifecycle_Opportunity_537 | AK1092: 537 | AL1092: =VLOOKUP($U1092,[2]Standard_Opportunity!$Q$1:$T$542,2,FALSE) -> 0.99999998 | AM1092: =VLOOKUP($U1092,[2]Standard_Opportunity!$Q$1:$T$542,3,FALSE) -> 2.2222222e-08 | AN1092: =VLOOKUP($U1092,[2]Standard_Opportunity!$Q$1:$T$542,4,FALSE) -> 0 | AO1092: =SUM(AL1092:AN1092) -> 1 | AP1092: =SUMPRODUCT($AL$1:$AN$1,AL1092:AN1092) -> 0.064625 | AQ1092: =(1+AP1092)^(1/12)-1 -> 0.0052321924 | AR1092: 0 | AS1092: =IF(AR1092=0,0,SUMPRODUCT($AL$3:$AN$3,AL1092:AN1092)) -> 0 | AT1092: =(1+AS1092)^(1/12)-1 -> 0 | AU1092: =SUMPRODUCT($AL$2:$AN$2,AL1092:AN1092) -> 0.0025 | AV1092: =(1+AU1092)^(1/12)-1 -> 0.000208095
A1093: Lifecycle | B1093: Opportunity | C1093: =A1093&"_"&B1093&"_"&D1093 -> Lifecycle_Opportunity_536 | D1093: 536 | E1093: =VLOOKUP($D1093,'[2]LC Opportunity'!$Q$2:$U$542,2,FALSE) -> 0 | F1093: =VLOOKUP($D1093,'[2]LC Opportunity'!$Q$2:$U$542,3,FALSE) -> 0 | G1093: =VLOOKUP($D1093,'[2]LC Opportunity'!$Q$2:$U$542,4,FALSE) -> 0 | H1093: =VLOOKUP($D1093,'[2]LC Opportunity'!$Q$2:$U$542,5,FALSE) -> 1 | I1093: =SUM(E1093:H1093) -> 1 | J1093: =SUMPRODUCT($E$1:$H$1,E1093:H1093) -> 0.072 | K1093: =(1+J1093)^(1/12)-1 -> 0.0058106553 | L1093: 0 | M1093: =IF($L1093=0,0,SUMPRODUCT($E$3:$H$3,E1093:H1093)) -> 0 | N1093: =1-(1-M1093)^(1/12) -> 0 | O1093: =SUMPRODUCT($E$2:$H$2,E1093:H1093) -> 0.005 | P1093: =1-(1-O1093)^(1/12) -> 0.00041762459 | R1093: Autopilot | S1093: Opportunity | T1093: =R1093&"_"&S1093&"_"&U1093 -> Autopilot_Opportunity_536 | U1093: 536 | V1093: =VLOOKUP($U1093,'[2]AP Opportunity'!$Q$1:$T$542,2,FALSE) -> 0.99999998 | W1093: =VLOOKUP($U1093,'[2]AP Opportunity'!$Q$1:$T$542,3,FALSE) -> 2.2222222e-08 | X1093: =VLOOKUP($U1093,'[2]AP Opportunity'!$Q$1:$T$542,4,FALSE) -> 0 | Y1093: =SUM(V1093:X1093) -> 1 | Z1093: =SUMPRODUCT($V$1:$X$1,V1093:X1093) -> 0.064625 | AA1093: =(1+Z1093)^(1/12)-1 -> 0.0052321924 | AB1093: 1 | AC1093: =IF($AB1093=0,0,SUMPRODUCT($V$3:$X$3,V1093:X1093)) -> 0.0085 | AD1093: =1-(1-AC1093)^(1/12) -> 0.00071110796 | AE1093: =SUMPRODUCT($V$2:$X$2,V1093:X1093) -> 0.0025 | AF1093: =1-(1-AE1093)^(1/12) -> 0.00020857243 | AH1093: Lifecycle | AI1093: Opportunity | AJ1093: =AH1093&"_"&AI1093&"_"&AK1093 -> Lifecycle_Opportunity_536 | AK1093: 536 | AL1093: =VLOOKUP($U1093,[2]Standard_Opportunity!$Q$1:$T$542,2,FALSE) -> 0.99999998 | AM1093: =VLOOKUP($U1093,[2]Standard_Opportunity!$Q$1:$T$542,3,FALSE) -> 2.2222222e-08 | AN1093: =VLOOKUP($U1093,[2]Standard_Opportunity!$Q$1:$T$542,4,FALSE) -> 0 | AO1093: =SUM(AL1093:AN1093) -> 1 | AP1093: =SUMPRODUCT($AL$1:$AN$1,AL1093:AN1093) -> 0.064625 | AQ1093: =(1+AP1093)^(1/12)-1 -> 0.0052321924 | AR1093: 0 | AS1093: =IF(AR1093=0,0,SUMPRODUCT($AL$3:$AN$3,AL1093:AN1093)) -> 0 | AT1093: =(1+AS1093)^(1/12)-1 -> 0 | AU1093: =SUMPRODUCT($AL$2:$AN$2,AL1093:AN1093) -> 0.0025 | AV1093: =(1+AU1093)^(1/12)-1 -> 0.000208095
A1094: Lifecycle | B1094: Opportunity | C1094: =A1094&"_"&B1094&"_"&D1094 -> Lifecycle_Opportunity_535 | D1094: 535 | E1094: =VLOOKUP($D1094,'[2]LC Opportunity'!$Q$2:$U$542,2,FALSE) -> 0 | F1094: =VLOOKUP($D1094,'[2]LC Opportunity'!$Q$2:$U$542,3,FALSE) -> 0 | G1094: =VLOOKUP($D1094,'[2]LC Opportunity'!$Q$2:$U$542,4,FALSE) -> 0 | H1094: =VLOOKUP($D1094,'[2]LC Opportunity'!$Q$2:$U$542,5,FALSE) -> 1 | I1094: =SUM(E1094:H1094) -> 1 | J1094: =SUMPRODUCT($E$1:$H$1,E1094:H1094) -> 0.072 | K1094: =(1+J1094)^(1/12)-1 -> 0.0058106553 | L1094: 0 | M1094: =IF($L1094=0,0,SUMPRODUCT($E$3:$H$3,E1094:H1094)) -> 0 | N1094: =1-(1-M1094)^(1/12) -> 0 | O1094: =SUMPRODUCT($E$2:$H$2,E1094:H1094) -> 0.005 | P1094: =1-(1-O1094)^(1/12) -> 0.00041762459 | R1094: Autopilot | S1094: Opportunity | T1094: =R1094&"_"&S1094&"_"&U1094 -> Autopilot_Opportunity_535 | U1094: 535 | V1094: =VLOOKUP($U1094,'[2]AP Opportunity'!$Q$1:$T$542,2,FALSE) -> 0.99999998 | W1094: =VLOOKUP($U1094,'[2]AP Opportunity'!$Q$1:$T$542,3,FALSE) -> 2.2222222e-08 | X1094: =VLOOKUP($U1094,'[2]AP Opportunity'!$Q$1:$T$542,4,FALSE) -> 0 | Y1094: =SUM(V1094:X1094) -> 1 | Z1094: =SUMPRODUCT($V$1:$X$1,V1094:X1094) -> 0.064625 | AA1094: =(1+Z1094)^(1/12)-1 -> 0.0052321924 | AB1094: 1 | AC1094: =IF($AB1094=0,0,SUMPRODUCT($V$3:$X$3,V1094:X1094)) -> 0.0085 | AD1094: =1-(1-AC1094)^(1/12) -> 0.00071110796 | AE1094: =SUMPRODUCT($V$2:$X$2,V1094:X1094) -> 0.0025 | AF1094: =1-(1-AE1094)^(1/12) -> 0.00020857243 | AH1094: Lifecycle | AI1094: Opportunity | AJ1094: =AH1094&"_"&AI1094&"_"&AK1094 -> Lifecycle_Opportunity_535 | AK1094: 535 | AL1094: =VLOOKUP($U1094,[2]Standard_Opportunity!$Q$1:$T$542,2,FALSE) -> 0.99999998 | AM1094: =VLOOKUP($U1094,[2]Standard_Opportunity!$Q$1:$T$542,3,FALSE) -> 2.2222222e-08 | AN1094: =VLOOKUP($U1094,[2]Standard_Opportunity!$Q$1:$T$542,4,FALSE) -> 0 | AO1094: =SUM(AL1094:AN1094) -> 1 | AP1094: =SUMPRODUCT($AL$1:$AN$1,AL1094:AN1094) -> 0.064625 | AQ1094: =(1+AP1094)^(1/12)-1 -> 0.0052321924 | AR1094: 0 | AS1094: =IF(AR1094=0,0,SUMPRODUCT($AL$3:$AN$3,AL1094:AN1094)) -> 0 | AT1094: =(1+AS1094)^(1/12)-1 -> 0 | AU1094: =SUMPRODUCT($AL$2:$AN$2,AL1094:AN1094) -> 0.0025 | AV1094: =(1+AU1094)^(1/12)-1 -> 0.000208095
A1095: Lifecycle | B1095: Opportunity | C1095: =A1095&"_"&B1095&"_"&D1095 -> Lifecycle_Opportunity_534 | D1095: 534 | E1095: =VLOOKUP($D1095,'[2]LC Opportunity'!$Q$2:$U$542,2,FALSE) -> 0 | F1095: =VLOOKUP($D1095,'[2]LC Opportunity'!$Q$2:$U$542,3,FALSE) -> 0 | G1095: =VLOOKUP($D1095,'[2]LC Opportunity'!$Q$2:$U$542,4,FALSE) -> 0 | H1095: =VLOOKUP($D1095,'[2]LC Opportunity'!$Q$2:$U$542,5,FALSE) -> 1 | I1095: =SUM(E1095:H1095) -> 1 | J1095: =SUMPRODUCT($E$1:$H$1,E1095:H1095) -> 0.072 | K1095: =(1+J1095)^(1/12)-1 -> 0.0058106553 | L1095: 0 | M1095: =IF($L1095=0,0,SUMPRODUCT($E$3:$H$3,E1095:H1095)) -> 0 | N1095: =1-(1-M1095)^(1/12) -> 0 | O1095: =SUMPRODUCT($E$2:$H$2,E1095:H1095) -> 0.005 | P1095: =1-(1-O1095)^(1/12) -> 0.00041762459 | R1095: Autopilot | S1095: Opportunity | T1095: =R1095&"_"&S1095&"_"&U1095 -> Autopilot_Opportunity_534 | U1095: 534 | V1095: =VLOOKUP($U1095,'[2]AP Opportunity'!$Q$1:$T$542,2,FALSE) -> 0.99999998 | W1095: =VLOOKUP($U1095,'[2]AP Opportunity'!$Q$1:$T$542,3,FALSE) -> 2.2222222e-08 | X1095: =VLOOKUP($U1095,'[2]AP Opportunity'!$Q$1:$T$542,4,FALSE) -> 0 | Y1095: =SUM(V1095:X1095) -> 1 | Z1095: =SUMPRODUCT($V$1:$X$1,V1095:X1095) -> 0.064625 | AA1095: =(1+Z1095)^(1/12)-1 -> 0.0052321924 | AB1095: 1 | AC1095: =IF($AB1095=0,0,SUMPRODUCT($V$3:$X$3,V1095:X1095)) -> 0.0085 | AD1095: =1-(1-AC1095)^(1/12) -> 0.00071110796 | AE1095: =SUMPRODUCT($V$2:$X$2,V1095:X1095) -> 0.0025 | AF1095: =1-(1-AE1095)^(1/12) -> 0.00020857243 | AH1095: Lifecycle | AI1095: Opportunity | AJ1095: =AH1095&"_"&AI1095&"_"&AK1095 -> Lifecycle_Opportunity_534 | AK1095: 534 | AL1095: =VLOOKUP($U1095,[2]Standard_Opportunity!$Q$1:$T$542,2,FALSE) -> 0.99999998 | AM1095: =VLOOKUP($U1095,[2]Standard_Opportunity!$Q$1:$T$542,3,FALSE) -> 2.2222222e-08 | AN1095: =VLOOKUP($U1095,[2]Standard_Opportunity!$Q$1:$T$542,4,FALSE) -> 0 | AO1095: =SUM(AL1095:AN1095) -> 1 | AP1095: =SUMPRODUCT($AL$1:$AN$1,AL1095:AN1095) -> 0.064625 | AQ1095: =(1+AP1095)^(1/12)-1 -> 0.0052321924 | AR1095: 0 | AS1095: =IF(AR1095=0,0,SUMPRODUCT($AL$3:$AN$3,AL1095:AN1095)) -> 0 | AT1095: =(1+AS1095)^(1/12)-1 -> 0 | AU1095: =SUMPRODUCT($AL$2:$AN$2,AL1095:AN1095) -> 0.0025 | AV1095: =(1+AU1095)^(1/12)-1 -> 0.000208095
A1096: Lifecycle | B1096: Opportunity | C1096: =A1096&"_"&B1096&"_"&D1096 -> Lifecycle_Opportunity_533 | D1096: 533 | E1096: =VLOOKUP($D1096,'[2]LC Opportunity'!$Q$2:$U$542,2,FALSE) -> 0 | F1096: =VLOOKUP($D1096,'[2]LC Opportunity'!$Q$2:$U$542,3,FALSE) -> 0 | G1096: =VLOOKUP($D1096,'[2]LC Opportunity'!$Q$2:$U$542,4,FALSE) -> 0 | H1096: =VLOOKUP($D1096,'[2]LC Opportunity'!$Q$2:$U$542,5,FALSE) -> 1 | I1096: =SUM(E1096:H1096) -> 1 | J1096: =SUMPRODUCT($E$1:$H$1,E1096:H1096) -> 0.072 | K1096: =(1+J1096)^(1/12)-1 -> 0.0058106553 | L1096: 0 | M1096: =IF($L1096=0,0,SUMPRODUCT($E$3:$H$3,E1096:H1096)) -> 0 | N1096: =1-(1-M1096)^(1/12) -> 0 | O1096: =SUMPRODUCT($E$2:$H$2,E1096:H1096) -> 0.005 | P1096: =1-(1-O1096)^(1/12) -> 0.00041762459 | R1096: Autopilot | S1096: Opportunity | T1096: =R1096&"_"&S1096&"_"&U1096 -> Autopilot_Opportunity_533 | U1096: 533 | V1096: =VLOOKUP($U1096,'[2]AP Opportunity'!$Q$1:$T$542,2,FALSE) -> 0.99999998 | W1096: =VLOOKUP($U1096,'[2]AP Opportunity'!$Q$1:$T$542,3,FALSE) -> 2.2222222e-08 | X1096: =VLOOKUP($U1096,'[2]AP Opportunity'!$Q$1:$T$542,4,FALSE) -> 0 | Y1096: =SUM(V1096:X1096) -> 1 | Z1096: =SUMPRODUCT($V$1:$X$1,V1096:X1096) -> 0.064625 | AA1096: =(1+Z1096)^(1/12)-1 -> 0.0052321924 | AB1096: 1 | AC1096: =IF($AB1096=0,0,SUMPRODUCT($V$3:$X$3,V1096:X1096)) -> 0.0085 | AD1096: =1-(1-AC1096)^(1/12) -> 0.00071110796 | AE1096: =SUMPRODUCT($V$2:$X$2,V1096:X1096) -> 0.0025 | AF1096: =1-(1-AE1096)^(1/12) -> 0.00020857243 | AH1096: Lifecycle | AI1096: Opportunity | AJ1096: =AH1096&"_"&AI1096&"_"&AK1096 -> Lifecycle_Opportunity_533 | AK1096: 533 | AL1096: =VLOOKUP($U1096,[2]Standard_Opportunity!$Q$1:$T$542,2,FALSE) -> 0.99999998 | AM1096: =VLOOKUP($U1096,[2]Standard_Opportunity!$Q$1:$T$542,3,FALSE) -> 2.2222222e-08 | AN1096: =VLOOKUP($U1096,[2]Standard_Opportunity!$Q$1:$T$542,4,FALSE) -> 0 | AO1096: =SUM(AL1096:AN1096) -> 1 | AP1096: =SUMPRODUCT($AL$1:$AN$1,AL1096:AN1096) -> 0.064625 | AQ1096: =(1+AP1096)^(1/12)-1 -> 0.0052321924 | AR1096: 0 | AS1096: =IF(AR1096=0,0,SUMPRODUCT($AL$3:$AN$3,AL1096:AN1096)) -> 0 | AT1096: =(1+AS1096)^(1/12)-1 -> 0 | AU1096: =SUMPRODUCT($AL$2:$AN$2,AL1096:AN1096) -> 0.0025 | AV1096: =(1+AU1096)^(1/12)-1 -> 0.000208095
A1097: Lifecycle | B1097: Opportunity | C1097: =A1097&"_"&B1097&"_"&D1097 -> Lifecycle_Opportunity_532 | D1097: 532 | E1097: =VLOOKUP($D1097,'[2]LC Opportunity'!$Q$2:$U$542,2,FALSE) -> 0 | F1097: =VLOOKUP($D1097,'[2]LC Opportunity'!$Q$2:$U$542,3,FALSE) -> 0 | G1097: =VLOOKUP($D1097,'[2]LC Opportunity'!$Q$2:$U$542,4,FALSE) -> 0 | H1097: =VLOOKUP($D1097,'[2]LC Opportunity'!$Q$2:$U$542,5,FALSE) -> 1 | I1097: =SUM(E1097:H1097) -> 1 | J1097: =SUMPRODUCT($E$1:$H$1,E1097:H1097) -> 0.072 | K1097: =(1+J1097)^(1/12)-1 -> 0.0058106553 | L1097: 0 | M1097: =IF($L1097=0,0,SUMPRODUCT($E$3:$H$3,E1097:H1097)) -> 0 | N1097: =1-(1-M1097)^(1/12) -> 0 | O1097: =SUMPRODUCT($E$2:$H$2,E1097:H1097) -> 0.005 | P1097: =1-(1-O1097)^(1/12) -> 0.00041762459 | R1097: Autopilot | S1097: Opportunity | T1097: =R1097&"_"&S1097&"_"&U1097 -> Autopilot_Opportunity_532 | U1097: 532 | V1097: =VLOOKUP($U1097,'[2]AP Opportunity'!$Q$1:$T$542,2,FALSE) -> 0.99999998 | W1097: =VLOOKUP($U1097,'[2]AP Opportunity'!$Q$1:$T$542,3,FALSE) -> 2.2222222e-08 | X1097: =VLOOKUP($U1097,'[2]AP Opportunity'!$Q$1:$T$542,4,FALSE) -> 0 | Y1097: =SUM(V1097:X1097) -> 1 | Z1097: =SUMPRODUCT($V$1:$X$1,V1097:X1097) -> 0.064625 | AA1097: =(1+Z1097)^(1/12)-1 -> 0.0052321924 | AB1097: 1 | AC1097: =IF($AB1097=0,0,SUMPRODUCT($V$3:$X$3,V1097:X1097)) -> 0.0085 | AD1097: =1-(1-AC1097)^(1/12) -> 0.00071110796 | AE1097: =SUMPRODUCT($V$2:$X$2,V1097:X1097) -> 0.0025 | AF1097: =1-(1-AE1097)^(1/12) -> 0.00020857243 | AH1097: Lifecycle | AI1097: Opportunity | AJ1097: =AH1097&"_"&AI1097&"_"&AK1097 -> Lifecycle_Opportunity_532 | AK1097: 532 | AL1097: =VLOOKUP($U1097,[2]Standard_Opportunity!$Q$1:$T$542,2,FALSE) -> 0.99999998 | AM1097: =VLOOKUP($U1097,[2]Standard_Opportunity!$Q$1:$T$542,3,FALSE) -> 2.2222222e-08 | AN1097: =VLOOKUP($U1097,[2]Standard_Opportunity!$Q$1:$T$542,4,FALSE) -> 0 | AO1097: =SUM(AL1097:AN1097) -> 1 | AP1097: =SUMPRODUCT($AL$1:$AN$1,AL1097:AN1097) -> 0.064625 | AQ1097: =(1+AP1097)^(1/12)-1 -> 0.0052321924 | AR1097: 0 | AS1097: =IF(AR1097=0,0,SUMPRODUCT($AL$3:$AN$3,AL1097:AN1097)) -> 0 | AT1097: =(1+AS1097)^(1/12)-1 -> 0 | AU1097: =SUMPRODUCT($AL$2:$AN$2,AL1097:AN1097) -> 0.0025 | AV1097: =(1+AU1097)^(1/12)-1 -> 0.000208095
A1098: Lifecycle | B1098: Opportunity | C1098: =A1098&"_"&B1098&"_"&D1098 -> Lifecycle_Opportunity_531 | D1098: 531 | E1098: =VLOOKUP($D1098,'[2]LC Opportunity'!$Q$2:$U$542,2,FALSE) -> 0 | F1098: =VLOOKUP($D1098,'[2]LC Opportunity'!$Q$2:$U$542,3,FALSE) -> 0 | G1098: =VLOOKUP($D1098,'[2]LC Opportunity'!$Q$2:$U$542,4,FALSE) -> 0 | H1098: =VLOOKUP($D1098,'[2]LC Opportunity'!$Q$2:$U$542,5,FALSE) -> 1 | I1098: =SUM(E1098:H1098) -> 1 | J1098: =SUMPRODUCT($E$1:$H$1,E1098:H1098) -> 0.072 | K1098: =(1+J1098)^(1/12)-1 -> 0.0058106553 | L1098: 0 | M1098: =IF($L1098=0,0,SUMPRODUCT($E$3:$H$3,E1098:H1098)) -> 0 | N1098: =1-(1-M1098)^(1/12) -> 0 | O1098: =SUMPRODUCT($E$2:$H$2,E1098:H1098) -> 0.005 | P1098: =1-(1-O1098)^(1/12) -> 0.00041762459 | R1098: Autopilot | S1098: Opportunity | T1098: =R1098&"_"&S1098&"_"&U1098 -> Autopilot_Opportunity_531 | U1098: 531 | V1098: =VLOOKUP($U1098,'[2]AP Opportunity'!$Q$1:$T$542,2,FALSE) -> 0.99999998 | W1098: =VLOOKUP($U1098,'[2]AP Opportunity'!$Q$1:$T$542,3,FALSE) -> 2.2222222e-08 | X1098: =VLOOKUP($U1098,'[2]AP Opportunity'!$Q$1:$T$542,4,FALSE) -> 0 | Y1098: =SUM(V1098:X1098) -> 1 | Z1098: =SUMPRODUCT($V$1:$X$1,V1098:X1098) -> 0.064625 | AA1098: =(1+Z1098)^(1/12)-1 -> 0.0052321924 | AB1098: 1 | AC1098: =IF($AB1098=0,0,SUMPRODUCT($V$3:$X$3,V1098:X1098)) -> 0.0085 | AD1098: =1-(1-AC1098)^(1/12) -> 0.00071110796 | AE1098: =SUMPRODUCT($V$2:$X$2,V1098:X1098) -> 0.0025 | AF1098: =1-(1-AE1098)^(1/12) -> 0.00020857243 | AH1098: Lifecycle | AI1098: Opportunity | AJ1098: =AH1098&"_"&AI1098&"_"&AK1098 -> Lifecycle_Opportunity_531 | AK1098: 531 | AL1098: =VLOOKUP($U1098,[2]Standard_Opportunity!$Q$1:$T$542,2,FALSE) -> 0.99999998 | AM1098: =VLOOKUP($U1098,[2]Standard_Opportunity!$Q$1:$T$542,3,FALSE) -> 2.2222222e-08 | AN1098: =VLOOKUP($U1098,[2]Standard_Opportunity!$Q$1:$T$542,4,FALSE) -> 0 | AO1098: =SUM(AL1098:AN1098) -> 1 | AP1098: =SUMPRODUCT($AL$1:$AN$1,AL1098:AN1098) -> 0.064625 | AQ1098: =(1+AP1098)^(1/12)-1 -> 0.0052321924 | AR1098: 0 | AS1098: =IF(AR1098=0,0,SUMPRODUCT($AL$3:$AN$3,AL1098:AN1098)) -> 0 | AT1098: =(1+AS1098)^(1/12)-1 -> 0 | AU1098: =SUMPRODUCT($AL$2:$AN$2,AL1098:AN1098) -> 0.0025 | AV1098: =(1+AU1098)^(1/12)-1 -> 0.000208095
A1099: Lifecycle | B1099: Opportunity | C1099: =A1099&"_"&B1099&"_"&D1099 -> Lifecycle_Opportunity_530 | D1099: 530 | E1099: =VLOOKUP($D1099,'[2]LC Opportunity'!$Q$2:$U$542,2,FALSE) -> 0 | F1099: =VLOOKUP($D1099,'[2]LC Opportunity'!$Q$2:$U$542,3,FALSE) -> 0 | G1099: =VLOOKUP($D1099,'[2]LC Opportunity'!$Q$2:$U$542,4,FALSE) -> 0 | H1099: =VLOOKUP($D1099,'[2]LC Opportunity'!$Q$2:$U$542,5,FALSE) -> 1 | I1099: =SUM(E1099:H1099) -> 1 | J1099: =SUMPRODUCT($E$1:$H$1,E1099:H1099) -> 0.072 | K1099: =(1+J1099)^(1/12)-1 -> 0.0058106553 | L1099: 0 | M1099: =IF($L1099=0,0,SUMPRODUCT($E$3:$H$3,E1099:H1099)) -> 0 | N1099: =1-(1-M1099)^(1/12) -> 0 | O1099: =SUMPRODUCT($E$2:$H$2,E1099:H1099) -> 0.005 | P1099: =1-(1-O1099)^(1/12) -> 0.00041762459 | R1099: Autopilot | S1099: Opportunity | T1099: =R1099&"_"&S1099&"_"&U1099 -> Autopilot_Opportunity_530 | U1099: 530 | V1099: =VLOOKUP($U1099,'[2]AP Opportunity'!$Q$1:$T$542,2,FALSE) -> 0.99999998 | W1099: =VLOOKUP($U1099,'[2]AP Opportunity'!$Q$1:$T$542,3,FALSE) -> 2.2222222e-08 | X1099: =VLOOKUP($U1099,'[2]AP Opportunity'!$Q$1:$T$542,4,FALSE) -> 0 | Y1099: =SUM(V1099:X1099) -> 1 | Z1099: =SUMPRODUCT($V$1:$X$1,V1099:X1099) -> 0.064625 | AA1099: =(1+Z1099)^(1/12)-1 -> 0.0052321924 | AB1099: 1 | AC1099: =IF($AB1099=0,0,SUMPRODUCT($V$3:$X$3,V1099:X1099)) -> 0.0085 | AD1099: =1-(1-AC1099)^(1/12) -> 0.00071110796 | AE1099: =SUMPRODUCT($V$2:$X$2,V1099:X1099) -> 0.0025 | AF1099: =1-(1-AE1099)^(1/12) -> 0.00020857243 | AH1099: Lifecycle | AI1099: Opportunity | AJ1099: =AH1099&"_"&AI1099&"_"&AK1099 -> Lifecycle_Opportunity_530 | AK1099: 530 | AL1099: =VLOOKUP($U1099,[2]Standard_Opportunity!$Q$1:$T$542,2,FALSE) -> 0.99999998 | AM1099: =VLOOKUP($U1099,[2]Standard_Opportunity!$Q$1:$T$542,3,FALSE) -> 2.2222222e-08 | AN1099: =VLOOKUP($U1099,[2]Standard_Opportunity!$Q$1:$T$542,4,FALSE) -> 0 | AO1099: =SUM(AL1099:AN1099) -> 1 | AP1099: =SUMPRODUCT($AL$1:$AN$1,AL1099:AN1099) -> 0.064625 | AQ1099: =(1+AP1099)^(1/12)-1 -> 0.0052321924 | AR1099: 0 | AS1099: =IF(AR1099=0,0,SUMPRODUCT($AL$3:$AN$3,AL1099:AN1099)) -> 0 | AT1099: =(1+AS1099)^(1/12)-1 -> 0 | AU1099: =SUMPRODUCT($AL$2:$AN$2,AL1099:AN1099) -> 0.0025 | AV1099: =(1+AU1099)^(1/12)-1 -> 0.000208095
A1100: Lifecycle | B1100: Opportunity | C1100: =A1100&"_"&B1100&"_"&D1100 -> Lifecycle_Opportunity_529 | D1100: 529 | E1100: =VLOOKUP($D1100,'[2]LC Opportunity'!$Q$2:$U$542,2,FALSE) -> 0 | F1100: =VLOOKUP($D1100,'[2]LC Opportunity'!$Q$2:$U$542,3,FALSE) -> 0 | G1100: =VLOOKUP($D1100,'[2]LC Opportunity'!$Q$2:$U$542,4,FALSE) -> 0 | H1100: =VLOOKUP($D1100,'[2]LC Opportunity'!$Q$2:$U$542,5,FALSE) -> 1 | I1100: =SUM(E1100:H1100) -> 1 | J1100: =SUMPRODUCT($E$1:$H$1,E1100:H1100) -> 0.072 | K1100: =(1+J1100)^(1/12)-1 -> 0.0058106553 | L1100: 0 | M1100: =IF($L1100=0,0,SUMPRODUCT($E$3:$H$3,E1100:H1100)) -> 0 | N1100: =1-(1-M1100)^(1/12) -> 0 | O1100: =SUMPRODUCT($E$2:$H$2,E1100:H1100) -> 0.005 | P1100: =1-(1-O1100)^(1/12) -> 0.00041762459 | R1100: Autopilot | S1100: Opportunity | T1100: =R1100&"_"&S1100&"_"&U1100 -> Autopilot_Opportunity_529 | U1100: 529 | V1100: =VLOOKUP($U1100,'[2]AP Opportunity'!$Q$1:$T$542,2,FALSE) -> 0.99999998 | W1100: =VLOOKUP($U1100,'[2]AP Opportunity'!$Q$1:$T$542,3,FALSE) -> 2.2222222e-08 | X1100: =VLOOKUP($U1100,'[2]AP Opportunity'!$Q$1:$T$542,4,FALSE) -> 0 | Y1100: =SUM(V1100:X1100) -> 1 | Z1100: =SUMPRODUCT($V$1:$X$1,V1100:X1100) -> 0.064625 | AA1100: =(1+Z1100)^(1/12)-1 -> 0.0052321924 | AB1100: 1 | AC1100: =IF($AB1100=0,0,SUMPRODUCT($V$3:$X$3,V1100:X1100)) -> 0.0085 | AD1100: =1-(1-AC1100)^(1/12) -> 0.00071110796 | AE1100: =SUMPRODUCT($V$2:$X$2,V1100:X1100) -> 0.0025 | AF1100: =1-(1-AE1100)^(1/12) -> 0.00020857243 | AH1100: Lifecycle | AI1100: Opportunity | AJ1100: =AH1100&"_"&AI1100&"_"&AK1100 -> Lifecycle_Opportunity_529 | AK1100: 529 | AL1100: =VLOOKUP($U1100,[2]Standard_Opportunity!$Q$1:$T$542,2,FALSE) -> 0.99999998 | AM1100: =VLOOKUP($U1100,[2]Standard_Opportunity!$Q$1:$T$542,3,FALSE) -> 2.2222222e-08 | AN1100: =VLOOKUP($U1100,[2]Standard_Opportunity!$Q$1:$T$542,4,FALSE) -> 0 | AO1100: =SUM(AL1100:AN1100) -> 1 | AP1100: =SUMPRODUCT($AL$1:$AN$1,AL1100:AN1100) -> 0.064625 | AQ1100: =(1+AP1100)^(1/12)-1 -> 0.0052321924 | AR1100: 0 | AS1100: =IF(AR1100=0,0,SUMPRODUCT($AL$3:$AN$3,AL1100:AN1100)) -> 0 | AT1100: =(1+AS1100)^(1/12)-1 -> 0 | AU1100: =SUMPRODUCT($AL$2:$AN$2,AL1100:AN1100) -> 0.0025 | AV1100: =(1+AU1100)^(1/12)-1 -> 0.000208095
... A1629: Lifecycle | B1629: Opportunity | C1629: =A1629&"_"&B1629&"_"&D1629 -> Lifecycle_Opportunity_0 | D1629: 0 | E1629: =VLOOKUP($D1629,'[2]LC Opportunity'!$Q$2:$U$542,2,FALSE) -> 0.128 | F1629: =VLOOKUP($D1629,'[2]LC Opportunity'!$Q$2:$U$542,3,FALSE) -> 0.371 | G1629: =VLOOKUP($D1629,'[2]LC Opportunity'!$Q$2:$U$542,4,FALSE) -> 0.501 | H1629: =VLOOKUP($D1629,'[2]LC Opportunity'!$Q$2:$U$542,5,FALSE) -> 0 | I1629: =SUM(E1629:H1629) -> 1 | J1629: =SUMPRODUCT($E$1:$H$1,E1629:H1629) -> 0.0552263 | K1629: =(1+J1629)^(1/12)-1 -> 0.0044896523 | L1629: 0 | M1629: =IF($L1629=0,0,SUMPRODUCT($E$3:$H$3,E1629:H1629)) -> 0 | N1629: =1-(1-M1629)^(1/12) -> 0 | O1629: =SUMPRODUCT($E$2:$H$2,E1629:H1629) -> 0.0061033 | P1629: =1-(1-O1629)^(1/12) -> 0.00051003666 | R1629: Autopilot | S1629: Opportunity | T1629: =R1629&"_"&S1629&"_"&U1629 -> Autopilot_Opportunity_0 | U1629: 0 | V1629: =VLOOKUP($U1629,'[2]AP Opportunity'!$Q$1:$T$542,2,FALSE) -> 0.22222222 | W1629: =VLOOKUP($U1629,'[2]AP Opportunity'!$Q$1:$T$542,3,FALSE) -> 0.77777778 | X1629: =VLOOKUP($U1629,'[2]AP Opportunity'!$Q$1:$T$542,4,FALSE) -> 0 | Y1629: =SUM(V1629:X1629) -> 1 | Z1629: =SUMPRODUCT($V$1:$X$1,V1629:X1629) -> 0.0543 | AA1629: =(1+Z1629)^(1/12)-1 -> 0.0044161425 | AB1629: 1 | AC1629: =IF($AB1629=0,0,SUMPRODUCT($V$3:$X$3,V1629:X1629)) -> 0.0069444444 | AD1629: =1-(1-AC1629)^(1/12) -> 0.00058055386 | AE1629: =SUMPRODUCT($V$2:$X$2,V1629:X1629) -> 0.0025 | AF1629: =1-(1-AE1629)^(1/12) -> 0.00020857243 | AH1629: Lifecycle | AI1629: Opportunity | AJ1629: =AH1629&"_"&AI1629&"_"&AK1629 -> Lifecycle_Opportunity_0 | AK1629: 0 | AL1629: =VLOOKUP($U1629,[2]Standard_Opportunity!$Q$1:$T$542,2,FALSE) -> 0.22222222 | AM1629: =VLOOKUP($U1629,[2]Standard_Opportunity!$Q$1:$T$542,3,FALSE) -> 0.77777778 | AN1629: =VLOOKUP($U1629,[2]Standard_Opportunity!$Q$1:$T$542,4,FALSE) -> 0 | AO1629: =SUM(AL1629:AN1629) -> 1 | AP1629: =SUMPRODUCT($AL$1:$AN$1,AL1629:AN1629) -> 0.0543 | AQ1629: =(1+AP1629)^(1/12)-1 -> 0.0044161425 | AR1629: 0 | AS1629: =IF(AR1629=0,0,SUMPRODUCT($AL$3:$AN$3,AL1629:AN1629)) -> 0 | AT1629: =(1+AS1629)^(1/12)-1 -> 0 | AU1629: =SUMPRODUCT($AL$2:$AN$2,AL1629:AN1629) -> 0.0025 | AV1629: =(1+AU1629)^(1/12)-1 -> 0.000208095

Sheet SRP
F1: =IF(OR(AND(SUM(F4:R4)>0,S4<>1),AND(SUM(F9:R9)>0,S9<>1),AND(SUM(F13:R13)>0,S13<>1)),"Total Fund Percents not equal to 100% For DIY Investment Strategy","")
A3: Select Product | B3: AVC PRSA? | C3: No | E3: DIY Investment Strategy | F3: =IF(Investment_Strategy="DIY",Parameters!$C$48,"") -> Allianz Strategy Select 30 | G3: =IF(Investment_Strategy="DIY",Parameters!$C$49,"") -> Allianz Strategy Select 50 | H3: =IF(Investment_Strategy="DIY",Parameters!$C$50,"") -> Allianz Strategy Select 75 | I3: =IF(AND(Investment_Strategy="DIY",Investment_Strategy_Sub1 <>"Standard"),Parameters!$C$51,"") -> Allianz Best Styles Global Equity SRI | J3: =IF(Investment_Strategy="DIY",Parameters!$C$52,"") -> Allianz Advanced Fixed Income Short Duration | K3: =IF(AND(Investment_Strategy="DIY",Investment_Strategy_Sub1 <>"Standard"),Parameters!$C$53,"") -> Allianz Advanced Fixed Income Euro | L3: =IF(AND(Investment_Strategy="DIY",Investment_Strategy_Sub1 <>"Standard"),Parameters!$C$54,"") -> Allianz Dynamic Multi Asset Strategy SRI 75 | M3: =IF(AND(Investment_Strategy="DIY",Investment_Strategy_Sub1 <>"Standard"),Parameters!$C$55,"") -> Allianz Dynamic Multi Asset Strategy SRI 50 | N3: =IF(AND(Investment_Strategy="DIY",Investment_Strategy_Sub1 <>"Standard"),Parameters!$C$56,"") -> Allianz Dynamic Multi Asset Strategy SRI 15 | O3: =IF(AND(Investment_Strategy="DIY"),Parameters!$C$57,"") -> HSBC EURO STOXX 50 UCITS ETF | P3: =IF(AND(Investment_Strategy="DIY"),Parameters!$C$58,"") -> HSBC MSCI World UCITS ETF | Q3: =IF(AND(Investment_Strategy="DIY"),Parameters!$C$59,"") -> HSBC S&P 500 UCITS ETF | R3: =IF(Investment_Strategy="DIY",Parameters!$C$60,"") -> Allianz Euro Cash | S3: Annual Rate | T3: Monthly Rate
B4: Product Version | C4: B | E4: % invested (Opening funds) | F4: 1 | S4: =SUM(F4:R4) -> 1 | U4: =IF(OR(AND(SUM(F4:R4)>0,S4<>1),AND(SUM(F9:R9)>0,S9<>1),AND(SUM(F13:R13)>0,S13<>1)),"Check","")
B5: Type | C5: 3. Non-Standard | E5: Rate of Return (Opening Funds) | F5: =IF(F$3="","",VLOOKUP(F$3,Rates_of_Return,2,FALSE)) -> 0.05135 | G5: =IF(G$3="","",VLOOKUP(G$3,Rates_of_Return,2,FALSE)) -> 0.05725 | H5: =IF(H$3="","",VLOOKUP(H$3,Rates_of_Return,2,FALSE)) -> 0.064625 | I5: =IF(I$3="","",VLOOKUP(I$3,Rates_of_Return,2,FALSE)) -> 0.072 | J5: =IF(J$3="","",VLOOKUP(J$3,Rates_of_Return,2,FALSE)) -> 0.0425 | K5: =IF(K$3="","",VLOOKUP(K$3,Rates_of_Return,2,FALSE)) -> 0.0425 | L5: =IF(L$3="","",VLOOKUP(L$3,Rates_of_Return,2,FALSE)) -> 0.064625 | M5: =IF(M$3="","",VLOOKUP(M$3,Rates_of_Return,2,FALSE)) -> 0.05725 | ... R5: =IF(R$3="","",VLOOKUP(R$3,Rates_of_Return,2,FALSE)) -> 0.032 | S5: =SUMPRODUCT($F$4:$R$4,$F5:$R5) -> 0.05135 | T5: =(1+S5)^(1/12)-1 -> 0.0041816398
B6: Investment Strategy | C6: DIY | E6: External Management Charge (Opening Funds) | F6: =IF(F$3="","",VLOOKUP(F$3,External_Man_Chrge,3,FALSE)) -> 0.0025 | G6: =IF(G$3="","",VLOOKUP(G$3,External_Man_Chrge,3,FALSE)) -> 0.0025 | H6: =IF(H$3="","",VLOOKUP(H$3,External_Man_Chrge,3,FALSE)) -> 0.0025 | I6: =IF(I$3="","",VLOOKUP(I$3,External_Man_Chrge,3,FALSE)) -> 0.005 | J6: =IF(J$3="","",VLOOKUP(J$3,External_Man_Chrge,3,FALSE)) -> 0.0024 | K6: =IF(K$3="","",VLOOKUP(K$3,External_Man_Chrge,3,FALSE)) -> 0.0028 | L6: =IF(L$3="","",VLOOKUP(L$3,External_Man_Chrge,3,FALSE)) -> 0.0072 | M6: =IF(M$3="","",VLOOKUP(M$3,External_Man_Chrge,3,FALSE)) -> 0.0067 | ... R6: =IF(R$3="","",VLOOKUP(R$3,External_Man_Chrge,3,FALSE)) -> 0.0018 | S6: =SUMPRODUCT($F$4:$R$4,$F6:$R6) -> 0.0025 | T6: =1-(1-S6)^(1/12) -> 0.00020857243
B7: Sub Category 1 | C7: =IF(RIGHT(Product_Type,12)="Non-Standard","Non-Standard","Standard") -> Non-Standard | E7: If Guarantee | F7: Yes | G7: No | H7: No
B8: Sub Category 2 | C8: NiL | E8: Guarantee Charge | F8: =IF(F$3="","",IF(F$7="Yes",VLOOKUP(F$3,Gtee_Chrge,2,FALSE),"")) -> 0.0065 | G8: =IF(G$3="","",IF(G$7="Yes",VLOOKUP(G$3,Gtee_Chrge,2,FALSE),"")) | H8: =IF(H$3="","",IF(H$7="Yes",VLOOKUP(H$3,Gtee_Chrge,2,FALSE),"")) | S8: =SUMPRODUCT($F$4:$R$4,$F8:$R8) -> 0.0065 | T8: =1-(1-S8)^(1/12) -> 0.00054328712
E9: SP Premiums (Fund Splits %) | H9: 1 | S9: =SUM(F9:R9) -> 1
